Workbook

Sheet Tender Data
A1: REPORT_DATE | B1: RECORD_ID | C1: TENDER_ID | D1: PUBLICATION_DATE | E1: CLOSING_DATE | F1: CLOSING_TIME | G1: TENDER_TYPE | H1: TENDER_DESCRIPTION | I1: TENDER_SOURCE | J1: DEPARTMENT | K1: PROVINCE | L1: ESUBMISSION | M1: CATEGORY | N1: IS_THERE_A_BRIEFING_SESSION | O1: BRIEFING_DATE | P1: COMPULSORY_BRIEFING | Q1: BRIEFING_SESSION_VENUE | R1: LINK | S1: SOE | T1: COST_OF_SALES_ESTIMATE | U1: CAPABILITY_AVAILABLE | V1: CAPABILITY_GROUP | W1: REQUIREMENTS
A2: 46163 | B2: 192 | C2: RFQ/OBP026/2026/27 | D2: 46160 | E2: 46168 | F2: 12:00 | G2: Request for Quotation | H2: Appointment of a service provider to Upgrade Kaspersky Security Center and End Node Anti-Virus | I2: ETENDERS.GOV.ZA | J2: Onderstepoort Biological Products Limited | K2: Gauteng | L2: No | M2: Services: Professional | N2: No | O2: N/A | P2: No | Q2: N/A | R2: https://www.etenders.gov.za/home/Download/?blobName=22c59f90-f466-44ed-98b2-de07b0485ccc.pdf&downloadedFileName=Solicitation%20ID%20RFQ_OBP026_2026_27%20Request%20for%20Quote%20May%2018%202026%20(1).pdf
A3: 46163 | B3: 191 | C3: ECR/RISK/01/05/2026 | D3: 46160 | E3: 46164 | F3: 12:00 | G3: Request for Quotation | H3: APPOINTMENT OF A SERVICE PROVIDER FOR CALIBRATION AND TRANSPORTATION OF MARK X MACHINES | I3: ETENDERS.GOV.ZA | J3: Passenger Rail Agency of South Africa | K3: Eastern Cape | L3: No | M3: Services: General | N3: Yes | O3: N/A | P3: Yes | Q3: N/A | R3: https://www.etenders.gov.za/home/Download/?blobName=92d5a67d-a91f-4ab5-a075-681ae3ec000e.pdf&downloadedFileName=RFQ%20Risk%20Calibration%20-%20Mark%20X%20Machines.pdf
A4: 46163 | B4: 190 | C4: RFQJW0053SM2026 | D4: 46160 | E4: 46167 | F4: 16:00 | G4: Request for Quotation | H4: Service of meter test equipment at Flow Lab, Ffennel Road Depot | I4: ETENDERS.GOV.ZA | J4: Johannesburg Water | K4: Gauteng | L4: No | M4: Other service activities | N4: No | O4: N/A | P4: No | Q4: N/A | R4: https://www.etenders.gov.za/home/Download/?blobName=2a227aab-ab2d-4962-9ff9-02cdcc1e8b3b.pdf&downloadedFileName=RFQJW0053SM2026%20%E2%80%93%20Service%20of%20meter%20test%20equipment%20at%20Flow%20Lab,%20Ffennell%20Road%20Depot.pdf
A5: 46163 | B5: 189 | C5: NKO 12/2026 | D5: 46160 | E5: 46198 | F5: 12:00 | G5: Request for Bid(Open-Tender) | H5: APPOINTMENT OF A SERVICE PROVIDER FOR THE SUPPLY AND DELIVERY OF TRANSPORT SERVICES TO NKOMAZI LOCAL MUNICIPALITY FOR A PERIOD OF THIRTY-SIX (36) MONTHS | I5: ETENDERS.GOV.ZA | J5: Nkomazi Local Municipality | K5: Mpumalanga | L5: No | M5: Transportation and storage | N5: Yes | O5: 46168 | P5: No | Q5: Municipal Town Hall (Kobwa), Fish Eagle, Malalane | R5: https://www.etenders.gov.za/home/Download/?blobName=e076bf5d-c128-4aeb-bb78-a1529e662e4c.pdf&downloadedFileName=Transport%20(5).pdf
A6: 46163 | B6: 188 | C6: 2026/081 | D6: 46160 | E6: 46191 | F6: 12:00 | G6: Request for Bid(Open-Tender) | H6: APPOINTMENT OF PANEL OF 10 (TEN) PROFESSIONAL SERVICE PROVIDERS FOR IMPLEMENTATION OF UTHUKELA DISTRICT MUNICIPALITY SECTION 63 MINISTERIAL DIRECTIVE FOR A PERIOD OF THREE (3) YEARS. | I6: ETENDERS.GOV.ZA | J6: Umgeni Water | K6: National | L6: No | M6: Services: Professional | N6: Yes | O6: 46171 | P6: Yes | Q6: uMngeni-uThukela Water, Richards Bay Regional Office, Cnr, South Central Arterial & Battery Bank Ric | R6: https://www.etenders.gov.za/home/Download/?blobName=2da0cf9c-b4b6-40e6-807a-8c16c6033212.pdf&downloadedFileName=2026-081%20Attachment%20for%20e-portal%20advert.pdf
A7: 46163 | B7: 187 | C7: SECU 26/010 | D7: 46160 | E7: 46163 | F7: 11:00 | G7: Request for Quotation | H7: DEWETSDORP, HOUSE NUMBER 21, VOORTREKKER STREET: RENDERING OF SECURITY SERVICES ON A MONTH-TO-MONTH BASIS FOR A PERIOD NOT EXCEEDING SIX (6) MONTHS | I7: ETENDERS.GOV.ZA | J7: Public Works | K7: Free State | L7: No | M7: Security and investigation activities | N7: No | O7: N/A | P7: No | Q7: N/A | R7: https://www.etenders.gov.za/home/Download/?blobName=d4077650-9f17-4113-9f64-519872f2bd1e.pdf&downloadedFileName=SECU%2026-010%20DOCUMENT.pdf
A8: 46163 | B8: 186 | C8: IFA/CONTRACTOR/TMT/EC/2026/1 | D8: 46160 | E8: 46181 | F8: 11:00 | G8: Expression of interest | H8: INVITATION FOR AN EOI TO REGISTER ON TMT INFRASTRUCTURE FRAMEWORK AGREEMENT FOR A PERIOD OF 3 YEARS FROM THE CONSTRUCTION INDUSTRY DEVELOPMENT BOARD (CIDB) REGISTERED CONTRACTORS IN THE FOLLOWING CLASS OF WORKS CATEGORIES • GB - General Building • CE - Civil Engineering • ME - Mechanical Engineering • EB - Electrical installations for buildings • SO - Water supply and drainage for buildings (wet services, plumbing) • SQ - Steel security fencing or precast concrete | I8: ETENDERS.GOV.ZA | J8: THE MVULA TRUST | K8: Eastern Cape | L8: No | M8: Construction | N8: No | O8: N/A | P8: No | Q8: N/A | R8: https://www.etenders.gov.za/home/Download/?blobName=f8e54a24-0a99-4221-860c-8f26cd506c32.pdf&downloadedFileName=Expression%20of%20Interest%20for%20Contractors.pdf
A9: 46163 | B9: 185 | C9: E2922GXMPKUS- | D9: 46160 | E9: 46174 | F9: 10:00 | G9: Request for Quotation | H9: Supply and Delivery of Spares (Boiler spares) for Replenishment at Kusile Power Station (Once-off) | I9: ETENDERS.GOV.ZA | J9: ESKOM | K9: Mpumalanga | L9: No | M9: Supplies: General | N9: Yes | O9: N/A | P9: Yes | Q9: MSTEAM | R9: https://www.etenders.gov.za/home/Download/?blobName=bc1c5767-4b41-4902-b7ed-6a93ee8cfcab.pdf&downloadedFileName=TES%20Boiler%20Spares%2025.03.2026.pdf
A10: 46163 | B10: 184 | C10: LPT/QUT 004/2025 | D10: 46160 | E10: 46178 | F10: 11:00 | G10: Request for Quotation | H10: FUMIGATION AND RODENT CONTROL SERVICES FOR LIMPOPO PROVINCIAL TREASURY DEPARTMENTAL BUILDINGS/FACILITIES | I10: ETENDERS.GOV.ZA | J10: Limpopo - Provincial Treasury | K10: Limpopo | L10: No | M10: Services: Building | N10: Yes | O10: 46170 | P10: Yes | Q10: 46 Hans van Rensburg Street, Polokwane Limpopo 0699 | R10: https://www.etenders.gov.za/home/Download/?blobName=cd49ef16-8d72-4481-a265-78272a3b88dc.pdf&downloadedFileName=LPT%20QUT%20004%202026%20FUMIGATION%20SERVICES.pdf
A11: 46163 | B11: 183 | C11: WTE-2608ES | D11: 46160 | E11: 46178 | F11: 11:00 | G11: Request for Quotation | H11: APPOINTMENT OF A PROFESSIONAL SERVICE PROVIDER TO CONDUCT OCCUPATIONAL HEALTH AND SAFETY(OHS) AUDITS FOR THE DEPARTMENT OF WATER AND SANITATION: EASTERN OPERATIONS | I11: ETENDERS.GOV.ZA | J11: Water and Sanitation | K11: KwaZulu-Natal | L11: No | M11: Human health activities | N11: No | O11: N/A | P11: No | Q11: N/A | R11: https://www.etenders.gov.za/home/Download/?blobName=f221b56e-d030-40c6-bf75-e69f391c06d2.pdf&downloadedFileName=General%20Conditions%20of%20Contract-%20Inclusion%20of%20par%2034%20CIBD.pdf
A12: 46163 | B12: 182 | C12: IHLM/187/2025-26/COMM | D12: 46160 | E12: 46169 | F12: 12:00 | G12: Request for Quotation | H12: PROCUREMENT OF TORCHES, PEPPER SPRAYS WITH POUCHES | I12: ETENDERS.GOV.ZA | J12: Ingquza Hill Local Municipality | K12: Eastern Cape | L12: No | M12: Supplies: General | N12: No | O12: N/A | P12: No | Q12: N/A | R12: https://www.etenders.gov.za/home/Download/?blobName=162fb755-f198-4e7f-94a8-67060b6f9513.pdf&downloadedFileName=BID%20DOCUMENT%20FOR%20PROCUREMENT%20OF%20TORCHES,%20PEPPER%20SPRAYS%20WITH%20POUCHES.pdf
A13: 46163 | B13: 181 | C13: ULM-INFR 015/26 | D13: 46160 | E13: 46178 | F13: 12:00 | G13: Request for Bid(Open-Tender) | H13: Completion of Ntlangwini Low Level Bridge ( Ward 18) | I13: ETENDERS.GOV.ZA | J13: Umzimkhulu Local Municipality | K13: KwaZulu-Natal | L13: No | M13: Construction | N13: Yes | O13: 46171 | P13: Yes | Q13: uMzimkhulu Municipality Makhosini Building Boardroom,247 Mzimkhulu Mlonyana Street, uMzimkhulu 3297. | R13: https://www.etenders.gov.za/home/Download/?blobName=203b6931-43bc-4491-862e-253edee2e4e5.pdf&downloadedFileName=18-05-2026%20TENDER%20ADVERT%20-COMPLETION%20OF%20NTLANGWINI%20LOW%20LEVEL%20BRIDGE%20(%20WARD%2018).pdf
A14: 46163 | B14: 180 | C14: bm28/25/26 | D14: 46160 | E14: 46191 | F14: 11:00 | G14: Request for Bid(Open-Tender) | H14: APPOINTMENT OF SERVICE PROVIDER TO SUPPLY, INSTALLATION AND MAINTENACE OF TELEPHONE SYSTEM FOR A PERIOD OF 36 MONTHS | I14: ETENDERS.GOV.ZA | J14: Blouberg Municipality | K14: Limpopo | L14: No | M14: Information and communication | N14: No | O14: N/A | P14: No | Q14: N/A | R14: https://www.etenders.gov.za/home/Download/?blobName=b2094674-6233-489e-a3b7-332f3b36fba3.pdf&downloadedFileName=Telephone%20tender%20advert05-18-2026-151330.pdf
A15: 46163 | B15: 179 | C15: SASSA:01-26-FAC-NW | D15: 46160 | E15: 46183 | F15: 11:00 | G15: Request for Proposal | H15: LEASING OF OFFICE ACCOMODATION FOR SASSA NORTH-WEST REGION FOR A PERIOD OF FIVE (05) YEARS IN MOGWASE CBD | I15: ETENDERS.GOV.ZA | J15: South African Social Security Agency | K15: North West | L15: No | M15: Accommodation | N15: No | O15: N/A | P15: No | Q15: N/A | R15: https://www.etenders.gov.za/home/Download/?blobName=f54073e2-f0f6-41ac-a1e8-f92d314404e5.pdf&downloadedFileName=SASSA%2001-26-FAC-NW%20Leasing%20of%20office%20accomodation%20for%20SASSA%20North-West%20Region%20for%20period%20of%20five(05)%20years%20in%20Mogwase%20CBD.pdf
A16: 46163 | B16: 178 | C16: ELM 25-26/05/03 | D16: 46160 | E16: 46188 | F16: 12:00 | G16: Request for Bid(Open-Tender) | H16: Provision of payroll and human resource management system with support and maintenance over a period of 60 months (5 years) for Emakhazeni Local Municipality | I16: ETENDERS.GOV.ZA | J16: EMAKHAZENI LOCAL MUNICIPALITY | K16: Mpumalanga | L16: No | M16: Services: Professional | N16: No | O16: N/A | P16: No | Q16: N/A | R16: https://www.etenders.gov.za/home/Download/?blobName=12471aa7-ecdc-4af2-8616-f4de6c55e8fb.pdf&downloadedFileName=Tender%20Data%20-%20HRM%20&%20Payroll.pdf
A17: 46163 | B17: 177 | C17: RFQJW112NS26 | D17: 46160 | E17: 46167 | F17: 16:00 | G17: Request for Quotation | H17: Supply, installation and Training of Wastewater Mathematical Modelling Software | I17: ETENDERS.GOV.ZA | J17: Johannesburg Water | K17: Gauteng | L17: No | M17: Other professional, scientific and technical activities | N17: No | O17: N/A | P17: No | Q17: N/A | R17: https://www.etenders.gov.za/home/Download/?blobName=74f6f1e7-37a7-470b-88e6-bcd8d7ce16d9.pdf&downloadedFileName=RFQJW112NS26-Supply,%20installation%20and%20Training%20of%20Wastewater%20Mathematical%20Modelling%20Software(18-25%20MAY.pdf
A18: 46163 | B18: 176 | C18: RFP/2021/001419 | D18: 46160 | E18: 46174 | F18: 11:00 | G18: Request for Quotation | H18: THE APPOINTMENT OF A SERVICE PROVIDER TO PROVIDE ENTERPRISE ARCHITECTURE SERVICES TO THE PSETA | I18: ETENDERS.GOV.ZA | J18: Public Service Sector Education and Training Authority | K18: Gauteng | L18: No | M18: Services: Professional | N18: Yes | O18: 46167 | P18: Yes | Q18: BRIEFING SESSION: MICROSOFT TEAMS | R18: https://www.etenders.gov.za/home/Download/?blobName=934c0a04-1f5c-4809-8486-429e03b0fd75.zip&downloadedFileName=RFP2021001419-ARCHITECTURE%20ENTERPRISE.zip
A19: 46163 | B19: 175 | C19: PR10115864 | D19: 46160 | E19: 46164 | F19: 14:00 | G19: Request for Quotation | H19: The Road Accident Fund (RAF) wishes to appoint a suitable service provider for the Design, Layout, Copy Editing, Proofreading, Interactive PDF Booklet and Printing of 2026 – 2027 Annual Performance Plan (APP). | I19: ETENDERS.GOV.ZA | J19: Road Accident Fund | K19: Gauteng | L19: No | M19: Services: Professional | N19: No | O19: N/A | P19: No | Q19: N/A | R19: https://www.etenders.gov.za/home/Download/?blobName=1b13318d-5497-4736-bc84-e088c2fcfd42.pdf&downloadedFileName=Annexure%20A%20-%20Security%20Measures.pdf
A20: 46163 | B20: 174 | C20: RFQ 144 | D20: 46160 | E20: 46168 | F20: 12:00 | G20: Request for Quotation | H20: Provision For Editing and Project management Training services | I20: ETENDERS.GOV.ZA | J20: Special Investigation Unit | K20: Gauteng | L20: No | M20: Education | N20: No | O20: N/A | P20: No | Q20: N/A | R20: https://www.etenders.gov.za/home/Download/?blobName=f42418e1-dc39-4aa2-a1f4-d7bd8b093194.pdf&downloadedFileName=RFQ%20144.pdf
A21: 46163 | B21: 173 | C21: SAST/RFQ/2026 -2027/360 | D21: 46160 | E21: 46171 | F21: 11:00 | G21: Request for Quotation | H21: THE APPOINTMENT OF A SERVICE PROVIDER FOR THE FUMIGATION SERVICES FOR THE PERIOD OF 36 MONTHS (Re-Issue) | I21: ETENDERS.GOV.ZA | J21: The South African State Theatre | K21: Gauteng | L21: No | M21: Other service activities | N21: No | O21: N/A | P21: No | Q21: N/A | R21: https://www.etenders.gov.za/home/Download/?blobName=af7ec8b4-a635-4f1f-b054-b6227a6fdfd8.pdf&downloadedFileName=SAST-RFQ-2026-360%20-%20Fumigation%20services%20for%2036%20months%20-%20Re-issue.pdf
A22: 46163 | B22: 172 | C22: NRWDI/ICT/2026-04 | D22: 46160 | E22: 46163 | F22: 17:00 | G22: Request for Quotation | H22: SUPPLY AND DELIVERY OF FIVE (5) LAPTOPS | I22: ETENDERS.GOV.ZA | J22: National Radioactive Waste Disposal Institute (NRWDI) | K22: North West | L22: No | M22: Supplies: Computer Equipment | N22: No | O22: N/A | P22: No | Q22: N/A | R22: https://www.etenders.gov.za/home/Download/?blobName=8c411dcd-7d36-4515-8b50-6acb7fa28e5c.pdf&downloadedFileName=NRWDI%20RFQ%20for%20Laptops.pdf
A23: 46163 | B23: 171 | C23: E1046GCDMPKUSR2C | D23: 46160 | E23: 46203 | F23: 11:00 | G23: Request for Bid(Open-Tender) | H23: Notification of cancellation_ E1046GCDMPKUSR2_ Wetland Offset at Kusile Power Station 60 Year ADF Project | I23: ETENDERS.GOV.ZA | J23: ESKOM | K23: Mpumalanga | L23: No | M23: Civil engineering | N23: No | O23: N/A | P23: No | Q23: N/A | R23: https://www.etenders.gov.za/home/Download/?blobName=cfc813e9-a278-4058-ae2c-61f53b9bd1e2.pdf&downloadedFileName=Tender%20Cancellation%20Letter%20Template%20-%20Wetland%20Offset.pdf
A24: 46163 | B24: 170 | C24: RFQ-PPECB/ GRABOUW-MAIN /04-26 | D24: 46160 | E24: 46178 | F24: 16:00 | G24: Request for Quotation | H24: THE PROVISION OF GENERAL MAINTENANCE SERVICES FOR THE GRABOUW OFFICE | I24: ETENDERS.GOV.ZA | J24: Perishable Products Export Control Board | K24: Western Cape | L24: No | M24: Services: General | N24: Yes | O24: 46170 | P24: Yes | Q24: 7 Bosbou Avenue, Grabouw, 7160 | R24: https://www.etenders.gov.za/home/Download/?blobName=74d3b7fb-505c-4cfa-9d15-97d1241ba161.pdf&downloadedFileName=RFQ%20Grabouw.pdf
A25: 46163 | B25: 169 | C25: FOSPHB-RFP-09-26/27 | D25: 46160 | E25: 46175 | F25: 12:00 | G25: Request for Proposal | H25: FOSPHB-RFP-09-26/27 REQUEST FOR PROPOSAL [RFP] ELECTRICAL SHUTDOWN WORK 2026 | I25: ETENDERS.GOV.ZA | J25: Industrial Development Corporation of South Africa Limited | K25: Limpopo | L25: No | M25: Supplies: General | N25: Yes | O25: 46163 | P25: Yes | Q25: Microsoft Teams | R25: https://www.etenders.gov.za/home/Download/?blobName=f4f34f2a-01e6-4807-9d1e-b44fb00243fc.zip&downloadedFileName=FOSPHB-RFP-09-2627-ELECTRICAL%20SHUTDOWN%20WORK%202026.zip
A26: 46163 | B26: 168 | C26: NLC2026-004 | D26: 46160 | E26: 46184 | F26: 11:00 | G26: Request for Proposal | H26: TERMS OF REFERENCE FOR THE APPOINTMENT OF SERVICE PROVIDER FOR THE PROVISION OF SPECIALISED TECHNICAL SYBRIN DEVELOPMENT RESOURCES FOR THE ENHANCEMENT OF THE THUTHUKA GRANTS MANAGEMENT SYSTEM FOR A PERIOD OF THREE YEARS. | I26: ETENDERS.GOV.ZA | J26: National Lotteries Commission | K26: National | L26: No | M26: Information service activities | N26: Yes | O26: 46171 | P26: Yes | Q26: Block D, Htfield Gardens, Corner Hilda and Arcadia Street. Hatfield | R26: https://www.etenders.gov.za/home/Download/?blobName=2697f098-25db-45ad-9f20-f9529cb2cfa9.xlsx&downloadedFileName=Annexure%20C_Sybrin_Pricing_Schedule_25.03.2026.xlsx
A27: 46163 | B27: 167 | C27: RFB 3238-2026 ERP NO:374011 | D27: 46160 | E27: 46188 | F27: 11:00 | G27: Request for Bid(Open-Tender) | H27: REQUEST FOR BID FOR THE PROCUREMENT OF A MANAGEMENT ADMINISTRATION SYSTEM (MAS) FOR THE FOUR NURSING COLLEGE CAMPUSES OF THE WESTERN CAPE COLLEGE OF NURSING, INCLUDING COLLEGE OF EMERGENCY CARE, WESTERN CAPE DEPARTMENT OF HEALTH & WELLNESS FOR A 5-YEAR PERIOD. COMPULSORY VIRTUAL SESSION WILL BE HELD ON 02 JUNE 2026 AT 11H00AM. | I27: ETENDERS.GOV.ZA | J27: State Information Technology Agency | K27: Western Cape | L27: No | M27: Information service activities | N27: Yes | O27: 46175 | P27: Yes | Q27: https://teams.microsoft.com/meet/378792528716857?p=IWlNcmRCYBQHR55m4n | R27: https://www.etenders.gov.za/home/Download/?blobName=3df52742-d738-421a-bbfa-9b0f85a8e006.pdf&downloadedFileName=Annexure%205a-Invitation%20Letter-RFB%203238-2026%2018052026.pdf
A28: 46163 | B28: 166 | C28: PR10116177 | D28: 46160 | E28: 46164 | F28: 11:00 | G28: Request for Quotation | H28: The Road Accident Fund (RAF) wishes to appoint a suitable service provider to provide Ambulance Services for the RAF on the Road Roadshow in Bethlehem on 13 June 2026. | I28: ETENDERS.GOV.ZA | J28: Road Accident Fund | K28: Free State | L28: No | M28: Services: General | N28: No | O28: N/A | P28: No | Q28: N/A | R28: https://www.etenders.gov.za/home/Download/?blobName=c1913a2b-db57-436e-957c-fad403f66573.pdf&downloadedFileName=Standard%20Bidding%20Document%20(SDB)%204.pdf
A29: 46163 | B29: 165 | C29: WTE-2607ES | D29: 46160 | E29: 46178 | F29: 11:00 | G29: Request for Quotation | H29: SUPPLY AND DELIVERY OF PLUMBING, MECHANICAL & ELECTRICAL TOOLS TO MIDMAR DAM NEAR HOWICK TOWN | I29: ETENDERS.GOV.ZA | J29: Water and Sanitation | K29: KwaZulu-Natal | L29: No | M29: Supplies: General | N29: No | O29: N/A | P29: No | Q29: N/A | R29: https://www.etenders.gov.za/home/Download/?blobName=a2bbd5df-eba8-43c0-9b83-f6a3c043ab11.pdf&downloadedFileName=guidelines%20for%20local%20content.pdf
A30: 46163 | B30: 164 | C30: DQP 16/2026 LG | D30: 46160 | E30: 46167 | F30: 11:00 | G30: Request for Quotation | H30: APPOINTMENT OF A SERVICE PROVIDER TO CONDUCT TRAINING FOR 60 OFFICIALS MS WORD 1 & 2 AND 60 OFFICIALS MS EXCEL 1 & 2 | I30: ETENDERS.GOV.ZA | J30: Kwazulu Natal - Cooperative Governance and Traditional Affairs | K30: KwaZulu-Natal | L30: No | M30: Services: Professional | N30: No | O30: N/A | P30: No | Q30: N/A | R30: https://www.etenders.gov.za/home/Download/?blobName=a7c09eda-5625-47aa-a1c1-83ada59be118.pdf&downloadedFileName=DQP%20162026%20LG%20%E2%80%93%20REQA60188.pdf
A31: 46163 | B31: 163 | C31: RFQJS36SN26 | D31: 46160 | E31: 46167 | F31: 16:00 | G31: Request for Quotation | H31: Repair steps at unit 3 bioreactors and supply cordless drill kit set | I31: ETENDERS.GOV.ZA | J31: Johannesburg Water | K31: Gauteng | L31: No | M31: Other personal service activities | N31: Yes | O31: 46163 | P31: Yes | Q31: Northern Works , off Winnie Mandela Drive school Road Diepsloot | R31: https://www.etenders.gov.za/home/Download/?blobName=01f3ae46-cf5e-4f7d-8a13-fb32474ae03c.pdf&downloadedFileName=RFQJW36SN26.pdf
A32: 46163 | B32: 162 | C32: ASA 04/05/2026 | D32: 46160 | E32: 46167 | F32: 12:00 | G32: Request for Quotation | H32: Appointment of a service provider to assist with purchasing and delivery of kitchen surplus | I32: ETENDERS.GOV.ZA | J32: Agrément South Africa | K32: National | L32: No | M32: Food and beverage service activities | N32: No | O32: N/A | P32: No | Q32: N/A | R32: https://www.etenders.gov.za/home/Download/?blobName=9f1d413d-051c-4650-91b1-f732f4019189.pdf&downloadedFileName=Terms%20of%20Reference%20-%20Purchasing%20of%20Grocery.pdf
A33: 46163 | B33: 161 | C33: SASSA:01-26-CS-LP | D33: 46160 | E33: 46181 | F33: 11:00 | G33: Request for Proposal | H33: Acquisition of an office accommodation for SASSA Limpopo Regional Office and Capricon District Office ( Combined Space) for a period of five (5) years. | I33: ETENDERS.GOV.ZA | J33: South African Social Security Agency | K33: Limpopo | L33: No | M33: Accommodation | N33: Yes | O33: 46167 | P33: No | Q33: VIRTUAL(MICROSOFT TEAMS) | R33: https://www.etenders.gov.za/home/Download/?blobName=e6ca7df1-0195-4c12-bc30-86da7d3426cc.pdf&downloadedFileName=SASSA-01-26-CS-LP.pdf
A34: 46163 | B34: 160 | C34: RFP-HO-04-2026 | D34: 46160 | E34: 46169 | F34: 11:00 | G34: Request for Proposal | H34: Appointment of Labour Relations Retainer for a period of 36 months (3 years) | I34: ETENDERS.GOV.ZA | J34: South African Human Rights Commission | K34: Gauteng | L34: No | M34: Legal and accounting activities | N34: Yes | O34: 46163 | P34: No | Q34: https://teams.microsoft.com/meet/329382618243468?p=X3C11r21xltocSMwf2 | R34: https://www.etenders.gov.za/home/Download/?blobName=4c222714-27be-4b64-8d24-09434f1d8c57.pdf&downloadedFileName=RFP-HO-04-2026-%20Labour%20Relation%20Service%20Retainer-001.pdf
A35: 46163 | B35: 159 | C35: DQP 20/2026 LG | D35: 46160 | E35: 46167 | F35: 11:00 | G35: Request for Quotation | H35: APPOINTMENT OF A SERVICE PROVIDER TO CONDUCT TRAINING FOR 68 OFFICIALS ON PROJECT MANAGEMENT | I35: ETENDERS.GOV.ZA | J35: Kwazulu Natal - Cooperative Governance and Traditional Affairs | K35: KwaZulu-Natal | L35: No | M35: Services: Professional | N35: No | O35: N/A | P35: No | Q35: N/A | R35: https://www.etenders.gov.za/home/Download/?blobName=78f9b89e-032f-47af-8fde-a159a6714d1a.pdf&downloadedFileName=DQP%20202026%20LG%20%E2%80%93%20REQA60192.pdf
A36: 46163 | B36: 158 | C36: ZNT 01-26-27 | D36: 46160 | E36: 46195 | F36: 11:00 | G36: Request for Bid(Open-Tender) | H36: Appointment of a service provider for the supply and delivery of stationery items on a two (2) year period contract (24 months). | I36: ETENDERS.GOV.ZA | J36: Kwazulu Natal - Public Works (Head Office) | K36: KwaZulu-Natal | L36: No | M36: Supplies: Stationery/Printing | N36: No | O36: N/A | P36: No | Q36: N/A | R36: https://www.etenders.gov.za/home/Download/?blobName=82bde937-63ac-4671-99b1-e77920f0de37.pdf&downloadedFileName=ZNT%2001-26-27%20advert.pdf
A37: 46163 | B37: 157 | C37: OLT2128185 | D37: 46160 | E37: 46168 | F37: 10:00 | G37: Request for Proposal | H37: Purchase, collect and Remove Scrapped and contaminated petrol and diesel from Komati Power Station at Eskom Mpumalanga | I37: ETENDERS.GOV.ZA | J37: ESKOM | K37: Mpumalanga | L37: No | M37: Disposals: General | N37: No | O37: N/A | P37: No | Q37: N/A | R37: https://www.etenders.gov.za/home/Download/?blobName=0eee4ba2-7634-490b-a7b7-6157c9605577.pdf&downloadedFileName=Eskom%20life-saving%20rules.pdf
A38: 46163 | B38: 156 | C38: ATNS/RFQ12/05/2026/27/ATA_Fans_Hardrives | D38: 46160 | E38: 46163 | F38: 11:00 | G38: Request for Quotation | H38: APPOINTMENT OF A SERVICE PROVIDER FOR THE SUPPLY AND DELIVERY OF HARDRIVES AND COOLING FANS AT THE ATNS AVIATION TRAINING ACADEMY | I38: ETENDERS.GOV.ZA | J38: Air Traffic and Navigation Services Company Limited | K38: Gauteng | L38: No | M38: Supplies: Computer Equipment | N38: No | O38: N/A | P38: No | Q38: N/A | R38: https://www.etenders.gov.za/home/Download/?blobName=277073aa-62b7-4fb0-b755-cf2742cec093.pdf&downloadedFileName=ATA%20-%20RFQ%20for%20Supply%20and%20Delivery%20of%20Colling%20Fans%20and%20Hardrives.pdf
A39: 46163 | B39: 155 | C39: GKM 48-25/26 | D39: 46160 | E39: 46175 | F39: 12:00 | G39: Request for Bid(Open-Tender) | H39: APPOINTMENT OF A SERVICE PROVIDER FOR THE SUPPLY & DELIVERY OF A RIDE ON ROAD MARKING MACHINE WITH BOOSTER & TO PROVIDE TRAINING ON THE HANDLE & USE OF THE MACHINE | I39: ETENDERS.GOV.ZA | J39: Greater Kokstad Local Municipality | K39: KwaZulu-Natal | L39: No | M39: Supplies: General | N39: No | O39: N/A | P39: No | Q39: N/A | R39: https://www.etenders.gov.za/home/Download/?blobName=f4b095fe-ffd4-4c56-a00a-dfceef02c00c.pdf&downloadedFileName=TOR%20RIDE%20ON%20ROAD%20MARKING%20MACHINE.pdf
A40: 46163 | B40: 154 | C40: INF012605RFQ11 | D40: 46160 | E40: 46167 | F40: 11:00 | G40: Request for Quotation | H40: Supply and Deliver of Bottles and Corks - Western Cape - Stellenbosch | I40: ETENDERS.GOV.ZA | J40: Agricultural Research Council | K40: Western Cape | L40: No | M40: Supplies: General | N40: No | O40: N/A | P40: No | Q40: N/A | R40: https://www.etenders.gov.za/home/Download/?blobName=dfe76ef5-0e9c-4d39-abfa-223fb6d652b9.pdf&downloadedFileName=SPECS%20WINE%20BOTTLES%20AND%20CORKS%20INF012506RFQ11.pdf
A41: 46163 | B41: 153 | C41: 6000008276 | D41: 46160 | E41: 46170 | F41: 12:00 | G41: Request for Quotation | H41: REQUEST FOR QUOTATION FOR THE PROVISION OF PIT DEWATERING SERVICES AT VLAKFONTEIN MINE FOR A PERIOD OF FIVE (5) MONTHS. | I41: ETENDERS.GOV.ZA | J41: African Exploration Mining and Finance Corporation Soc Ltd | K41: Mpumalanga | L41: No | M41: Mining and quarrying | N41: No | O41: N/A | P41: No | Q41: N/A | R41: https://www.etenders.gov.za/home/Download/?blobName=50710f73-be2a-45af-9d59-5e5fa3af5a99.pdf&downloadedFileName=Request%20For%20Quotation%20RFQ_Pit%20dewatering%20for%20a%20period%20of%205months%2018-05-2026.pdf
A42: 46163 | B42: 152 | C42: FSDSD RFQ 064/2026 | D42: 46160 | E42: 46167 | F42: 11:00 | G42: Request for Quotation | H42: APPOINTMENT OF AN INDEPENDENT SUITABLE SERVICE PROVIDER TO CONDUCT TRAINING ON COMBINED ASSURANCE FOR 1 DAY ON A VIRTUAL PLATFORM (MS TEAMS) ON BEHALF OF DEPARTMENT OF SOCIAL DEVELOPMENT, FREE STATE | I42: ETENDERS.GOV.ZA | J42: Free State - Social Development | K42: Free State | L42: No | M42: Other service activities | N42: No | O42: N/A | P42: No | Q42: N/A | R42: https://www.etenders.gov.za/home/Download/?blobName=1e0de177-5042-4bca-854e-830e26a04386.pdf&downloadedFileName=FSDSD%20RFQ%20064%20IIASA%20TRAINING.pdf
A43: 46163 | B43: 151 | C43: 5/2/1/1/(2025-2026) 664 | D43: 46160 | E43: 46168 | F43: 11:00 | G43: Request for Quotation | H43: APPOINTMENT OF A SUITABLE AND QUALIFIED SERVICE PROVIDER TO PROVIDE THE DEPARTMENT OF AGRICULTURE ACCESS TO CONDUCT SECURITY/ PRE-EMPLOYMENT SCREENING FOR PERIOD OF 12 MONTHS | I43: ETENDERS.GOV.ZA | J43: National - Department of Agriculture | K43: National | L43: No | M43: Other service activities | N43: No | O43: N/A | P43: No | Q43: N/A | R43: https://www.etenders.gov.za/home/Download/?blobName=d4205b2e-1df2-4909-bae5-65c2a91351b5.pdf&downloadedFileName=FILE%20664%20NEW.pdf
A44: 46163 | B44: 150 | C44: Q12/1353 OF 25/26 | D44: 46160 | E44: 46169 | F44: 11:00 | G44: Request for Quotation | H44: APPOINTMENT OF SERVICE PROVIDER FOR THE SUPPLY AND INSTALLATION OF GAS BURNERS. | I44: ETENDERS.GOV.ZA | J44: Msunduzi Local Municipality | K44: KwaZulu-Natal | L44: No | M44: Electricity, gas, steam and air conditioning | N44: No | O44: N/A | P44: No | Q44: N/A | R44: https://www.etenders.gov.za/home/Download/?blobName=0911f351-8d14-48c4-9601-0cf42cf9a9b6.pdf&downloadedFileName=Q12-1353%20DOCUMENT.pdf
A45: 46163 | B45: 149 | C45: H004L2705RFP00039 | D45: 46160 | E45: 46175 | F45: 11:00 | G45: Request for Quotation | H45: APPOINTMENT OF A CONTRACTOR WITH CIDB GRADE 2 GB OR ABOVE FOR SUPPLY AND PROVISION OF MAINTENANCE AND REPAIRS ISSUES FOR THE CITY DEEP SATELLITE PORT HEALTH OFFICE. | I45: ETENDERS.GOV.ZA | J45: Border Management Authority | K45: Gauteng | L45: No | M45: Services: Building | N45: Yes | O45: 46168 | P45: Yes | Q45: TRANSNET BUILDING 13 ANGUS ROAD, JOHANNESBURG SOUTH 2197 | R45: https://www.etenders.gov.za/home/Download/?blobName=90d1cf7c-d26d-4faa-93a6-998bd9b288a7.pdf&downloadedFileName=QUOTE%20PACK%20-%20TENDER%20SPECIFICATION%20CITY%20DEEP%20JOHANNESBURG.pdf
A46: 46163 | B46: 148 | C46: PPA-122342 - TE/2026/05/1667/5424/RFQ | D46: 46160 | E46: 46188 | F46: 12:00 | G46: Request for Quotation | H46: THE REPLACEMENT OF TRANSLUCENT SHEETS AND BROKEN WINDOWS AT CONTAINER PARK, ELECTRICAL TRAINING CENTER AND PATTEN SHOP FOR FOE BUSINESS, BAY 1A-3, PATTER SHOP LIFT AREA AND SAND PLANT FOR FOUNDRY BUSINESS, BAY 40-45, BAY 39, BAY 25, LOCO- STORE, RM STORE AND LOCOMOTIVE MAIN BUILDING FOR LOCOMOTIVE BUSINESS, BAY 32-38-BAY 26 AND BAY 48-50 FOR WAGON MANUFACTURING BUSINESS, BAY46-47 AT WHEELS, BAY 9-13, RFR STORE WAGON STORE, BAY 13A OFFICES AND KITCHEN FOR WAGON BUILD BUSINESS, FOR A PERIOD OF ONE MONTH | I46: ETENDERS.GOV.ZA | J46: Transnet SOC Ltd | K46: Free State | L46: No | M46: Construction of buildings | N46: Yes | O46: 46168 | P46: Yes | Q46: BLOEMFONTEIN | R46: https://www.etenders.gov.za/home/Download/?blobName=cefcb4df-157b-4550-abf3-0ae13c5de134.pdf&downloadedFileName=ANNEXURE%20C%20Price%20Schedule%20of%20clear%20Perspex%20windowpanes%20and%20translucent%20sheets.pdf
A47: 46163 | B47: 147 | C47: E2062GXMPKUSEXTENSION | D47: 46160 | E47: 46167 | F47: 10:00 | G47: Request for Quotation | H47: Validity Extension - Supply and Delivery of Laboratory Chemicals and Consumables on an as and when basis for a period of 5 years at Kusile Power Station | I47: ETENDERS.GOV.ZA | J47: ESKOM | K47: Mpumalanga | L47: No | M47: Supplies: General | N47: No | O47: N/A | P47: No | Q47: N/A | R47: https://www.etenders.gov.za/home/Download/?blobName=611b8d4b-83d0-4b39-83ca-ba73ba712429.pdf&downloadedFileName=Letter%20to%20Extend%20validity%20period%20of%20Tender%20-%20Lab%20Chemicals.pdf
A48: 46163 | B48: 146 | C48: 30241/TNP/2026-27 | D48: 46160 | E48: 46168 | F48: 11:00 | G48: Request for Quotation | H48: APPOINTMENT OF A SERVICE PROVIDER FOR THE PROVISION OF SECURITY SERVICES AT THE TSITSIKAMMA SECTION OF GARDEN ROUTE NATIONAL PARK FOR A PERIOD OF 6 MONTHS ON A MONTH-TO-MONTH BASIS (30 DAY CANCELLATION PERIOD). | I48: ETENDERS.GOV.ZA | J48: South African National Parks | K48: Eastern Cape | L48: No | M48: Security and investigation activities | N48: Yes | O48: 46163 | P48: Yes | Q48: FORESTRY OFFICE, STORMSRIVER VILLAGE, STORMSRIVER, TSITSIKAMMA | R48: https://www.etenders.gov.za/home/Download/?blobName=0c881649-ec81-4d71-97b6-aa347848f8a8.pdf&downloadedFileName=RFQ%20-%2030241-TNP-2026-27.pdf
A49: 46163 | B49: 145 | C49: RFQJW0052SM2026 | D49: 46160 | E49: 46167 | F49: 16:00 | G49: Request for Quotation | H49: Supply, deliver and install high-precision floor scale with display | I49: ETENDERS.GOV.ZA | J49: Johannesburg Water | K49: Gauteng | L49: No | M49: Other service activities | N49: No | O49: N/A | P49: No | Q49: N/A | R49: https://www.etenders.gov.za/home/Download/?blobName=b495af31-2f2c-4351-8f33-91eb17594717.pdf&downloadedFileName=RFQJW0052SM2026%20%E2%80%93%20Supply,%20deliver%20and%20install%20high-precision%20floor%20scale%20with%20display.pdf
A50: 46163 | B50: 144 | C50: Iziko OCEO|RFQ 2026/05/05 | D50: 46160 | E50: 46168 | F50: 11:00 | G50: Request for Quotation | H50: Request For Quotation (RFQ) for the Design, Layout and Printing of Annual Report and Corporate Publications | I50: ETENDERS.GOV.ZA | J50: Iziko Museums of Cape Town | K50: Western Cape | L50: No | M50: Administrative and support activities | N50: No | O50: N/A | P50: No | Q50: N/A | R50: https://www.etenders.gov.za/home/Download/?blobName=237ad044-b02e-4c35-8399-bae303f168ee.pdf&downloadedFileName=FINAL_AR-RFQ%202026-27%20SO%20(002).pdf
A51: 46163 | B51: 143 | C51: RFQ 189 | D51: 46160 | E51: 46168 | F51: 12:00 | G51: Request for Quotation | H51: Provision For Media Training services. | I51: ETENDERS.GOV.ZA | J51: Special Investigation Unit | K51: Gauteng | L51: No | M51: Education | N51: No | O51: N/A | P51: No | Q51: N/A | R51: https://www.etenders.gov.za/home/Download/?blobName=faa4b81e-6b79-454d-8f0e-f6556d6218e5.pdf&downloadedFileName=RFQ%20189.pdf
A52: 46163 | B52: 142 | C52: NKO 04/2026 | D52: 46160 | E52: 46203 | F52: 12:00 | G52: Request for Bid(Open-Tender) | H52: APPOINTMENT OF A SERVICE PROVIDER FOR THE LEASING, SUPPLY, INSTALLATION, OPERATION AND MAINTENANCE OF MULTIFUNCTIONAL PRINTING EQUIPMENT AND AN AUTOMATED PRINT, FOLD AND SEAL SOLUTION FOR NKOMAZI LOCAL MUNICIPALITY FOR A PERIOD OF THIRTY-SIX (36) MONTHS | I52: ETENDERS.GOV.ZA | J52: Nkomazi Local Municipality | K52: Mpumalanga | L52: No | M52: Rental and leasing activities | N52: Yes | O52: 46168 | P52: Yes | Q52: Municipal Town Hall (Kobwa), Fish Eagle, Malalane | R52: https://www.etenders.gov.za/home/Download/?blobName=6a56f104-6b65-4012-b385-d54851568f58.pdf&downloadedFileName=Tender%20Multimedia%20Printers%202026.pdf
A53: 46163 | B53: 141 | C53: RFI/OBP001/2026/27 | D53: 46160 | E53: 46174 | F53: 15:00 | G53: Request for Information | H53: Request for Information regarding the Optimal Land-Use, Development Options, and Feasibility for House Numbers 16,17,25,27,28,30,31,32 and 33 Flip Fourie Street, Old Soutpan Road, Onderstepoort, Pretoria North. | I53: ETENDERS.GOV.ZA | J53: Onderstepoort Biological Products Limited | K53: Gauteng | L53: No | M53: Services: Professional | N53: Yes | O53: 46167 | P53: Yes | Q53: 100 Old Soutpan Rd Onderstepoort, Pretoria, 0110 | R53: https://www.etenders.gov.za/home/Download/?blobName=d257f26f-91af-4d67-89ea-2297b0133084.pdf&downloadedFileName=Solicitation%20ID%20RFI_OBP001_2026_27%20Request%20for%20Information%20May%2018%202026.pdf
A54: 46163 | B54: 140 | C54: DQP 17/2026 LG | D54: 46160 | E54: 46167 | F54: 11:00 | G54: Request for Quotation | H54: APPOINTMENT OF A SERVICE PROVIDER TO CONDUCT TRAINING FOR 20 OFFICIALS ON ADMINISTRATION SKILLS | I54: ETENDERS.GOV.ZA | J54: Kwazulu Natal - Cooperative Governance and Traditional Affairs | K54: KwaZulu-Natal | L54: No | M54: Services: Professional | N54: No | O54: N/A | P54: No | Q54: N/A | R54: https://www.etenders.gov.za/home/Download/?blobName=ef1ccffc-dfb3-44fd-8a77-89db8ccfe2a5.pdf&downloadedFileName=DQP%20172026%20LG%20%E2%80%93%20REQA60186.pdf
A55: 46163 | B55: 139 | C55: CSIR RFP 3730/01/06/2026 | D55: 46160 | E55: 46174 | F55: 16:30 | G55: Request for Proposal | H55: Request for Proposals (RFP) from Suitably Qualified SMMEs for the Provision of Technical Research and Development (R&D) Support in building Cyber Defence Capabilities | I55: ETENDERS.GOV.ZA | J55: Council for Scientific and Industrial Research (CSIR) | K55: National | L55: No | M55: Professional, scientific and technical activities | N55: No | O55: N/A | P55: No | Q55: N/A | R55: https://www.etenders.gov.za/home/Download/?blobName=aa7f6eb8-fd93-4a25-9a79-c65c2b0639c0.pdf&downloadedFileName=RFP%203730-01-06-2026%20-%20Cyber%20Defence%20Capabilities.pdf
A56: 46163 | B56: 138 | C56: E2919GXMPARN | D56: 46160 | E56: 46175 | F56: 10:00 | G56: Request for Bid(Open-Tender) | H56: The provision of subsidised meals, catering, cleaning services and maintenance of e-hospitality system and supply and delivery of beverages on ‘As when required at Arnot Power Station for a period of three (3) years | I56: ETENDERS.GOV.ZA | J56: ESKOM | K56: Mpumalanga | L56: No | M56: Other service activities | N56: Yes | O56: 46167 | P56: No | Q56: Msteams | R56: https://www.etenders.gov.za/home/Download/?blobName=80f8b56e-c034-4064-b31a-2f1486c3b5f7.pdf&downloadedFileName=NEC%20draft-%20Catering%20&%20Cleaning%20Service.Rev06-1-60.pdf
A57: 46163 | B57: 137 | C57: WTE1000CE | D57: 46160 | E57: 46175 | F57: 11:00 | G57: Request for Quotation | H57: MANUFACTURE, SUPPLY, DELIVERY, INSTALLATION, TEST COMMISSION AND ISSUE COC FOR A LOCAL CONTENT ULTRASONIC FLOW METER AT MTHATHA DAM MCC BUILDING PROJECT IN THE EASTERN CAPE PROVINCE. | I57: ETENDERS.GOV.ZA | J57: Water and Sanitation | K57: Eastern Cape | L57: No | M57: Repair and installation of machinery and equipment | N57: Yes | O57: 46168 | P57: Yes | Q57: Mthatha Dam, Construction East Offices in Ncise Village | R57: https://www.etenders.gov.za/home/Download/?blobName=9a7c91f1-a415-4377-a396-1d24001eef92.pdf&downloadedFileName=WTE1000CE.pdf
A58: 46163 | B58: 136 | C58: ELM 25- 26/05/05 | D58: 46160 | E58: 46188 | F58: 12:00 | G58: Request for Bid(Open-Tender) | H58: APPOINTMENT OF AN UCTIONEER FOR THE AUCTION OF MUNICIPAL ASSETS FOR A PERIOD OF 3 YEARS | I58: ETENDERS.GOV.ZA | J58: EMAKHAZENI LOCAL MUNICIPALITY | K58: Mpumalanga | L58: No | M58: Services: Professional | N58: No | O58: N/A | P58: No | Q58: N/A | R58: https://www.etenders.gov.za/home/Download/?blobName=edee94d9-215f-42fc-b370-f98064afe4b2.pdf&downloadedFileName=Tender%20Document%20%20-%20ELM%20Auction.pdf
A59: 46163 | B59: 135 | C59: SCMU5-26/27-0016 AMR INF | D59: 46160 | E59: 46191 | F59: 11:00 | G59: Request for Bid(Open-Tender) | H59: PROVISION OF PROFESSIONAL ARCHITECTURAL SERVICES AND PRINCIPAL AGENCY FOR THE CONSTRUCTION OF NEWLANDS CLINIC | I59: ETENDERS.GOV.ZA | J59: Eastern Cape - Roads and Public Works | K59: Eastern Cape | L59: No | M59: Architectural and engineering activities; technical testing and analysis | N59: No | O59: N/A | P59: No | Q59: N/A | R59: https://www.etenders.gov.za/home/Download/?blobName=e33ce730-8bed-42dd-af0e-e24b6275e1e5.pdf&downloadedFileName=SCMU5-26-27-0016%20AMR%20INF%20PROVISION%20OF%20PROFESSIONAL%20ARCHITECTURAL%20SERVICES%20AND%20PRINCIPAL%20AGENCY%20FOR%20THE%20CONSTRUCTION%20OF%20NEWLANDS%20CLINIC.pdf
A60: 46163 | B60: 134 | C60: RFQJW095TN26 | D60: 46160 | E60: 46167 | F60: 16:00 | G60: Request for Quotation | H60: RFQJW095TN26 - LAB REFRIGIRATORS | I60: ETENDERS.GOV.ZA | J60: Johannesburg Water | K60: Gauteng | L60: No | M60: Services: General | N60: No | O60: N/A | P60: No | Q60: N/A | R60: https://www.etenders.gov.za/home/Download/?blobName=3cd569b1-f5a9-4cf0-a595-bc91c40a0da8.pdf&downloadedFileName=RFQJW095TN26%20-%20LAB%20REFRIGIRATORS.pdf
A61: 46163 | B61: 133 | C61: POS9676 | D61: 46160 | E61: 46167 | F61: 09:00 | G61: Request for Quotation | H61: REQUEST FOR QUOTATION – DOCUSIGN RENEWAL | I61: ETENDERS.GOV.ZA | J61: Technology Innovation Agency | K61: National | L61: No | M61: Information and communication | N61: No | O61: N/A | P61: No | Q61: N/A | R61: https://www.etenders.gov.za/home/Download/?blobName=2e15839c-814f-4a3b-b38c-b7cbc0f672e9.docx&downloadedFileName=POS9767.docx
A62: 46163 | B62: 132 | C62: NCREGIONUNIT-18052026 | D62: 46160 | E62: 46178 | F62: 12:00 | G62: Request for Quotation | H62: REQUEST FOR QUOTATION OF THE IDT NORTHERN CAPE OFFICE SIGNAGE/BRANDING. | I62: ETENDERS.GOV.ZA | J62: Independent Development Trust | K62: Gauteng | L62: No | M62: Supplies: Stationery/Printing | N62: Yes | O62: N/A | P62: Yes | Q62: 13 Bishop Avenue Labram Kimberly 8301 | R62: https://www.etenders.gov.za/home/Download/?blobName=d7bd67e8-fc02-4dd6-b117-bcea1d8721f4.pdf&downloadedFileName=NCREGIONUNIT-18052026.pdf
A63: 46163 | B63: 131 | C63: MLRF217/26 | D63: 46160 | E63: 46182 | F63: 11:00 | G63: Request for Bid(Open-Tender) | H63: THE APPOINTMENT OF A SERVICE PROVIDER AS AN INDEPENDENT ENVIRONMENTAL CONTROL OFFICER (“ECO”) BY THE MLRF IN COMPLIANCE WITH THE STIPULATIONS IN THE ENVIRONMENTAL AUTHORISATION (“EA”) AND THE ENVIRONMENTAL MANAGEMENT PROGRAMME (“EMPr”) FOR THE SEA-BASED AQUACULTURE DEVELOPMENT ZONE (“ADZ”) LOCATED WITHIN SALDANHA BAY IN THE WESTERN CAPE, FOR A PERIOD OF THIRTY-SIX (36) | I63: ETENDERS.GOV.ZA | J63: Marine Living Resources Fund | K63: Western Cape | L63: No | M63: Services: Professional | N63: Yes | O63: 46169 | P63: Yes | Q63: MS Teams, link can be requested from MLRFTENDERS@DFFE.GOV.ZA | R63: https://www.etenders.gov.za/home/Download/?blobName=5bc381a4-8fbf-4950-8b5f-6c5fb613171e.pdf&downloadedFileName=MLRF217-26-%20Final%20Bid%20Pack.pdf
A64: 46163 | B64: 130 | C64: RFQJW37SN26 | D64: 46160 | E64: 46167 | F64: 16:00 | G64: Request for Quotation | H64: REPAIR UNIT 3 MODULE 2 CLARIFIER NUMBER 3 SCUM BOX AND STRAIGHTEN AND INSTALL BEND SCRAPPERS AND PLATES | I64: ETENDERS.GOV.ZA | J64: Johannesburg Water | K64: Gauteng | L64: No | M64: Other service activities | N64: Yes | O64: 46163 | P64: Yes | Q64: Northern Works , off Winnie Mandela Drive school Road Diepsloot | R64: https://www.etenders.gov.za/home/Download/?blobName=e0712b5e-711f-4a14-ac57-a0637633a696.pdf&downloadedFileName=UNIT%203%20MODULE%202%20CLARIFIER%203%20SCUM%20BOX%20REPAIR.pdf
A65: 46163 | B65: 129 | C65: 0010565668 | D65: 46160 | E65: 46182 | F65: 11:00 | G65: Request for Bid(Open-Tender) | H65: Tamper-evident sealing tape | I65: ETENDERS.GOV.ZA | J65: Electoral Commission (IEC) | K65: National | L65: No | M65: Supplies: General | N65: Yes | O65: 46169 | P65: No | Q65: Riverside Office Park,Election House, 1303 Heuwel Avenue, Centurion | R65: https://www.etenders.gov.za/home/Download/?blobName=46d841a0-4246-442b-a089-f51ba1623b40.pdf&downloadedFileName=0010565668%20Tamper%20Evident%20Sealing%20Tape.pdf
A66: 46163 | B66: 128 | C66: DQP 21/2026 LG | D66: 46161 | E66: 46169 | F66: 11:00 | G66: Request for Quotation | H66: APPOINTMENT OF A SERVICE PROVIDER TO CONDUCT TRAINING FOR 20 COGTA OFFICIALS TO ATTEND THE CONTACT SESSION OF RISK MANAGEMENT COURSE PHYSICAL IN-HOUSE TRAINING | I66: ETENDERS.GOV.ZA | J66: Kwazulu Natal - Cooperative Governance and Traditional Affairs | K66: KwaZulu-Natal | L66: No | M66: Services: Professional | N66: No | O66: N/A | P66: No | Q66: N/A | R66: https://www.etenders.gov.za/home/Download/?blobName=559b692f-2527-4e4b-9e07-461d867c0fc5.pdf&downloadedFileName=DQP%20212026%20LG%20%E2%80%93%20REQA60193.pdf
A67: 46163 | B67: 127 | C67: JCPZ/RFQ/FM90/2025 | D67: 46161 | E67: 46168 | F67: 12:00 | G67: Request for Quotation | H67: Pest Control for JCPZ Depots | I67: ETENDERS.GOV.ZA | J67: Johannesburg City Parks and Zoo | K67: National | L67: No | M67: Other service activities | N67: No | O67: N/A | P67: No | Q67: N/A | R67: https://www.etenders.gov.za/home/Download/?blobName=c712dc0f-1816-4323-ad76-3a74928ce0b8.pdf&downloadedFileName=JCPZ-RFQ-FM90-2025.pdf
A68: 46163 | B68: 126 | C68: SCMR 01/04/03R | D68: 46161 | E68: 46167 | F68: 18:00 | G68: Request for Proposal | H68: APPOINTMENT OF A SERVICE PROVIDER TO PROVIDE SURVEY DEVELOPMENT, ANALYSIS SERVICES AND FOCUS GROUPS ON THE EFFECTIVENESS OF THE APPROVED FLEXIBLE WORKING CONDITIONS GUIDELINES IN THE PRESIDENCY OFFICES (PRETORIA, CAPE TOWN AND DURBAN) FOR A PERIOD OF TWO (2) MONTHS | I68: ETENDERS.GOV.ZA | J68: The Presidency | K68: Gauteng | L68: No | M68: Administrative and support activities | N68: Yes | O68: 46163 | P68: No | Q68: Meeting ID: 335 728 261 511 226 Passcode: Ph9Tm7H7 | R68: https://www.etenders.gov.za/home/Download/?blobName=edba7b9a-c6ce-45c2-a40e-48c0a37d663c.pdf&downloadedFileName=TOR%20Flexible%20Working%20Conditions%20Guidelines.pdf
A69: 46163 | B69: 125 | C69: FTM/T29/25/26 | D69: 46161 | E69: 46204 | F69: 12:00 | G69: Request for Bid(Open-Tender) | H69: Appointment of a service provider for Closure of Burgersfort Landfill Site for a period of thirty-six (36) months. | I69: ETENDERS.GOV.ZA | J69: Fetakgomo Tubatse Local Municipality | K69: Limpopo | L69: No | M69: Construction | N69: No | O69: N/A | P69: No | Q69: N/A | R69: https://www.etenders.gov.za/home/Download/?blobName=00ba3775-fd0e-4c96-827d-290e90729d41.pdf&downloadedFileName=Advert%2018%20May%202026.pdf
A70: 46163 | B70: 124 | C70: E2803GXMPKOMBids | D70: 46161 | E70: 46192 | F70: 10:00 | G70: Request for Bid(Open-Tender) | H70: Publication of Names of Bidders in Respect of Advertised Competitive Bids - Provision of Subsidized Meals (Catering service) at Komati Power Station | I70: ETENDERS.GOV.ZA | J70: ESKOM | K70: Mpumalanga | L70: No | M70: Food and beverage service activities | N70: No | O70: N/A | P70: No | Q70: N/A | R70: https://www.etenders.gov.za/home/Download/?blobName=d786dc4f-8281-41f4-8563-582c4738c95f.pdf&downloadedFileName=Publication%20of%20Names%20of%20Bidders%20iro%20advertised%20Competitive%20Bids.pdf
A71: 46163 | B71: 123 | C71: EDUMT02/2026/27 | D71: 46161 | E71: 46182 | F71: 12:00 | G71: Request for Bid(Open-Tender) | H71: CONSTRUCTION OF GULEZ PEDESTRIAN BRIDGE IN WARD 04 | I71: ETENDERS.GOV.ZA | J71: eDumbe Local Municipality | K71: KwaZulu-Natal | L71: No | M71: Civil engineering | N71: Yes | O71: 46167 | P71: Yes | Q71: eDumbe Town Hall | R71: https://www.etenders.gov.za/home/Download/?blobName=4f99308a-f26c-4b3e-9750-3ac882cb5acf.pdf&downloadedFileName=MIG%20ADVERT%202026%2027.pdf
A72: 46163 | B72: 122 | C72: ELM 25-26/05/02 | D72: 46161 | E72: 46188 | F72: 12:00 | G72: Request for Bid(Open-Tender) | H72: Provision of security services for Emakhazeni Local Municipality’s offices, plants and workshops for a period of 36 months | I72: ETENDERS.GOV.ZA | J72: EMAKHAZENI LOCAL MUNICIPALITY | K72: Mpumalanga | L72: No | M72: Services: Functional (Including Cleaning and Security Services) | N72: No | O72: N/A | P72: No | Q72: N/A | R72: https://www.etenders.gov.za/home/Download/?blobName=9f0c4ccb-641a-4094-8767-c7b7c4c84122.pdf&downloadedFileName=Tender%20Data%20-%20Security%20Services.pdf
A73: 46163 | B73: 121 | C73: E2505NTCSAMWPR | D73: 46161 | E73: 46182 | F73: 10:00 | G73: Request for Bid(Open-Tender) | H73: LM CONTAINER REFURBISHMENT PHASE 1 AT ZANDSPRUIT RADIO STATION. | I73: ETENDERS.GOV.ZA | J73: Eskom National Transmission Company of South Africa | K73: Limpopo | L73: No | M73: Construction | N73: Yes | O73: N/A | P73: Yes | Q73: Ms teams | R73: https://www.etenders.gov.za/home/Download/?blobName=1f72c720-e288-487b-b4c3-a030fb20c4f0.zip&downloadedFileName=Container%20Document%20to%20the%20market.zip
A74: 46163 | B74: 120 | C74: RFQ2085 | D74: 46161 | E74: 46167 | F74: 11:00 | G74: Request for Quotation | H74: APPOINTMENT OF AN ACCREDITED SERVICE PROVIDER TO PROVIDE AUCTION SERVICES TO THE MHSC FOR A PERIOD OF 12 MONTHS | I74: ETENDERS.GOV.ZA | J74: Mine Health and Safety Council | K74: National | L74: No | M74: Services: General | N74: No | O74: N/A | P74: No | Q74: N/A | R74: https://www.etenders.gov.za/home/Download/?blobName=e1b9aa94-99f4-4985-a5c9-76324c9d68e2.pdf&downloadedFileName=RFQ%202085.pdf
A75: 46163 | B75: 119 | C75: MLRF218/26 | D75: 46161 | E75: 46185 | F75: 11:00 | G75: Request for Bid(Open-Tender) | H75: THE APPOINTMENT OF A SERVICE PROVIDER AS AN INDEPENDENT ENVIRONMENTAL CONTROL OFFICER (“ECO”) BY THE MLRF IN COMPLIANCE WITH THE STIPULATIONS IN THE ENVIRONMENTAL AUTHORISATION (“EA”) AND THE ENVIRONMENTAL MANAGEMENT PROGRAMME (“EMPr”) FOR THE SEA-BASED AQUACULTURE DEVELOPMENT ZONE (“ADZ”) LOCATED WITHIN ALGOA BAY IN THE EASTERN CAPE, FOR A PERIOD OF THIRTY-SIX (36) MONTHS. | I75: ETENDERS.GOV.ZA | J75: Marine Living Resources Fund | K75: Eastern Cape | L75: No | M75: Services: Professional | N75: Yes | O75: 46176 | P75: Yes | Q75: MS Teams, link can be requested from MLRFTENDERS@DFFE.GOV.ZA | R75: https://www.etenders.gov.za/home/Download/?blobName=24b2bfa2-24fc-4f09-a264-9e4cce5afb09.pdf&downloadedFileName=MLRF218-26-%20Final%20Bid%20Pack.pdf
A76: 46163 | B76: 118 | C76: RFQJW0051SM2026 | D76: 46161 | E76: 46171 | F76: 16:00 | G76: Request for Quotation | H76: SUPPLY AND INSPECTION OF CCTV CAMERAS FOR SEWER LINE AT ENNERDALE DEPOT | I76: ETENDERS.GOV.ZA | J76: Johannesburg Water | K76: Gauteng | L76: No | M76: Other service activities | N76: Yes | O76: 46164 | P76: Yes | Q76: Johannesburg water Ennerdale Depot, no 2 James street | R76: https://www.etenders.gov.za/home/Download/?blobName=9c92deea-e82d-494b-997a-68570b6e8aa9.pdf&downloadedFileName=RFQJW0051SM2026%20%E2%80%93%20SUPPLY%20AND%20INSPECTION%20OF%20CCTV%20CAMERAS%20FOR%20SEWER%20LINE%20AT%20ENNERDALE%20DEPOT.pdf
A77: 46163 | B77: 117 | C77: E2914GXLPMED | D77: 46161 | E77: 46185 | F77: 10:00 | G77: Request for Quotation | H77: Occupational Hygiene Services for 60 Months (5 years) at Medupi Power Station | I77: ETENDERS.GOV.ZA | J77: ESKOM | K77: Northern Cape | L77: No | M77: Services: General | N77: Yes | O77: N/A | P77: Yes | Q77: MS Teams | R77: https://www.etenders.gov.za/home/Download/?blobName=4d5e6a85-c6ce-470f-87b0-11553d33eeae.docx&downloadedFileName=240-106084675%20%20Annexure%20C%203%20OHS%20Tender%20Evaluation%20Template%20(Low%20risk).docx
A78: 46163 | B78: 116 | C78: (NRCS 001-2026/2027) | D78: 46161 | E78: 46196 | F78: 11:00 | G78: Request for Bid(Open-Tender) | H78: APPOINTMENT OF SERVICE PROVIDERS TO PROVIDE OFFICE ACCOMMODATION BLOEMFONTEIN REGIONAL OFFICE, LEASE FOR A PERIOD OF 9 YEARS 11 MONTHS (NRCS 001-2026/2027) | I78: ETENDERS.GOV.ZA | J78: National Regulator for Compulsory Specifications | K78: Free State | L78: No | M78: Accommodation | N78: Yes | O78: 46177 | P78: No | Q78: https://teams.microsoft.com/meet/358288650446670?p=khCYRq7pFyiVB6EbZK | R78: https://www.etenders.gov.za/home/Download/?blobName=9a593aee-040d-4b9e-b66c-7d42800c9582.pdf&downloadedFileName=BLOEMFONTEIN%20OFFICE%20SPACE-%20TERMS%20OF%20REFERENCE%20-%20Advert.pdf
A79: 46163 | B79: 115 | C79: FTM/T28/25/26 | D79: 46161 | E79: 46196 | F79: 12:00 | G79: Request for Bid(Open-Tender) | H79: Appointment of a service provider for Supply, delivery and installation of Clear view fence in Mashifane township for a period of thirty-six (36) months. | I79: ETENDERS.GOV.ZA | J79: Fetakgomo Tubatse Local Municipality | K79: Limpopo | L79: No | M79: Construction | N79: No | O79: N/A | P79: No | Q79: N/A | R79: https://www.etenders.gov.za/home/Download/?blobName=6a5cf8fe-8b84-4360-85e5-f0cd98cbd87c.pdf&downloadedFileName=Advert%2018%20May%202026.pdf
A80: 46163 | B80: 114 | C80: NQULM69/25-26 | D80: 46161 | E80: 46190 | F80: 12:00 | G80: Request for Quotation | H80: APPOINTMENT OF A SERVICE PROVIDER FOR THE PROVISION OF A VEHICLE TRACKING DEVICE SYSTEM FOR A PERIOD OF 36 MONTHS | I80: ETENDERS.GOV.ZA | J80: Nquthu Local Municipality | K80: KwaZulu-Natal | L80: No | M80: Other service activities | N80: No | O80: N/A | P80: No | Q80: N/A | R80: https://www.etenders.gov.za/home/Download/?blobName=3e612a6e-20c5-47fe-a94f-ab88d226e78d.pdf&downloadedFileName=18%20MAY.pdf
A81: 46163 | B81: 113 | C81: 10024029 | D81: 46161 | E81: 46169 | F81: 11:00 | G81: Request for Quotation | H81: Hard case shell case QTY 4. Refer to the detailed attached specs. | I81: ETENDERS.GOV.ZA | J81: State Security Agency | K81: Gauteng | L81: No | M81: Supplies: General | N81: No | O81: N/A | P81: No | Q81: N/A | R81: https://www.etenders.gov.za/home/Download/?blobName=eea4e3ba-1e7b-4632-9c7b-80f95539c85f.pdf&downloadedFileName=RFQ%20Hard%20cases%20updated.pdf
A82: 46163 | B82: 112 | C82: 134/2026 | D82: 46161 | E82: 46192 | F82: 12:00 | G82: Request for Bid(Open-Tender) | H82: PHASE 4 OF 66 KV DOUBLE CIRCUIT OVERHEAD LINE | I82: ETENDERS.GOV.ZA | J82: Kouga Municipality | K82: Eastern Cape | L82: No | M82: Electricity, gas, steam and air conditioning | N82: Yes | O82: 46175 | P82: Yes | Q82: https://teams.microsoft.com/meet/344417045492097?p=0s7Tfvl1wGcoicplKp | R82: https://www.etenders.gov.za/home/Download/?blobName=c1b6fd0f-846a-4cdf-aceb-dc7622b0ed1b.pdf&downloadedFileName=Specification%20Tender%20Notice%20134-2026.pdf
A83: 46163 | B83: 111 | C83: MBDA EWS 15/25-26 | D83: 46161 | E83: 46192 | F83: 12:00 | G83: Request for Proposal | H83: REQUEST FOR PROPOSALS FOR EMPLOYEE WELLNESS SERVICES | I83: ETENDERS.GOV.ZA | J83: Mandela Bay Development Agency | K83: Eastern Cape | L83: No | M83: Services: Professional | N83: Yes | O83: 46169 | P83: Yes | Q83: https://teams.microsoft.com/meet/35950291662900?p=FtDffF8KVD3lyYtzYn | R83: https://www.etenders.gov.za/home/Download/?blobName=47f8cc1d-e0ee-4e27-8ee0-504b23c704da.pdf&downloadedFileName=Employee%20Wellness%20Services%20RFP.pdf
A84: 46163 | B84: 110 | C84: MPMAT11199GX00 | D84: 46161 | E84: 46195 | F84: 10:00 | G84: Request for Bid(Open-Tender) | H84: Provision of Vacuum Truck Services at Matla Power Station for a period of thirty-six months (36) - tender cancellation | I84: ETENDERS.GOV.ZA | J84: ESKOM | K84: Mpumalanga | L84: No | M84: Services: General | N84: No | O84: N/A | P84: No | Q84: N/A | R84: https://www.etenders.gov.za/home/Download/?blobName=f7fa297a-eb69-4574-85d6-c304dc59ed9b.pdf&downloadedFileName=Tender%20Cancellation%20Letter%20Template2%20-%20Vacuum%20trucks.pdf
A85: 46163 | B85: 109 | C85: IHLM-188/2025-26/MM'S | D85: 46161 | E85: 46168 | F85: 12:00 | G85: Request for Quotation | H85: VIP CATERING FOR 500 PEOPLE ATTENDING MPONDO REVOLT | I85: ETENDERS.GOV.ZA | J85: Ingquza Hill Local Municipality | K85: Eastern Cape | L85: No | M85: Services: General | N85: No | O85: N/A | P85: No | Q85: N/A | R85: https://www.etenders.gov.za/home/Download/?blobName=5ea45ae1-5a3d-46d5-9ae1-c6e77ca636ee.pdf&downloadedFileName=BID%20DOCUMENT%20FOR%20VIP%20CATERING%20FOR%20500%20PEOPLE%20ATTENDING%20MPONDO%20REVOLT%20docx.pdf
A86: 46163 | B86: 108 | C86: RLM15/2025/2026 | D86: 46161 | E86: 46174 | F86: 10:00 | G86: Request for Bid(Open-Tender) | H86: SUPPLY OF ASPHALT HOT MIX FOR A PERIOD OF 36 MONTHS – RICHMOND LM | I86: ETENDERS.GOV.ZA | J86: Richmond - KZ Local Municipality | K86: KwaZulu-Natal | L86: No | M86: Services: General | N86: Yes | O86: 46164 | P86: Yes | Q86: Richmond Council Chambers | R86: https://www.etenders.gov.za/home/Download/?blobName=c9884f45-65b7-4c98-a874-7dd4291a63ec.pdf&downloadedFileName=SUPPLY%20OF%20HOT%20MIX%20%20DOCUMENT%20FINAL%201520252026.pdf
A87: 46163 | B87: 107 | C87: E0426LSERI | D87: 46161 | E87: 46183 | F87: 10:00 | G87: Request for Bid(Open-Tender) | H87: PLANT HIRE – 34 TON TIPPER TRUCKS ON AN AS AN WHEN REQUIRED BASIS FOR A PERIOD OF 5 YEARS | I87: ETENDERS.GOV.ZA | J87: ESKOM | K87: National | L87: No | M87: Services: General | N87: Yes | O87: 46168 | P87: No | Q87: MS Teams | R87: https://www.etenders.gov.za/home/Download/?blobName=6975a3dc-8b0d-4087-be1a-567163f9dae4.zip&downloadedFileName=Docs%20for%20Adv%2034%20T0N.zip
A88: 46163 | B88: 106 | C88: E0526LSERI | D88: 46161 | E88: 46183 | F88: 10:00 | G88: Request for Bid(Open-Tender) | H88: PLANT HIRE – SUPER SUCKER TRUCKS ON AN AS AN WHEN REQUIRED BASIS FOR A PERIOD OF 5 YEARS | I88: ETENDERS.GOV.ZA | J88: ESKOM | K88: National | L88: No | M88: Services: General | N88: Yes | O88: N/A | P88: No | Q88: MS Teams | R88: https://www.etenders.gov.za/home/Download/?blobName=4896fd70-98e4-4825-af1f-cc31b3b9042b.zip&downloadedFileName=Docs%20for%20adv.zip
A89: 46163 | B89: 105 | C89: SASSA:02-26-CS-WC | D89: 46161 | E89: 46185 | F89: 11:00 | G89: Request for Proposal | H89: ACQUISITION OF OFFICE ACCOMODTION OF 1177.50M2 AND 12 PARING BAYS FOR SASSA WESTERN CAPE GUGULETHU LOCAL OFFICE FOR A PERIOD OF FIVE (5) YERS. | I89: ETENDERS.GOV.ZA | J89: South African Social Security Agency | K89: Western Cape | L89: No | M89: Accommodation | N89: No | O89: N/A | P89: No | Q89: N/A | R89: https://www.etenders.gov.za/home/Download/?blobName=ebf8f680-9d74-4ce5-bd53-d04eec654aed.pdf&downloadedFileName=SASSA-02-26-CS-WC.pdf
A90: 46163 | B90: 104 | C90: NQULM53/25-26 | D90: 46161 | E90: 46190 | F90: 12:00 | G90: Request for Quotation | H90: SERVICE PROVIDER TO DESIGN, DEVELOP, HOST, AND MAINTAIN AN OFFICIAL MUNICIPAL WEBSITE FOR A PERIOD OF 36 MONTHS | I90: ETENDERS.GOV.ZA | J90: Nquthu Local Municipality | K90: KwaZulu-Natal | L90: No | M90: Other personal service activities | N90: No | O90: N/A | P90: No | Q90: N/A | R90: https://www.etenders.gov.za/home/Download/?blobName=51484578-87f5-41cb-b7e0-f4713a92d79f.pdf&downloadedFileName=18%20MAY.pdf
A91: 46163 | B91: 103 | C91: 10024059/ 10024044 | D91: 46161 | E91: 46168 | F91: 11:00 | G91: Request for Quotation | H91: Abby Fine Reader Software | I91: ETENDERS.GOV.ZA | J91: State Security Agency | K91: Gauteng | L91: No | M91: Supplies: Computer Equipment | N91: No | O91: N/A | P91: No | Q91: N/A | R91: https://www.etenders.gov.za/home/Download/?blobName=2ebd8519-8044-4f75-a6a1-04cc464f95a8.pdf&downloadedFileName=RFQ%20Abby%20Fine%20reader.pdf
A92: 46163 | B92: 102 | C92: NQULM71/25-26 | D92: 46161 | E92: 46190 | F92: 12:00 | G92: Request for Quotation | H92: SERVICE PROVIDER TO OPERATE THE EXISTING CAR WASH FACILITY IN NQUTHU MUNICIPALITY | I92: ETENDERS.GOV.ZA | J92: Nquthu Local Municipality | K92: KwaZulu-Natal | L92: No | M92: Other service activities | N92: No | O92: N/A | P92: No | Q92: N/A | R92: https://www.etenders.gov.za/home/Download/?blobName=5a59e698-813c-47e6-b17e-8d13442b637a.pdf&downloadedFileName=18%20MAY.pdf
A93: 46163 | B93: 101 | C93: E2867CXMWP | D93: 46161 | E93: 46192 | F93: 10:00 | G93: Request for Quotation | H93: The Provision of Employee Assistance Programme (EAP) Services for Eskom Employees and their immediate families for a period of Five years (60 months) on an “as and when required” basis. | I93: ETENDERS.GOV.ZA | J93: ESKOM | K93: Gauteng | L93: No | M93: Services: Professional | N93: Yes | O93: N/A | P93: Yes | Q93: MS Teams | R93: https://www.etenders.gov.za/home/Download/?blobName=cce70372-f8be-47a4-aa60-251effcaaab5.pdf&downloadedFileName=Invitation%20to%20Tender%20for%20the%20Provision%20of%20a%20Comprehensive%20Employee%20Assistance%20Programme%20(EAP)%20transaction.pdf
A94: 46163 | B94: 100 | C94: NERSA/2627/CSM/PCP/BID004 | D94: 46161 | E94: 46185 | F94: 11:00 | G94: Request for Proposal | H94: THE APPOINTMENT OF A SERVICE PROVIDER TO ASSIST THE NATIONAL ENERGY REGULATOR WITH THE PRODUCTION OF CORPORATE PUBLICATIONS FOR A PERIOD OF THREE (3) YEARS. | I94: ETENDERS.GOV.ZA | J94: National Energy Regulator of South Africa | K94: National | L94: No | M94: Services: Professional | N94: Yes | O94: 46168 | P94: No | Q94: MS TEAMS | R94: https://www.etenders.gov.za/home/Download/?blobName=ee63f60a-9f55-4c37-83bf-0789aeff3a72.pdf&downloadedFileName=BID%20DOCUMENT_%20NERSA-2627-CSM-PCP-BID004.pdf
A95: 46163 | B95: 99 | C95: FTM/T27/25/26 | D95: 46161 | E95: 46204 | F95: 12:00 | G95: Request for Bid(Open-Tender) | H95: Appointment of a Panel of Implementation of Digitalization and Modernization of Information Communication Technology and Environment Solutions for a period of thirty-six (36) months. | I95: ETENDERS.GOV.ZA | J95: Fetakgomo Tubatse Local Municipality | K95: Limpopo | L95: No | M95: Information and communication | N95: No | O95: N/A | P95: No | Q95: N/A | R95: https://www.etenders.gov.za/home/Download/?blobName=a75bf076-4abb-47f0-952c-6785df66b0eb.pdf&downloadedFileName=Advert%2018%20May%202026.pdf
A96: 46163 | B96: 98 | C96: LDE/B01/2026/27 | D96: 46161 | E96: 46182 | F96: 11:00 | G96: Request for Bid(Open-Tender) | H96: INVITATION OF SERVICE PROVIDERS FOR THE ESTABLISHMENT OF A PANEL OF CONTRACTORS FOR INFRASTRUCTURE GENERAL BUILDING WORKS GRADE 6GB ALL PUBLIC SCHOOLS, INSTITUTIONS AND OFFICES, LIMPOPO DEPARTMENT OF EDUCATION, FOR THE PERIOD OF THREE (03) YEARS | I96: ETENDERS.GOV.ZA | J96: Limpopo - Education | K96: Limpopo | L96: No | M96: Construction | N96: No | O96: N/A | P96: No | Q96: N/A | R96: https://www.etenders.gov.za/home/Download/?blobName=5bcbc27f-744a-4322-b0ec-eb68572ead15.pdf&downloadedFileName=LDEB01-2026-27.pdf
A97: 46163 | B97: 97 | C97: NQULM67/25-26 | D97: 46161 | E97: 46190 | F97: 12:00 | G97: Request for Quotation | H97: MUNICIPAL FLEET MAINTANANCE FOR A PERIOD OF 36 MONTHS | I97: ETENDERS.GOV.ZA | J97: Nquthu Local Municipality | K97: KwaZulu-Natal | L97: No | M97: Other service activities | N97: No | O97: N/A | P97: No | Q97: N/A | R97: https://www.etenders.gov.za/home/Download/?blobName=37ca14de-3fee-4c7c-9ba0-81e742389860.pdf&downloadedFileName=18%20MAY.pdf
A98: 46163 | B98: 96 | C98: SCMF 21/04/09R | D98: 46161 | E98: 46167 | F98: 18:00 | G98: Request for Proposal | H98: Appointment of the service provider to support and maintain the video conferencing system in the Presidency (boardrooms 108, 144, and 145) for a period of 3 years. | I98: ETENDERS.GOV.ZA | J98: The Presidency | K98: Gauteng | L98: No | M98: Administrative and support activities | N98: Yes | O98: 46163 | P98: Yes | Q98: Meeting ID: 331 140 622 845 223 Passcode: zc2Xb68w | R98: https://www.etenders.gov.za/home/Download/?blobName=fbfdfcc4-8490-4826-90c5-5dfabb1268ad.pdf&downloadedFileName=TORAppointment%20for%20service%20provider%20to%20provide%20vidoe%20conference%20support%20and%20maintenance%20in%20boardroom%20108%20144%20and%20145.pdf
A99: 46163 | B99: 95 | C99: DQP 14/2026 LG | D99: 46161 | E99: 46169 | F99: 11:00 | G99: Request for Quotation | H99: APPOINTMENT OF A SERVICE PROVIDER TO CONDUCT TRAINING FOR 18 OFFICIALS ON MONITORING AND EVALUATION TRAINING | I99: ETENDERS.GOV.ZA | J99: Kwazulu Natal - Cooperative Governance and Traditional Affairs | K99: KwaZulu-Natal | L99: No | M99: Services: Professional | N99: No | O99: N/A | P99: No | Q99: N/A | R99: https://www.etenders.gov.za/home/Download/?blobName=b9e8d8f9-68ca-43dd-aef0-03cd88e208a4.pdf&downloadedFileName=DQP%20142026%20LG%20%E2%80%93%20REQA60186.pdf
A100: 46163 | B100: 94 | C100: THEK/WANP/02/2026 | D100: 46161 | E100: 46182 | F100: 12:00 | G100: Request for Proposal | H100: THEKWINI TVET COLLEGE PRIMARY WIDE AREA NETWORK (6 CAMPUSES) FOR A PERIOD OF 5 YEARS | I100: ETENDERS.GOV.ZA | J100: Thekwini TVET College | K100: KwaZulu-Natal | L100: No | M100: Information and communication | N100: Yes | O100: 46168 | P100: Yes | Q100: THEKWINI TVET COLLEGE MELBOURNE CAMPUS, Crn SRDNEY & BLAKE RD, DALBRIDGE, SYDNEY ROAD, DURBAN,4001 | R100: https://www.etenders.gov.za/home/Download/?blobName=b30d44c1-be74-44b0-a45f-af337c965060.pdf&downloadedFileName=Advert%20for%20Primary%20WAN%20Tender%202026.pdf
...

Sheet Final
A1: Source | B1: Number of New Tenders | C1: ICT Tenders | D1: RFQs
A2: Report Date | B2: (T) 20/05/2026
A3: eTenders (All) | B3: =COUNTA('Tender Data'!J:J)-1 -> 192 | C3: =COUNTIF('Tender Data'!M:M,"Information service activities")+COUNTIF('Tender Data'!M:M,"Information and communication") -> 12 | D3: =COUNTIF('Tender Data'!G:G,"Request for Quotation") -> 89
A4: Eskom | B4: =COUNTIF('Tender Data'!J:J,"ESKOM") -> 18 | C4: =COUNTIFS('Tender Data'!M:M,"Information service activities",'Tender Data'!J:J,"ESKOM")+COUNTIFS('Tender Data'!M:M,"Information and communication",'Tender Data'!J:J,"ESKOM") -> 0 | D4: =COUNTIFS('Tender Data'!J:J,"ESKOM",'Tender Data'!G:G,"Request for Quotation") -> 5
A5: SITA | B5: =COUNTIF('Tender Data'!J:J,"State Information Technology Agency") -> 1 | C5: =COUNTIFS('Tender Data'!M:M,"Information service activities",'Tender Data'!J:J,"State Information Technology Agency")+COUNTIFS('Tender Data'!M:M,"Information and communication",'Tender Data'!J:J,"State Information Technology Agency") -> 1 | D5: =COUNTIFS('Tender Data'!J:J,"State Information Technology Agency",'Tender Data'!G:G,"Request for Quotation") -> 0
A6: Transnet | B6: =COUNTIF('Tender Data'!J:J,"Transnet*") -> 4 | C6: =COUNTIFS('Tender Data'!M:M,"Information service activities",'Tender Data'!J:J,"Transnet*")+COUNTIFS('Tender Data'!M:M,"Information and communication",'Tender Data'!J:J,"Transnet*") -> 0 | D6: =COUNTIFS('Tender Data'!J:J,"Transnet*",'Tender Data'!G:G,"Request for Quotation") -> 1
A7: JPC | B7: =COUNTIF('Tender Data'!J:J,"*Joburg Property*") -> 0 | C7: =COUNTIFS('Tender Data'!M:M,"Information service activities",'Tender Data'!J:J,"*Joburg Property*")+COUNTIFS('Tender Data'!M:M,"Information and communication",'Tender Data'!J:J,"*Joburg Property*") -> 0 | D7: =COUNTIFS('Tender Data'!J:J,"*Joburg Property*",'Tender Data'!G:G,"Request for Quotation") -> 0
A8: Matatiele LM | B8: =COUNTIF('Tender Data'!J:J,"Matatiele Local Municipality") -> 0 | C8: =COUNTIFS('Tender Data'!M:M,"Information service activities",'Tender Data'!J:J,"Matatiele Local Municipality")+COUNTIFS('Tender Data'!M:M,"Information and communication",'Tender Data'!J:J,"Matatiele Local Municipality") -> 0 | D8: =COUNTIFS('Tender Data'!J:J,"Matatiele Local Municipality",'Tender Data'!G:G,"Request for Quotation") -> 0
A9: Ntabankulu LM | B9: =COUNTIF('Tender Data'!J:J,"Ntabankulu Local Municipality") -> 0 | C9: =COUNTIFS('Tender Data'!M:M,"Information service activities",'Tender Data'!J:J,"Ntabankulu Local Municipality")+COUNTIFS('Tender Data'!M:M,"Information and communication",'Tender Data'!J:J,"Ntabankulu Local Municipality") -> 0 | D9: =COUNTIFS('Tender Data'!J:J,"Ntabankulu Local Municipality",'Tender Data'!G:G,"Request for Quotation") -> 0
A10: Umzimvubu LM | B10: =COUNTIF('Tender Data'!J:J,"Umzimvubu Local Municipality") -> 0 | C10: =COUNTIFS('Tender Data'!M:M,"Information service activities",'Tender Data'!J:J,"Umzimvubu Local Municipality")+COUNTIFS('Tender Data'!M:M,"Information and communication",'Tender Data'!J:J,"Umzimvubu Local Municipality") -> 0 | D10: =COUNTIFS('Tender Data'!J:J,"Umzimvubu Local Municipality",'Tender Data'!G:G,"Request for Quotation") -> 0
A11: Winnie Mandela LM | B11: =COUNTIF('Tender Data'!J:J,"Winnie Madikizela*") -> 0 | C11: =COUNTIFS('Tender Data'!M:M,"Information service activities",'Tender Data'!J:J,"Winnie Madikizela*")+COUNTIFS('Tender Data'!M:M,"Information and communication",'Tender Data'!J:J,"Winnie Madikizela*") -> 0 | D11: =COUNTIFS('Tender Data'!J:J,"Winnie Madikizela*",'Tender Data'!G:G,"Request for Quotation") -> 0
A12: Mnquma LM | B12: =COUNTIF('Tender Data'!J:J,"Mnquma Local Municipality") -> 0 | C12: =COUNTIFS('Tender Data'!M:M,"Information service activities",'Tender Data'!J:J,"Mnquma Local Municipality")+COUNTIFS('Tender Data'!M:M,"Information and communication",'Tender Data'!J:J,"Mnquma Local Municipality") -> 0 | D12: =COUNTIFS('Tender Data'!J:J,"Mnquma Local Municipality",'Tender Data'!G:G,"Request for Quotation") -> 0
A13: Great Kei LM | B13: =COUNTIF('Tender Data'!J:J,"Great Kei Local Municipality") -> 0 | C13: =COUNTIFS('Tender Data'!M:M,"Information service activities",'Tender Data'!J:J,"Great Kei Local Municipality")+COUNTIFS('Tender Data'!M:M,"Information and communication",'Tender Data'!J:J,"Great Kei Local Municipality") -> 0 | D13: =COUNTIFS('Tender Data'!J:J,"Great Kei Local Municipality",'Tender Data'!G:G,"Request for Quotation") -> 0
A14: Amahlathi LM | B14: =COUNTIF('Tender Data'!J:J,"Amahlathi Local Municipality") -> 0 | C14: =COUNTIFS('Tender Data'!M:M,"Information service activities",'Tender Data'!J:J,"Amahlathi Local Municipality")+COUNTIFS('Tender Data'!M:M,"Information and communication",'Tender Data'!J:J,"Amahlathi Local Municipality") -> 0 | D14: =COUNTIFS('Tender Data'!J:J,"Amahlathi Local Municipality",'Tender Data'!G:G,"Request for Quotation") -> 0
A15: Raymond Mhlaba LM | B15: =COUNTIF('Tender Data'!J:J,"Raymond Mhlaba Local Municipality") -> 0 | C15: =COUNTIFS('Tender Data'!M:M,"Information service activities",'Tender Data'!J:J,"Raymond Mhlaba Local Municipality")+COUNTIFS('Tender Data'!M:M,"Information and communication",'Tender Data'!J:J,"Raymond Mhlaba Local Municipality") -> 0 | D15: =COUNTIFS('Tender Data'!J:J,"Raymond Mhlaba Local Municipality",'Tender Data'!G:G,"Request for Quotation") -> 0
A16: JOSHCO | B16: =COUNTIF('Tender Data'!J:J,"*Johannesburg Social Housing*") -> 0 | C16: =COUNTIFS('Tender Data'!M:M,"Information service activities",'Tender Data'!J:J,"*Johannesburg Social Housing*")+COUNTIFS('Tender Data'!M:M,"Information and communication",'Tender Data'!J:J,"*Johannesburg Social Housing*") -> 0 | D16: =COUNTIFS('Tender Data'!J:J,"*Johannesburg Social Housing*",'Tender Data'!G:G,"Request for Quotation") -> 0
A17: GPL | B17: =COUNTIF('Tender Data'!J:J,"Gauteng Provincial Legislature") -> 0 | C17: =COUNTIFS('Tender Data'!M:M,"Information service activities",'Tender Data'!J:J,"Gauteng Provincial Legislature")+COUNTIFS('Tender Data'!M:M,"Information and communication",'Tender Data'!J:J,"Gauteng Provincial Legislature") -> 0 | D17: =COUNTIFS('Tender Data'!J:J,"Gauteng Provincial Legislature",'Tender Data'!G:G,"Request for Quotation") -> 0
A18: RAF | B18: =COUNTIF('Tender Data'!J:J,"Road Accident Fund") -> 3 | C18: =COUNTIFS('Tender Data'!M:M,"Information service activities",'Tender Data'!J:J,"Road Accident Fund")+COUNTIFS('Tender Data'!M:M,"Information and communication",'Tender Data'!J:J,"Road Accident Fund") -> 1 | D18: =COUNTIFS('Tender Data'!J:J,"Road Accident Fund",'Tender Data'!G:G,"Request for Quotation") -> 2
A19: MM Trading Company | B19: =COUNTIF('Tender Data'!J:J,"*Metropolitan Trading*") -> 0 | C19: =COUNTIFS('Tender Data'!M:M,"Information service activities",'Tender Data'!J:J,"*Metropolitan Trading*")+COUNTIFS('Tender Data'!M:M,"Information and communication",'Tender Data'!J:J,"*Metropolitan Trading*") -> 0 | D19: =COUNTIFS('Tender Data'!J:J,"*Metropolitan Trading*",'Tender Data'!G:G,"Request for Quotation") -> 0
A20: Nelson Mandela Bay MM | B20: =COUNTIF('Tender Data'!J:J,"*Nelson Mandela Bay*") -> 0 | C20: =COUNTIFS('Tender Data'!M:M,"Information service activities",'Tender Data'!J:J,"*Nelson Mandela Bay*")+COUNTIFS('Tender Data'!M:M,"Information and communication",'Tender Data'!J:J,"*Nelson Mandela Bay*") -> 0 | D20: =COUNTIFS('Tender Data'!J:J,"*Nelson Mandela Bay*",'Tender Data'!G:G,"Request for Quotation") -> 0
A21: Buffalo City MM | B21: =COUNTIF('Tender Data'!J:J,"*Buffalo City*") -> 0 | C21: =COUNTIFS('Tender Data'!M:M,"Information service activities",'Tender Data'!J:J,"*Buffalo City*")+COUNTIFS('Tender Data'!M:M,"Information and communication",'Tender Data'!J:J,"*Buffalo City*") -> 0 | D21: =COUNTIFS('Tender Data'!J:J,"*Buffalo City*",'Tender Data'!G:G,"Request for Quotation") -> 0
A22: EC DPW | B22: =COUNTIF('Tender Data'!J:J,"*Eastern Cape*Public Works*") -> 2 | C22: =COUNTIFS('Tender Data'!M:M,"Information service activities",'Tender Data'!J:J,"*Eastern Cape*Public Works*")+COUNTIFS('Tender Data'!M:M,"Information and communication",'Tender Data'!J:J,"*Eastern Cape*Public Works*") -> 0 | D22: =COUNTIFS('Tender Data'!J:J,"*Eastern Cape*Public Works*",'Tender Data'!G:G,"Request for Quotation") -> 1
A23: DEL | B23: =COUNTIF('Tender Data'!J:J,"*Labour*") -> 0 | C23: =COUNTIFS('Tender Data'!M:M,"Information service activities",'Tender Data'!J:J,"*Labour*")+COUNTIFS('Tender Data'!M:M,"Information and communication",'Tender Data'!J:J,"*Labour*") -> 0 | D23: =COUNTIFS('Tender Data'!J:J,"*Labour*",'Tender Data'!G:G,"Request for Quotation") -> 0
A24: SIU | B24: =COUNTIF('Tender Data'!J:J,"Special Investigations Unit*") -> 0 | C24: =COUNTIFS('Tender Data'!M:M,"Information service activities",'Tender Data'!J:J,"Special Investigations Unit*")+COUNTIFS('Tender Data'!M:M,"Information and communication",'Tender Data'!J:J,"Special Investigations Unit*") -> 0 | D24: =COUNTIFS('Tender Data'!J:J,"Special Investigations Unit*",'Tender Data'!G:G,"Request for Quotation") -> 0
A25: GDoH | B25: =COUNTIF('Tender Data'!J:J,"*Gauteng*Health*") -> 0 | C25: =COUNTIFS('Tender Data'!M:M,"Information service activities",'Tender Data'!J:J,"*Gauteng*Health*")+COUNTIFS('Tender Data'!M:M,"Information and communication",'Tender Data'!J:J,"*Gauteng*Health*") -> 0 | D25: =COUNTIFS('Tender Data'!J:J,"*Gauteng*Health*",'Tender Data'!G:G,"Request for Quotation") -> 0
A26: DIRCO | B26: =COUNTIF('Tender Data'!J:J,"*International Relation*") -> 0 | C26: =COUNTIFS('Tender Data'!M:M,"Information service activities",'Tender Data'!J:J,"*International Relation*")+COUNTIFS('Tender Data'!M:M,"Information and communication",'Tender Data'!J:J,"*International Relation*") -> 0 | D26: =COUNTIFS('Tender Data'!J:J,"*International Relation*",'Tender Data'!G:G,"Request for Quotation") -> 0
A27: CP JHB | B27: =COUNTIF('Tender Data'!J:J,"*Joburg Property*") -> 0 | C27: =COUNTIFS('Tender Data'!M:M,"Information service activities",'Tender Data'!J:J,"*Joburg Property*")+COUNTIFS('Tender Data'!M:M,"Information and communication",'Tender Data'!J:J,"*Joburg Property*") -> 0 | D27: =COUNTIFS('Tender Data'!J:J,"*Joburg Property*",'Tender Data'!G:G,"Request for Quotation") -> 0
A28: W JHB | B28: =COUNTIF('Tender Data'!J:J,"*Johannesburg Water*") -> 11 | C28: =COUNTIFS('Tender Data'!M:M,"Information service activities",'Tender Data'!J:J,"*Johannesburg Water*")+COUNTIFS('Tender Data'!M:M,"Information and communication",'Tender Data'!J:J,"*Johannesburg Water*") -> 0 | D28: =COUNTIFS('Tender Data'!J:J,"*Johannesburg Water*",'Tender Data'!G:G,"Request for Quotation") -> 11
B29: =SUM(B4:B28) -> 39 | C29: =SUM(C4:C28) -> 2 | D29: =SUM(D4:D28) -> 20
