Workbook

Sheet Tender Data
A1: REPORT_DATE | B1: RECORD_ID | C1: TENDER_ID | D1: PUBLICATION_DATE | E1: CLOSING_DATE | F1: CLOSING_TIME | G1: TENDER_TYPE | H1: TENDER_DESCRIPTION | I1: TENDER_SOURCE | J1: DEPARTMENT | K1: PROVINCE | L1: ESUBMISSION | M1: CATEGORY | N1: IS_THERE_A_BRIEFING_SESSION | O1: COMPULSORY_BRIEFING | P1: BRIEFING_SESSION_VENUE | Q1: LINK | R1: SOE | S1: COST_OF_SALES_ESTIMATE | T1: CAPABILITY_AVAILABLE | U1: CAPABILITY_GROUP | V1: REQUIREMENTS
A2: 46191 | B2: 502 | C2: CO 26/12 O | D2: 46191 | E2: 46230 | F2: 12:00 | G2: Request for Bid(Open-Tender) | H2: Provision of Grounds and Gardening Services at Majuba TVET College for a period of 5 Years | I2: ETENDERS.GOV.ZA | J2: Majuba Tvet college | K2: KwaZulu-Natal | L2: No | M2: Other service activities | N2: Yes | O2: Yes | P2: Newcastle Training Centre Hall, 2 HJ Van Eck Avenue, Newcastle | Q2: https://www.etenders.gov.za/home/Download/?blobName=1debbfd3-bfd5-48cc-9819-dab8ebf24933.pdf&downloadedFileName=Advert%20for%20PROVISION%20OF%20GROUND%20AND%20GARDENING%20SERVICES%20AT%20MAJUBA%20TVET%20COLLEGE%20SITES%20FOR%20THE%20PERIOD%20OF%20(05)%20YEARS.pdf
A3: 46191 | B3: 501 | C3: IT 26/03 C | D3: 46191 | E3: 46230 | F3: 12:00 | G3: Request for Bid(Open-Tender) | H3: Provision of Endpoint Protection and XDR Security Solution at Majuba TVET College for the period of five (05) Years | I3: ETENDERS.GOV.ZA | J3: Majuba Tvet college | K3: KwaZulu-Natal | L3: No | M3: Information and communication | N3: Yes | O3: Yes | P3: Virtual meeting - the link will be shared with service providers that requested for the document | Q3: https://www.etenders.gov.za/home/Download/?blobName=3e0a07c5-0aab-491e-8cd4-3b631e78b5b1.pdf&downloadedFileName=Advert%20for%20Provision%20of%20internet%20services%20-%20End%20Point-%203%20Tier.pdf
A4: 46191 | B4: 500 | C4: GMT061/25-26 | D4: 46191 | E4: 46230 | F4: 12:00 | G4: Request for Bid(Open-Tender) | H4: Appointment of a Panel of Contractors to attend to Plumbing Related Services for Municipal Buildings and Facilities, Informal Settlement Areas and Indigent Households, as and when required, for a period of three (3) years from date of appointment until 30 June 2029 | I4: ETENDERS.GOV.ZA | J4: George Municipality | K4: Western Cape | L4: No | M4: Other service activities | N4: Yes | O4: Yes | P4: Conference Hall at George Municipality’s Civic Centre, York Street, George | Q4: https://www.etenders.gov.za/home/Download/?blobName=822effce-63d3-4ef3-b75c-03cdcac572ce.pdf&downloadedFileName=GMT061%20of%2025-26%20Tender%20document_18%20June%202026_%20Final.pdf
A5: 46191 | B5: 499 | C5: NKO10/2026 | D5: 46191 | E5: 46234 | F5: 12:00 | G5: Request for Bid(Open-Tender) | H5: APPOINTMENT OF A SUITABLE SERVICE PROVIDER FOR SUPPLY AND DELIVERY OF PROTECTIVE CLOTHING AND RELATED ITEMS FOR NKOMAZI LOCAL MUNICIPALITY FOR A PERIOD OF THREE YEARS (36 MONTHS) | I5: ETENDERS.GOV.ZA | J5: Nkomazi Local Municipality | K5: Mpumalanga | L5: No | M5: Supplies: Clothing/Textiles/Footwear | N5: Yes | O5: Yes | P5: Municipal Town Hall (Kobwa), Fish Eagle, Malalane | Q5: https://www.etenders.gov.za/home/Download/?blobName=f2432ad0-77b3-4217-aace-6ab28d55ed7a.pdf&downloadedFileName=NKO%2010%202026.pdf
A6: 46191 | B6: 498 | C6: IT 26/03 O | D6: 46191 | E6: 46226 | F6: 12:00 | G6: Request for Bid(Open-Tender) | H6: Provision of Internet Services at Majuba TVET College for the period of five(05) Years | I6: ETENDERS.GOV.ZA | J6: Majuba Tvet college | K6: KwaZulu-Natal | L6: No | M6: Information and communication | N6: Yes | O6: Yes | P6: 83 Allen Street, Newcastle | Q6: https://www.etenders.gov.za/home/Download/?blobName=aa42ef56-627e-43ee-8472-b8b52e5ca98b.pdf&downloadedFileName=Advert%20for%20Provision%20of%20internet%20services%20-%20End%20Point-%203%20Tier.pdf
A7: 46191 | B7: 497 | C7: IT 26/02 O | D7: 46191 | E7: 46226 | F7: 12:00 | G7: Request for Bid(Open-Tender) | H7: Provision of 3 Tier Virtual Environment at Majuba TVET College for the Period of (05) Five Years | I7: ETENDERS.GOV.ZA | J7: Majuba Tvet college | K7: KwaZulu-Natal | L7: No | M7: Information and communication | N7: Yes | O7: Yes | P7: 83 Allen Street, Newcastle | Q7: https://www.etenders.gov.za/home/Download/?blobName=ab8110d3-d32a-4e46-9514-4dade2be3b29.pdf&downloadedFileName=Advert%20for%20Provision%20of%20internet%20services%20-%20End%20Point-%203%20Tier.pdf
A8: 46191 | B8: 496 | C8: MDM 2025/26 -54 | D8: 46191 | E8: 46225 | F8: 12:00 | G8: Request for Bid(Open-Tender) | H8: Giyani Water Reticulation Phase 2A(Contract 014)-Mushiyani Water Reticulation | I8: ETENDERS.GOV.ZA | J8: Mopani District Municipality | K8: Limpopo | L8: No | M8: Civil engineering | N8: No | O8: No | P8: N/A | Q8: https://www.etenders.gov.za/home/Download/?blobName=3de493a7-77b0-4082-93f7-5392f24917ed.pdf&downloadedFileName=Giyani%20Water%20Reticulation%20to%20Villages%20Phase%202A%20-%20Final%20advert%20.pdf
A9: 46191 | B9: 495 | C9: MDM 2025/26 -55 | D9: 46191 | E9: 46225 | F9: 12:00 | G9: Request for Bid(Open-Tender) | H9: Giyani Water Reticulation Phase 2A(Contract 015)-Nsavulani Water Reticulation | I9: ETENDERS.GOV.ZA | J9: Mopani District Municipality | K9: Limpopo | L9: No | M9: Civil engineering | N9: No | O9: No | P9: N/A | Q9: https://www.etenders.gov.za/home/Download/?blobName=ff75eedc-33dd-4422-ad80-c8b5c3edd20d.pdf&downloadedFileName=Giyani%20Water%20Reticulation%20to%20Villages%20Phase%202A%20-%20Final%20advert%20.pdf
A10: 46191 | B10: 494 | C10: MDM 2025/26 -56 | D10: 46191 | E10: 46225 | F10: 12:00 | G10: Request for Bid(Open-Tender) | H10: Giyani Water Reticulation Phase 2A(Contract 016)-Nwadzekudzeku Water Reticulation | I10: ETENDERS.GOV.ZA | J10: Mopani District Municipality | K10: Limpopo | L10: No | M10: Civil engineering | N10: No | O10: No | P10: N/A | Q10: https://www.etenders.gov.za/home/Download/?blobName=6c20d68c-60b4-4bd6-bec6-d223d4334480.pdf&downloadedFileName=Giyani%20Water%20Reticulation%20to%20Villages%20Phase%202A%20-%20Final%20advert%20.pdf
A11: 46191 | B11: 493 | C11: MDM 2025/26 -57 | D11: 46191 | E11: 46225 | F11: 12:00 | G11: Request for Bid(Open-Tender) | H11: Giyani Water Reticulation Phase 2A(Contract 017)-Phlaubeni Water Reticulation | I11: ETENDERS.GOV.ZA | J11: Mopani District Municipality | K11: Limpopo | L11: No | M11: Civil engineering | N11: No | O11: No | P11: N/A | Q11: https://www.etenders.gov.za/home/Download/?blobName=e0fd5d6a-ebc0-4d41-8d0b-e7da53144af0.pdf&downloadedFileName=Giyani%20Water%20Reticulation%20to%20Villages%20Phase%202A%20-%20Final%20advert%20.pdf
A12: 46191 | B12: 492 | C12: MDM 2025/26 -58 | D12: 46191 | E12: 46225 | F12: 12:00 | G12: Request for Bid(Open-Tender) | H12: Giyani Water Reticulation Phase 2A(Contract 018)-Vuhehli Water Reticulation Contract B | I12: ETENDERS.GOV.ZA | J12: Mopani District Municipality | K12: Limpopo | L12: No | M12: Civil engineering | N12: No | O12: No | P12: N/A | Q12: https://www.etenders.gov.za/home/Download/?blobName=0d05656e-3662-4857-adb5-1edf132c6906.pdf&downloadedFileName=Giyani%20Water%20Reticulation%20to%20Villages%20Phase%202A%20-%20Final%20advert%20.pdf
A13: 46191 | B13: 491 | C13: MDM 2025/26 -59 | D13: 46191 | E13: 46225 | F13: 12:00 | G13: Request for Bid(Open-Tender) | H13: Giyani Water Reticulation Phase 2A(Contract 019)-Xikhumba Water Reticulation Contract A | I13: ETENDERS.GOV.ZA | J13: Mopani District Municipality | K13: Limpopo | L13: No | M13: Civil engineering | N13: No | O13: No | P13: N/A | Q13: https://www.etenders.gov.za/home/Download/?blobName=6259c7a5-5913-45da-ac0a-0c6715b34390.pdf&downloadedFileName=Giyani%20Water%20Reticulation%20to%20Villages%20Phase%202A%20-%20Final%20advert%20.pdf
... A337: 46194 | B337: 167 | C337: Table 01 | D337: 46194 | E337: 46198 | F337: 10:00 | G337: Request for Quotation | H337: Supply and delivery of Boardroom table | I337: ETENDERS.GOV.ZA | J337: South African Nuclear Energy Corporation Limited | K337: North West | L337: No | M337: Manufacture of furniture | N337: No | O337: No | P337: N/A | Q337: https://www.etenders.gov.za/home/Download/?blobName=f329ec1e-7fd4-4245-af1d-3b7843d6cfaf.docx&downloadedFileName=RFQ%20number%20Tables%2001.docx
A338: 46196 | B338: 166 | C338: BCM5-26/27-0013 | D338: 46196 | E338: 46205 | F338: 11:00 | G338: Request for Quotation | H338: QUOTATION FOR THE APPOINTMENT OF A SUITABLE SERVICE PROVIDER TO RENDER TRAINING SERVICES FOR MASTERING ENGINEERING AND CONSTRUCTION CONTRACTS FOR EIGHT (08) OFFICIALS AS PER SPECIFICATION TO THE EASTERN CAPE DEPARTMENT OF PUBLIC WORKS & INFRASTRUCTURE | I338: ECDPW.GOV.ZA | J338: Eastern Cape Department of Public Works and Infrastructure | K338: Eastern Cape | Q338: https://www.ecdpw.gov.za/wp-content/tender-uploads/bcm5-2627-0013.pdf
A339: 46196 | B339: 165 | C339: SCMU5-26/27-0035 | D339: 46195 | E339: 46210 | F339: 11:00 | G339: Request for Bid | H339: APPOINTMENT OF SERVICE PROVIDER FOR THE PROVISION OF ADEQUATE OFFICE ACCOMMODATION WITHIN MTHATHA CENTRAL BUSINESS DISTRICT - DEPARTMENT OF AGRICULTURE | I339: ECDPW.GOV.ZA | J339: Eastern Cape Department of Public Works and Infrastructure | K339: Eastern Cape | Q339: https://www.ecdpw.gov.za/wp-content/tender-uploads/department-of-agriculture--mthatha-cbd--final-0035.pdf
A340: 46196 | B340: 164 | C340: SCMU5-26/27-0034 | D340: 46195 | E340: 46210 | F340: 11:00 | G340: Request for Bid | H340: APPOINTMENT OF SERVICE PROVIDER FOR THE PROVISION OF ADEQUATE OFFICE ACCOMMODATION WITHIN MTHATHA CENTRAL BUSINESS DISTRICT - DEPARTMENT OF SOCIAL DEVELOPMENT: DISTRICT OFFICE | I340: ECDPW.GOV.ZA | J340: Eastern Cape Department of Public Works and Infrastructure | K340: Eastern Cape | Q340: https://www.ecdpw.gov.za/wp-content/tender-uploads/department-of-social-development-district-office--mthatha-cbd--final-0034.pdf
A341: 46196 | B341: 163 | C341: SCMU5-26/27-0029 | D341: 46195 | E341: 46224 | G341: Request for Bid | H341: TAFALOFEFE HOSPITAL: WATER AND WASTEWATER TREATMENT WORKS | I341: ECDPW.GOV.ZA | J341: Eastern Cape Department of Public Works and Infrastructure | K341: Eastern Cape | Q341: https://www.ecdpw.gov.za/wp-content/tender-uploads/scmu5-2627-0029_-tafalofefe-hospital--water-and-wastewater-treatment-works-.pdf
A342: 46196 | B342: 162 | C342: SCMU5-26/27-0033 | D342: 46195 | E342: 46210 | F342: 11:00 | G342: Request for Bid | H342: APPOINTMENT OF SERVICE PROVIDER FOR THE PROVISION OF ADEQUATE OFFICE ACCOMMODATION WITHIN MTHATHA CENTRAL BUSINESS DISTRICT - DEPARTMENT OF TRANSPORT | I342: ECDPW.GOV.ZA | J342: Eastern Cape Department of Public Works and Infrastructure | K342: Eastern Cape | Q342: https://www.ecdpw.gov.za/wp-content/tender-uploads/department-of-transport--mthatha-cbd--final-0033.pdf
A343: 46196 | B343: 161 | C343: SCMU5-26/27-0032 | D343: 46195 | E343: 46210 | F343: 11:00 | G343: Request for Bid | H343: APPOINTMENT OF SERVICE PROVIDER FOR THE PROVISION OF ADEQUATE OFFICE ACCOMMODATION WITHIN MTHATHA CENTRAL BUSINESS DISTRICT - DEPARTMENT OF SOCIAL DEVELOPMENT: LOCAL AREA OFFICE | I343: ECDPW.GOV.ZA | J343: Eastern Cape Department of Public Works and Infrastructure | K343: Eastern Cape | Q343: https://www.ecdpw.gov.za/wp-content/tender-uploads/department-of-social-development-local-area-office--mthatha-cbd--final-0032.pdf
A344: 46196 | B344: 160 | C344: SCMU5-26/27-0009 | D344: 46195 | G344: Request for Bid | H344: ERRATUM: TERM CONTRACT FOR MANAGEMENT AND ADMINISTERING PAYMENT OF MONTHLYSTIPEND FOR EPWP PARTICIPANTS FOR A PERIOD OF 3 YEARS. | I344: ECDPW.GOV.ZA | J344: Eastern Cape Department of Public Works and Infrastructure | K344: Eastern Cape | Q344: https://www.ecdpw.gov.za/wp-content/tender-uploads/erratum-scmu5-26-27-0009.pdf
A345: 46196 | B345: 159 | C345: SCMU5-26/27-0002 | D345: 46195 | E345: 46238 | F345: 14:00 | G345: Request for Bid | H345: EXPRESSION OF INTEREST FOR A PANEL OF TRAINING PROVIDERS FOR EPWP PROGRAMMES FOR A PERIOD OF THREE (3) YEARS. | I345: ECDPW.GOV.ZA | J345: Eastern Cape Department of Public Works and Infrastructure | K345: Eastern Cape | Q345: https://www.ecdpw.gov.za/wp-content/tender-uploads/0002-9.pdf
A346: 46196 | B346: 158 | C346: SCMU5-26/27-0022 | D346: 46195 | E346: 46224 | F346: 11:00 | G346: Request for Bid | H346: BID FOR THE APPOINTMENT OF SERVICE PROVIDER FOR THE RENEWAL OF SUPPORT AND MAINTENANCE FOR DISASTER RECOVERY AND MANAGED BACKUP SERVICES INCLUDING LICENSES FOR A PERIOD OF 24 MONTHS AS PER SPECIFICATION | I346: ECDPW.GOV.ZA | J346: Eastern Cape Department of Public Works and Infrastructure | K346: Eastern Cape | Q346: https://www.ecdpw.gov.za/wp-content/tender-uploads/scmu5-26-27-0022.pdf
A347: 46196 | B347: 157 | C347: BCM5-26/27-0012 | D347: 46192 | E347: 46196 | F347: 11:00 | G347: Request for Quotation | H347: QUOTATION FOR SUPPLY, DELIVERY AND DECANTING OF DIESEL AT AMALINDA OFFICES AS PER SPECIFICATION FROM DEPARTMENT OF PUBLIC WORKS AND INFRASTRUCTURE | I347: ECDPW.GOV.ZA | J347: Eastern Cape Department of Public Works and Infrastructure | K347: Eastern Cape | Q347: https://www.ecdpw.gov.za/wp-content/tender-uploads/bcm5-26-27-0012-quotation-for-supply-delivery-and-decanting-of-diesel-at---amalinda-offices-as-per-specification-from-department-of-public-works-and-infrastructure-.pdf
A348: 46196 | B348: 156 | C348: ALF5-26/27-0004 | D348: 46192 | E348: 46216 | F348: 11:00 | G348: Request for Bid | H348: TWO YEAR TERM CONTRACT FOR SUPPLY, SERVICING, REPAIRS AND MAINTENANCE OF GENERAL BUILDING FOR ALFRED NZO DISTRICT | I348: ECDPW.GOV.ZA | J348: Eastern Cape Department of Public Works and Infrastructure | K348: Eastern Cape | Q348: https://www.ecdpw.gov.za/wp-content/tender-uploads/alf5-26-27-0004-term-contract-gaeneral-building.pdf
A349: 46196 | B349: 155 | C349: ALF5-26/27-0003 | D349: 46192 | E349: 46213 | F349: 11:00 | G349: Request for Bid | H349: TWO YEAR TERM CONTRACT FOR SUPPLY, SERVICING, REPAIRS AND MAINTENANCE OF PLUMBING AND DRAINAGE EQUIPMENT IN ALFRED NZO DISTRICT | I349: ECDPW.GOV.ZA | J349: Eastern Cape Department of Public Works and Infrastructure | K349: Eastern Cape | Q349: https://www.ecdpw.gov.za/wp-content/tender-uploads/alf5-26-27-0003-term-contract-plumbing.pdf
A350: 46196 | B350: 154 | C350: ALF5-26/27-0002 | D350: 46192 | E350: 46213 | F350: 11:00 | G350: Request for Bid | H350: TWO YEAR TERM CONTRACT FOR SUPPLY, SERVICING, REPAIRS AND MAINTENANCE OF ELECTRICAL EQUIPMENT FOR ALFRED NZO DISTRICT | I350: ECDPW.GOV.ZA | J350: Eastern Cape Department of Public Works and Infrastructure | K350: Eastern Cape | Q350: https://www.ecdpw.gov.za/wp-content/tender-uploads/alf5-26-27-0002-term-contract-electical.pdf
A351: 46194 | B351: 153 | G351: Request for Bid | H351: Training on People 300 Skills Development and Emplyment Equity for 5 Employees | I351: NTABANKULU.GOV.ZA | J351: Ntabankulu Local Municipality | K351: Eastern Cape | Q351: https://www.ntabankulu.gov.za/2026/06/19/training-on-people-300-skills-development-and-emplyment-equity-for-5-employees/
A352: 46194 | B352: 152 | G352: Request for Bid | H352: Bid Invitation for Construction of Tsweleni AR and Gxwaleni Concrete Slab | I352: NTABANKULU.GOV.ZA | J352: Ntabankulu Local Municipality | K352: Eastern Cape | Q352: https://www.ntabankulu.gov.za/2026/06/19/bid-invitation-for-construction-of-tsweleni-ar-and-gxwaleni-concrete-slab/
A353: 46194 | B353: 151 | G353: Request for Bid | H353: CLOSING REGISTER FOR SUPPLY AND DELIVERY OF DIESEL | I353: NTABANKULU.GOV.ZA | J353: Ntabankulu Local Municipality | K353: Eastern Cape | Q353: https://www.ntabankulu.gov.za/2026/06/17/closing-register-for-supply-and-delivery-of-diesel/
A354: 46194 | B354: 150 | G354: Request for Bid | H354: CLOSING REGISTER FOR PROVISION OF SECURITY SERVICES | I354: NTABANKULU.GOV.ZA | J354: Ntabankulu Local Municipality | K354: Eastern Cape | Q354: https://www.ntabankulu.gov.za/2026/06/17/closing-register-for-provision-of-security-services/
A355: 46194 | B355: 149 | G355: Request for Bid | H355: TENDER DOCUMENTFOR 3 YEAR FRAMEWORK CONTRACT OF 05 ROAD MAINTENANCE CONTRACTORS | I355: NTABANKULU.GOV.ZA | J355: Ntabankulu Local Municipality | K355: Eastern Cape | Q355: https://www.ntabankulu.gov.za/2026/06/10/tender-documentfor-3-year-framework-contract-of-05-road-maintenance-contractors/
A356: 46194 | B356: 148 | G356: Request for Bid | H356: Closing Register for Construction of Fenced Mathole Pre-School with Ablution Facilities | I356: NTABANKULU.GOV.ZA | J356: Ntabankulu Local Municipality | K356: Eastern Cape | Q356: https://www.ntabankulu.gov.za/2026/06/03/closing-register-for-construction-of-fenced-mathole-pre-school-with-ablution-facilities/
A357: 46194 | B357: 147 | G357: Request for Bid | H357: Bid Invitation for Electrification and Maintenance Contractors | I357: NTABANKULU.GOV.ZA | J357: Ntabankulu Local Municipality | K357: Eastern Cape | Q357: https://www.ntabankulu.gov.za/2026/05/29/bid-invitation-for-electrification-and-maintenance-contractors/
A358: 46194 | B358: 146 | G358: Request for Bid | H358: Supply and Delivery of Kid’s Learning Gadgets | I358: NTABANKULU.GOV.ZA | J358: Ntabankulu Local Municipality | K358: Eastern Cape | Q358: https://www.ntabankulu.gov.za/2026/05/29/supply-and-delivery-of-kids-learning-gadgets-2/
A359: 46194 | B359: 145 | G359: Request for Bid | H359: Closing Register for Construction of Rwantsana Community Hall | I359: NTABANKULU.GOV.ZA | J359: Ntabankulu Local Municipality | K359: Eastern Cape | Q359: https://www.ntabankulu.gov.za/2026/05/26/closing-register-for-construction-of-rwantsana-community-hall/
A360: 46194 | B360: 144 | G360: Request for Bid | H360: Supply and Delivery of Diesel for 12 Months | I360: NTABANKULU.GOV.ZA | J360: Ntabankulu Local Municipality | K360: Eastern Cape | Q360: https://www.ntabankulu.gov.za/2026/05/21/supply-and-delivery-of-diesel-for-12-months/
A361: 46194 | B361: 143 | G361: Request for Bid | H361: WEBSITE HOSTING AND MAINTENANCE SERVICES FOR UMZIMVUBU LOCAL MUNICIPALITY FOR A PERIOD OF 3 YEARS (1) | I361: UMZIMVUBU.GOV.ZA | J361: Umzimvubu Local Municipality | K361: Eastern Cape | Q361: https://www.umzimvubu.gov.za/wp-content/uploads/2025/02/WEBSITE-HOSTING-AND-MAINTENANCE-SERVICES-FOR-UMZIMVUBU-LOCAL-MUNICIPALITY-FOR-A-PERIOD-OF-3-YEARS-1.pdf
A362: 46194 | B362: 142 | G362: Request for Bid | H362: Umndini Tender Document 1 | I362: UMZIMVUBU.GOV.ZA | J362: Umzimvubu Local Municipality | K362: Eastern Cape | Q362: https://www.umzimvubu.gov.za/wp-content/uploads/2025/02/Umndini-Tender-Document-1.pdf
... A436: 46194 | B436: 68 | G436: Request for Bid | H436: INVITATION TO A TENDER | I436: GREATKEILM.GOV.ZA | J436: Great Kei Local Municipality | K436: Eastern Cape | Q436: https://greatkeilm.gov.za/web/2026/06/09/invitation-to-a-tender-briefing/
A437: 46194 | B437: 67 | C437: RFQ/BTO/09 | G437: Request for Bid | H437: RFQ/BTO/09/2025/26 : Request for Re advertisement for Supply and delivery of Alternative Energy. | I437: GREATKEILM.GOV.ZA | J437: Great Kei Local Municipality | K437: Eastern Cape | Q437: https://greatkeilm.gov.za/web/2026/06/05/rfq-bto-09-2025-26-request-for-re-advertisement-for-supply-and-delivery-of-alternative-energy/
A438: 46194 | B438: 66 | G438: Request for Bid | H438: RFQ/COMM/ 08/2025/26 : Request for Fencing of Kei Mouth Transfer Station. | I438: GREATKEILM.GOV.ZA | J438: Great Kei Local Municipality | K438: Eastern Cape | Q438: https://greatkeilm.gov.za/web/2026/06/01/rfq-comm-08-2025-26-request-for-fencing-of-kei-mouth-transfer-station/
A439: 46194 | B439: 65 | G439: Request for Bid | H439: TENDER: TECH/COMM: 21/2025/26 : Re-Advertisement of Supply. Delivery, Implementation and Commissioning of Server Infrastructure for a period of Three Years | I439: GREATKEILM.GOV.ZA | J439: Great Kei Local Municipality | K439: Eastern Cape | Q439: https://greatkeilm.gov.za/web/2026/05/13/tender-tech-comm-21-2025-26-re-advertisement-of-supply-delivery-implementation-and-commissioning-of-server-infrastructure-for-a-period-of-three-years/
A440: 46194 | B440: 64 | G440: Request for Bid | H440: TENDER: CORP: 01/2025/26 : Panel of Four Service Providers for the Provision of Travel & Accommodation Services for a Period of Two (2) Years. | I440: GREATKEILM.GOV.ZA | J440: Great Kei Local Municipality | K440: Eastern Cape | Q440: https://greatkeilm.gov.za/web/2026/05/13/tender-corp-01-2025-26-panel-of-four-service-providers-for-the-provision-of-travel-accommodation-services-for-a-period-of-two-2-years/
A441: 46194 | B441: 63 | G441: Request for Bid | H441: TECH/QS: 01/2025/26 : Provision for a Panel of Ten (10) Professional Quantity Surveyors for a Period of Three (3) years | I441: GREATKEILM.GOV.ZA | J441: Great Kei Local Municipality | K441: Eastern Cape | Q441: https://greatkeilm.gov.za/web/2026/05/13/tech-qs-01-2025-26-provision-for-a-panel-of-ten-10-professional-quantity-surveyors-for-a-period-of-three-3-years/
A442: 46194 | B442: 62 | G442: Request for Bid | H442: TENDER: CORP: 02/2025/26 : Provision of Vetting Services For a Period of Three Years | I442: GREATKEILM.GOV.ZA | J442: Great Kei Local Municipality | K442: Eastern Cape | Q442: https://greatkeilm.gov.za/web/2026/05/13/tender-corp-02-2025-26-provision-of-vetting-services-for-a-period-of-three-years/
A443: 46194 | B443: 61 | G443: Request for Bid | H443: TENDER: BTO: 22/2025/26 : Provision of Insurance for Municipal Assets and Public Liability for a Period of Three (3) Years | I443: GREATKEILM.GOV.ZA | J443: Great Kei Local Municipality | K443: Eastern Cape | Q443: https://greatkeilm.gov.za/web/2026/05/13/tender-bto-22-2025-26-provision-of-insurance-for-municipal-assets-and-public-liability-for-a-period-of-three-3-years/
A444: 46194 | B444: 60 | G444: Request for Bid | H444: INVITATION TO TENDER FOR THE APPOINTED PANEL FOR THE IMPLEMENTATION OF TURNKEY ELECTRICAL SERVICES | I444: GREATKEILM.GOV.ZA | J444: Great Kei Local Municipality | K444: Eastern Cape | Q444: https://greatkeilm.gov.za/web/2026/04/30/invitation-to-tender-for-the-appointed-panel-for-the-implementation-of-turnkey-electrical-services/
A445: 46194 | B445: 59 | C445: RFQ/BTO/10 | G445: Request for Bid | H445: RFQ/BTO/10/2025/26 : Request for Supply and Delivery of Laptops and Laptop Bags. | I445: GREATKEILM.GOV.ZA | J445: Great Kei Local Municipality | K445: Eastern Cape | Q445: https://greatkeilm.gov.za/web/2026/04/29/rfq-bto-10-2025-26-request-for-supply-and-delivery-of-laptops-and-laptop-bags/
A446: 46194 | B446: 58 | C446: RFQ/BTO/11 | G446: Request for Bid | H446: RFQ/BTO/11/2025/26 : Request for Supply and Installation of Microsoft Exchange Online Licenses. | I446: GREATKEILM.GOV.ZA | J446: Great Kei Local Municipality | K446: Eastern Cape | Q446: https://greatkeilm.gov.za/web/2026/04/29/rfq-bto-11-2025-26-request-for-supply-and-installation-of-microsoft-exchange-online-licenses/
A447: 46194 | B447: 57 | C447: RFQ/STRA/02 | G447: Request for Bid | H447: RFQ/STRA/02/2025/26 : Request for Supply and Delivery of Cropping Projects. | I447: GREATKEILM.GOV.ZA | J447: Great Kei Local Municipality | K447: Eastern Cape | Q447: https://greatkeilm.gov.za/web/2026/04/22/rfq-stra-02-2025-26-request-for-supply-and-delivery-of-cropping-projects/
A448: 46194 | B448: 56 | C448: RFQ/COMM/04 | G448: Request for Bid | H448: RFQ/COMM/04/2025/26 : Request for Re Advertisement for Supply and delivery of Protective Clothing for Community Services Staff. | I448: GREATKEILM.GOV.ZA | J448: Great Kei Local Municipality | K448: Eastern Cape | Q448: https://greatkeilm.gov.za/web/2026/04/10/rfq-comm-04-2025-26-request-for-re-advertisement-for-supply-and-delivery-of-protective-clothing-for-community-services-staff/
A449: 46194 | B449: 55 | G449: Request for Bid | H449: INVITATION – TENDER TECH/CIV:01/2025/26 – Provision for a panel of ten (10) Professional Civil Engineering Consultants for a Period of THREE (3) Years | I449: GREATKEILM.GOV.ZA | J449: Great Kei Local Municipality | K449: Eastern Cape | Q449: https://greatkeilm.gov.za/web/2026/03/09/invitation-tender-tech-civ01-2025-26-provision-for-a-panel-of-ten-10-professional-civil-engineering-consultants-for-a-period-of-three-3-years/
A450: 46194 | B450: 54 | G450: Request for Bid | H450: INVITATION TO TENDER FOR THREE DISASTER ROADS PROJECTS | I450: GREATKEILM.GOV.ZA | J450: Great Kei Local Municipality | K450: Eastern Cape | Q450: https://greatkeilm.gov.za/web/2026/03/06/invitation-to-tender-for-three-disaster-roads-projects/
A451: 46194 | B451: 53 | C451: RFQ/MAY02/2025 | G451: Request for Bid | H451: RFQ/MAY02/2025/26 : Request for Supply and delivery of Banners. | I451: GREATKEILM.GOV.ZA | J451: Great Kei Local Municipality | K451: Eastern Cape | Q451: https://greatkeilm.gov.za/web/2026/03/05/rfq-may02-2025-26-request-for-supply-and-delivery-of-banners/
A452: 46194 | B452: 52 | C452: RFQ/COMM/07 | G452: Request for Bid | H452: RFQ/COMM/07/2025/26 : SUPPLY AND DELIVERY OF PROTECTIVE CLOTHING FOR DFFE PARICIPANTS | I452: GREATKEILM.GOV.ZA | J452: Great Kei Local Municipality | K452: Eastern Cape | Q452: https://greatkeilm.gov.za/web/2026/03/05/rfq-comm-07-2025-26-supply-and-delivery-of-protective-clothing-for-dffe-paricipants/
A453: 46194 | B453: 51 | C453: RFQ/CORP/02 | G453: Request for Bid | H453: RFQ/CORP/02/2025/26 : Request for Supply, delivery and Assembling of a Council Chamber Furniture | I453: GREATKEILM.GOV.ZA | J453: Great Kei Local Municipality | K453: Eastern Cape | Q453: https://greatkeilm.gov.za/web/2026/02/04/rfq-corp-02-2025-26-request-for-supply-delivery-and-assembling-of-a-council-chamber-furniture/
A454: 46194 | B454: 50 | G454: Request for Quotation | H454: Requests for Quotation | I454: GPL.GOV.ZA | J454: Gauteng Provincial Legislature | K454: Gauteng | Q454: https://www.gpl.gov.za/category/business/bids-tenders/advertised-tenders/
A455: 46194 | B455: 49 | C455: SCM/1367/S/2025-2026 | G455: Request for Bid | H455: THE CO- MANAGEMENT AND OPERATION OF MUNICIPAL POUNDValidity period: 90 days | I455: NELSONMANDELABAY.GOV.ZA | J455: Nelson Mandela Bay Metropolitan Municipality | K455: Eastern Cape
A456: 46194 | B456: 48 | C456: SCM/1351/G/2025-2026 | G456: Request for Bid | H456: SUPPLY AND DELIVERY OF WATER METERS, METER INTERFACE UNIT’S AND RELATED MATERIALSValidity period: 90 days | I456: NELSONMANDELABAY.GOV.ZA | J456: Nelson Mandela Bay Metropolitan Municipality | K456: Eastern Cape
A457: 46194 | B457: 47 | C457: SCM/1347/G/2025-2026 | G457: Expression of Interest | H457: EXPRESSION OF INTEREST (EOI) FOR THE SUPPLY AND DELIVERY OF VARIOUS CLEANING MATERIALValidity period: N/A | I457: NELSONMANDELABAY.GOV.ZA | J457: Nelson Mandela Bay Metropolitan Municipality | K457: Eastern Cape
A458: 46194 | B458: 46 | C458: SCM/1346/G/2025-2026 | G458: Request for Bid | H458: SUPPLY AND DELIVERY OF ELECTRICAL PRODUCTS FOR UNDERGROUND AND OVERHEAD SYSTEMSValidity period: 90 days | I458: NELSONMANDELABAY.GOV.ZA | J458: Nelson Mandela Bay Metropolitan Municipality | K458: Eastern Cape
A459: 46194 | B459: 45 | C459: SCM/1360/S/2025-2026 | G459: Expression of Interest | H459: CALL FOR EXPRESSION OF INTEREST FOR REPAIRS AND MAINTENANCE OF VEHICLES FOR A PERIOD OF 36 MONTHSValidity Period: N/A | I459: NELSONMANDELABAY.GOV.ZA | J459: Nelson Mandela Bay Metropolitan Municipality | K459: Eastern Cape
A460: 46194 | B460: 44 | C460: SCM/1046/G/2022-2023 | G460: Request for Bid | H460: SPECIALIZED FIRE FIGHTING VEHICLESValidity period: 90 days | I460: NELSONMANDELABAY.GOV.ZA | J460: Nelson Mandela Bay Metropolitan Municipality | K460: Eastern Cape
A461: 46194 | B461: 43 | C461: SCM/1312/S/2025-2026 | G461: Request for Bid | H461: EXTERNAL HIRE OF REFUSE COMPACTION VEHICLES ON AN "AS AND WHEN REQUIRED BASIS”Compulsory Clarification Meeting: 10 June 2026, Waste Management Boardroom, Harrower Road, Gqeberha at 10:00amValidity period: 90 days | I461: NELSONMANDELABAY.GOV.ZA | J461: Nelson Mandela Bay Metropolitan Municipality | K461: Eastern Cape
A462: 46194 | B462: 42 | C462: SCM/1333/G/2025-2026 | G462: Request for Bid | H462: MANUFACTURE, TESTING, SUPPLY AND DELIVERY OF CSP TRANSFORMERSValidity period: 90 days | I462: NELSONMANDELABAY.GOV.ZA | J462: Nelson Mandela Bay Metropolitan Municipality | K462: Eastern Cape
A463: 46194 | B463: 41 | C463: SCM/1343/C/2025-2026CIDB GRADING: 3GB or HIGHER | G463: Request for Bid | H463: CONSTRUCTION OF WARD 8 COUNCILLORS’ OFFICE FOR A PERIOD OF THREE (3) MONTHSCompulsory Clarification Meeting: 17 June 2026, 61 Longway Avenue, Lorraine, Gqeberha at 11:00 amValidity period: 90 days | I463: NELSONMANDELABAY.GOV.ZA | J463: Nelson Mandela Bay Metropolitan Municipality | K463: Eastern Cape
A464: 46194 | B464: 40 | C464: SCM/1085/C/2022-2023 | G464: Request for Bid | H464: TRIENNIAL CONTRACT FOR PROVISION OF BASIC SANITATION SERVICES: CLUSTERS 1 - 6Validity period: 90 days | I464: NELSONMANDELABAY.GOV.ZA | J464: Nelson Mandela Bay Metropolitan Municipality | K464: Eastern Cape
A465: 46194 | B465: 39 | C465: SCM/1235/S/2024-2025 | G465: Request for Bid | H465: OCCASSIONAL HIRE OF PLANT / TRUCKS FOR RELOCATIONN OF HOUSEHOLDS AND THEIR BELONGINGS FROM STRESSED INFORMAL SETTLEMENTS TO HUMAN SETTLEMENTS PROJECTSValidity period: 90 days | I465: NELSONMANDELABAY.GOV.ZA | J465: Nelson Mandela Bay Metropolitan Municipality | K465: Eastern Cape
A466: 46194 | B466: 38 | C466: SCM/1339/S/2025-2026 | G466: Request for Bid | H466: SUPPLY AND DELIVERY OF TEMPO CONSUMABLES, SPARE PARTS AND MAINTENANCE THEREOF, FOR THE MICROBIOLOGICAL ANALYSES OF FOOD AND ENVIRONMENTAL SAMPLESValidity period: 90 days | I466: NELSONMANDELABAY.GOV.ZA | J466: Nelson Mandela Bay Metropolitan Municipality | K466: Eastern Cape
... A473: 46194 | B473: 31 | C473: SCM/1035/S/2022-2023 | G473: Request for Bid | H473: PROFESSIONAL ENGINEERING SERVICES FOR JACHVLAKTE BULK_x000D_ SEWERAGE: PHASE 1Compulsory Clarification meeting: 19 May 2026, at 10:00am, 6thfloor Boardroom, Fidelity Building, 188 Govan Mbeki Avenue, Port Elizabeth_x000D_ Central, 6001Validity period: 90 | I473: NELSONMANDELABAY.GOV.ZA | J473: Nelson Mandela Bay Metropolitan Municipality | K473: Eastern Cape
A474: 46194 | B474: 30 | C474: UIF 3/26/27 | E474: 46205 | F474: 00:00 | G474: Request for Proposal | H474: Request for proposals for the appointment of a service provider to provide day-to-day cleaning and pest control services at 94 WF Nkomo Building for the Unemployment Insurance Fund for a period of thirty-six (36) Months | I474: LABOUR.GOV.ZA | J474: Department of Employment and Labour | K474: National | Q474: https://www.labour.gov.za/Tenders/Available-Tenders/Lists/Open%20Tenders/Attachments/538/DAY%20TO%20DAY%20AND%20PEST%20CONTROL%20TENDER%20.pdf
A475: 46194 | B475: 29 | C475: UIF3/26/27 | E475: 46205 | F475: 00:00 | G475: Request for Proposal | H475: Request for proposals for the appointment of a service provider to provide day to day cleaning and pest control services at 94 WF Nkomo Building for the Unemployment Insurance Fund for a period of thirty (36) months – Specifications | I475: LABOUR.GOV.ZA | J475: Department of Employment and Labour | K475: National | Q475: https://www.labour.gov.za/Tenders/Available-Tenders/Lists/Open%20Tenders/Attachments/539/DAY%20TO%20DAY%20CLEANING%20%20AND%20PEST%20CONTROL%20SERVICES%20SPECIFICATION%2009%20JUNE%202026.pdf
A476: 46194 | B476: 28 | C476: UIF2/26/27 | E476: 46202 | F476: 00:00 | G476: Request for Proposal | H476: Request for proposals for the appointment of a service provider to provide deep cleaning and hygiene services, materials, and consumable items to the Unemployment Insurance Fund for a period of thirty-six (36) months | I476: LABOUR.GOV.ZA | J476: Department of Employment and Labour | K476: National | Q476: https://www.labour.gov.za/Tenders/Available-Tenders/Lists/Open%20Tenders/Attachments/537/Approved%20Deep%20cleaning%20tender%20specification%20advert%20date%2005%20June%202026.pdf
A477: 46194 | B477: 27 | C477: DRT 02/05/2026 | E477: 46210 | F477: 11:00 AM | G477: Request for Bid | H477: ESTABLISHMENT OF A PANEL OF SERVICE PROVIDERS FOR THE SUPPLY AND DELIVERY OF PERSONAL PROTECTIVE AND SAFETY EQUIPMENT FOR A PERIOD OF THREE YEARS TO THE DEPARTMENT | I477: E-TENDERS.GAUTENG.GOV.ZA | J477: Gauteng Department of Health | K477: Gauteng | N477: Yes | O477: Yes
A478: 46194 | B478: 26 | C478: DRT 01/05/2026 | E478: 46209 | F478: 11:00 AM | G478: Request for Bid | H478: Appointment of a service provider to perform specialized traffic surveying on provincial roads in Gauteng Province for a period of (3) three years. | I478: E-TENDERS.GAUTENG.GOV.ZA | J478: Gauteng Department of Health | K478: Gauteng | N478: Yes | O478: Yes
A479: 46194 | B479: 25 | C479: HLA 4/2/4-2026/01 | E479: 46199 | F479: 11:00 AM | G479: Request for Bid | H479: THE ESTABLISHMENT OF A PRE-APPROVED LIST OF SERVICE PROVIDERS TO PROVIDE EVENTS MANAGEMENT SERVICES FOR THE DEPARTMENT OF HUMAN SETTLEMENTS OVER A PERIOD OF 36 MONTHS | I479: E-TENDERS.GAUTENG.GOV.ZA | J479: Gauteng Department of Health | K479: Gauteng | N479: Yes
A480: 46194 | B480: 24 | C480: GT/GPT/018/2026 | E480: 46199 | F480: 11:00 AM | G480: Request for Bid | H480: APPOINTMENT OF A SERVICE PROVIDER TO RENDER PROFESSIONAL RESEARCH SERVICES FOR THE COMPILATION OF THE MUNICIPAL ECONOMIC REVIEW AND OUTLOOK (MERO) REPORT FOR THE 2026/2027 FINANCIAL YEAR | I480: E-TENDERS.GAUTENG.GOV.ZA | J480: Gauteng Department of Health | K480: Gauteng | N480: Yes
A481: 46194 | B481: 23 | G481: Request for Bid | H481: RFQ – Appointment Of A Suitable Service Provider For The Delivery, Facilitation, Assessment Moderation And Learner Support For The Certificate: Municipal Finance Management (NQF Level: 6) | I481: AMAHLATHI.GOV.ZA | J481: Amahlathi Local Municipality | K481: Eastern Cape | Q481: https://amahlathi.gov.za/event/rfq-appointment-of-a-suitable-service-provider-for-the-delivery-facilitation-assessment-moderation-and-learner-support-for-the-certificate-municipal-finance-management-nqf-level-6/
A482: 46194 | B482: 22 | E482: 46197 | G482: Request for Bid | H482: ADDENDAM: APPOINTMENT OF A PANEL OF SIX (6) CIVIL ENGINEERING PROFESSIONAL SERVICE PROVIDERS FOR PREPARING BUSINESS PLAN, FEASIBILITY STUDY, PRELIMINARY DESIGN, DETAIL DESIGN, TENDER DOCUMENTATION AND CONSTRUCTION MONITORING OF SURFACED PAVED ROADS, BRIDGES AND GRAVEL ROADS PROJECTS FOR A PERIOD OF 3 YEARS. | I482: MATATIELE.GOV.ZA | J482: Matatiele Local Municipality | K482: Eastern Cape | Q482: https://www.matatiele.gov.za/job/addendam-appointment-of-a-panel-of-six-6-civil-engineering-professional-service-providers-for-preparing-business-plan-feasibility-study-preliminary-design-detail-design-tender-documentation-and/
A483: 46194 | B483: 21 | E483: 46197 | G483: Request for Bid | H483: Advert for Bakkies accessories installation-128 | I483: MATATIELE.GOV.ZA | J483: Matatiele Local Municipality | K483: Eastern Cape | Q483: https://www.matatiele.gov.za/job/advert-for-bakkies-accessories-installation-128/
A484: 46194 | B484: 20 | E484: 46197 | G484: Request for Bid | H484: Advert for Printing and Mailing For Consumer Debtors-78 | I484: MATATIELE.GOV.ZA | J484: Matatiele Local Municipality | K484: Eastern Cape | Q484: https://www.matatiele.gov.za/job/advert-for-printing-and-mailing-for-consumer-debtors-78/
A485: 46194 | B485: 19 | E485: 46197 | G485: Request for Bid | H485: Advert for Road signs-127 | I485: MATATIELE.GOV.ZA | J485: Matatiele Local Municipality | K485: Eastern Cape | Q485: https://www.matatiele.gov.za/job/advert-for-road-signs-127/
A486: 46194 | B486: 18 | E486: 46199 | G486: Request for Bid | H486: BID DOCUMENTS: INSTALLATION OF VEHICLE ACCESSORIES ON THREE (3) X SINGLE CABS ELECTRICAL SERVICES BAKKIES. | I486: MATATIELE.GOV.ZA | J486: Matatiele Local Municipality | K486: Eastern Cape | Q486: https://www.matatiele.gov.za/job/bid-documents-installation-of-vehicle-accessories-on-three-3-x-single-cabs-electrical-services-bakkies/
A487: 46194 | B487: 17 | E487: 46199 | G487: Request for Bid | H487: BID DOCUMENT: PRINTING AND MAILING OF CONSUMER DEBTOR’S STATEMENTS. NAME OF THE COMPANY. | I487: MATATIELE.GOV.ZA | J487: Matatiele Local Municipality | K487: Eastern Cape | Q487: https://www.matatiele.gov.za/job/bid-document-printing-and-mailing-of-consumer-debtors-statements-name-of-the-company/
A488: 46194 | B488: 16 | E488: 46199 | G488: Request for Bid | H488: BID DOCUMENT: SUPPLY AND DELIVERY OF ROAD SIGNS. | I488: MATATIELE.GOV.ZA | J488: Matatiele Local Municipality | K488: Eastern Cape | Q488: https://www.matatiele.gov.za/job/bid-document-supply-and-delivery-of-road-signs/
A489: 46194 | B489: 15 | E489: 46203 | G489: Request for Bid | H489: Opening and closing register: Supply and delivery of Fifty-Three (53) Protective clothing/staff uniform for admin and support unit. for | I489: MATATIELE.GOV.ZA | J489: Matatiele Local Municipality | K489: Eastern Cape | Q489: https://www.matatiele.gov.za/job/opening-and-closing-register-supply-and-delivery-of-fifty-three-53-protective-clothing-staff-uniform-for-admin-and-support-unit-for/
A490: 46194 | B490: 14 | E490: 46203 | G490: Request for Bid | H490: OPENING AND CLOSING REGISTER: PROVISION OF ACTIVE DIRECTION AUDIT SOFTWARE. | I490: MATATIELE.GOV.ZA | J490: Matatiele Local Municipality | K490: Eastern Cape | Q490: https://www.matatiele.gov.za/job/opening-and-closing-register-provision-of-active-direction-audit-software/
A491: 46194 | B491: 13 | E491: 46203 | G491: Request for Bid | H491: OPENING AND CLOSING REGISTER: SUPPY AND DELIVER TRAFFIC OFFICERS MOTORCYCLE PPE. | I491: MATATIELE.GOV.ZA | J491: Matatiele Local Municipality | K491: Eastern Cape | Q491: https://www.matatiele.gov.za/job/opening-and-closing-register-suppy-and-deliver-traffic-officers-motorcycle-ppe/
A492: 46194 | B492: 12 | E492: 46211 | G492: Request for Bid | H492: closing register for printing and mailing statements-78 | I492: MATATIELE.GOV.ZA | J492: Matatiele Local Municipality | K492: Eastern Cape | Q492: https://www.matatiele.gov.za/job/closing-register-for-printing-and-mailing-statements-78/
A493: 46194 | B493: 11 | E493: 46211 | G493: Request for Bid | H493: closing register road signs | I493: MATATIELE.GOV.ZA | J493: Matatiele Local Municipality | K493: Eastern Cape | Q493: https://www.matatiele.gov.za/job/closing-register-road-signs/
... A503: 46194 | B503: 1 | E503: 46191 | G503: Request for Bid | H503: INTENTION TO AWARD FOR MULTI FUNCTIONAL PRINTERS | I503: MATATIELE.GOV.ZA | J503: Matatiele Local Municipality | K503: Eastern Cape | Q503: https://www.matatiele.gov.za/?post_type=job_listing&p=24872

Sheet Final
A1: Source | B1: Number of New Tenders | C1: ICT Tenders | D1: RFQs
A2: Report Date | B2: (M) 21/06/2026
A3: eTenders (All) | B3: =COUNTA('Tender Data'!J:J)-1 -> 502 | C3: =COUNTIF('Tender Data'!M:M,"Information service activities")+COUNTIF('Tender Data'!M:M,"Information and communication") -> 8 | D3: =COUNTIF('Tender Data'!G:G,"Request for Quotation") -> 91
A4: Eskom | B4: =COUNTIF('Tender Data'!J:J,"ESKOM") -> 22 | C4: =COUNTIFS('Tender Data'!M:M,"Information service activities",'Tender Data'!J:J,"ESKOM")+COUNTIFS('Tender Data'!M:M,"Information and communication",'Tender Data'!J:J,"ESKOM") -> 0 | D4: =COUNTIFS('Tender Data'!J:J,"ESKOM",'Tender Data'!G:G,"Request for Quotation") -> 1
A5: SITA | B5: =COUNTIF('Tender Data'!J:J,"State Information Technology Agency") -> 0 | C5: =COUNTIFS('Tender Data'!M:M,"Information service activities",'Tender Data'!J:J,"State Information Technology Agency")+COUNTIFS('Tender Data'!M:M,"Information and communication",'Tender Data'!J:J,"State Information Technology Agency") -> 0 | D5: =COUNTIFS('Tender Data'!J:J,"State Information Technology Agency",'Tender Data'!G:G,"Request for Quotation") -> 0
A6: Transnet | B6: =COUNTIF('Tender Data'!J:J,"Transnet*") -> 33 | C6: =COUNTIFS('Tender Data'!M:M,"Information service activities",'Tender Data'!J:J,"Transnet*")+COUNTIFS('Tender Data'!M:M,"Information and communication",'Tender Data'!J:J,"Transnet*") -> 0 | D6: =COUNTIFS('Tender Data'!J:J,"Transnet*",'Tender Data'!G:G,"Request for Quotation") -> 1
A7: JPC | B7: =COUNTIF('Tender Data'!J:J,"*Joburg Property*") -> 0 | C7: =COUNTIFS('Tender Data'!M:M,"Information service activities",'Tender Data'!J:J,"*Joburg Property*")+COUNTIFS('Tender Data'!M:M,"Information and communication",'Tender Data'!J:J,"*Joburg Property*") -> 0 | D7: =COUNTIFS('Tender Data'!J:J,"*Joburg Property*",'Tender Data'!G:G,"Request for Quotation") -> 0
A8: Matatiele LM | B8: =COUNTIF('Tender Data'!J:J,"Matatiele Local Municipality") -> 24 | C8: =COUNTIFS('Tender Data'!M:M,"Information service activities",'Tender Data'!J:J,"Matatiele Local Municipality")+COUNTIFS('Tender Data'!M:M,"Information and communication",'Tender Data'!J:J,"Matatiele Local Municipality") -> 0 | D8: =COUNTIFS('Tender Data'!J:J,"Matatiele Local Municipality",'Tender Data'!G:G,"Request for Quotation") -> 0
A9: Ntabankulu LM | B9: =COUNTIF('Tender Data'!J:J,"Ntabankulu Local Municipality") -> 12 | C9: =COUNTIFS('Tender Data'!M:M,"Information service activities",'Tender Data'!J:J,"Ntabankulu Local Municipality")+COUNTIFS('Tender Data'!M:M,"Information and communication",'Tender Data'!J:J,"Ntabankulu Local Municipality") -> 0 | D9: =COUNTIFS('Tender Data'!J:J,"Ntabankulu Local Municipality",'Tender Data'!G:G,"Request for Quotation") -> 0
A10: Umzimvubu LM | B10: =COUNTIF('Tender Data'!J:J,"Umzimvubu Local Municipality") -> 73 | C10: =COUNTIFS('Tender Data'!M:M,"Information service activities",'Tender Data'!J:J,"Umzimvubu Local Municipality")+COUNTIFS('Tender Data'!M:M,"Information and communication",'Tender Data'!J:J,"Umzimvubu Local Municipality") -> 0 | D10: =COUNTIFS('Tender Data'!J:J,"Umzimvubu Local Municipality",'Tender Data'!G:G,"Request for Quotation") -> 0
A11: Winnie Mandela LM | B11: =COUNTIF('Tender Data'!J:J,"Winnie Madikizela*") -> 2 | C11: =COUNTIFS('Tender Data'!M:M,"Information service activities",'Tender Data'!J:J,"Winnie Madikizela*")+COUNTIFS('Tender Data'!M:M,"Information and communication",'Tender Data'!J:J,"Winnie Madikizela*") -> 0 | D11: =COUNTIFS('Tender Data'!J:J,"Winnie Madikizela*",'Tender Data'!G:G,"Request for Quotation") -> 0
A12: Mnquma LM | B12: =COUNTIF('Tender Data'!J:J,"Mnquma Local Municipality") -> 0 | C12: =COUNTIFS('Tender Data'!M:M,"Information service activities",'Tender Data'!J:J,"Mnquma Local Municipality")+COUNTIFS('Tender Data'!M:M,"Information and communication",'Tender Data'!J:J,"Mnquma Local Municipality") -> 0 | D12: =COUNTIFS('Tender Data'!J:J,"Mnquma Local Municipality",'Tender Data'!G:G,"Request for Quotation") -> 0
A13: Great Kei LM | B13: =COUNTIF('Tender Data'!J:J,"Great Kei Local Municipality") -> 18 | C13: =COUNTIFS('Tender Data'!M:M,"Information service activities",'Tender Data'!J:J,"Great Kei Local Municipality")+COUNTIFS('Tender Data'!M:M,"Information and communication",'Tender Data'!J:J,"Great Kei Local Municipality") -> 0 | D13: =COUNTIFS('Tender Data'!J:J,"Great Kei Local Municipality",'Tender Data'!G:G,"Request for Quotation") -> 0
A14: Amahlathi LM | B14: =COUNTIF('Tender Data'!J:J,"Amahlathi Local Municipality") -> 1 | C14: =COUNTIFS('Tender Data'!M:M,"Information service activities",'Tender Data'!J:J,"Amahlathi Local Municipality")+COUNTIFS('Tender Data'!M:M,"Information and communication",'Tender Data'!J:J,"Amahlathi Local Municipality") -> 0 | D14: =COUNTIFS('Tender Data'!J:J,"Amahlathi Local Municipality",'Tender Data'!G:G,"Request for Quotation") -> 0
A15: Raymond Mhlaba LM | B15: =COUNTIF('Tender Data'!J:J,"Raymond Mhlaba Local Municipality") -> 0 | C15: =COUNTIFS('Tender Data'!M:M,"Information service activities",'Tender Data'!J:J,"Raymond Mhlaba Local Municipality")+COUNTIFS('Tender Data'!M:M,"Information and communication",'Tender Data'!J:J,"Raymond Mhlaba Local Municipality") -> 0 | D15: =COUNTIFS('Tender Data'!J:J,"Raymond Mhlaba Local Municipality",'Tender Data'!G:G,"Request for Quotation") -> 0
A16: JOSHCO | B16: =COUNTIF('Tender Data'!J:J,"*Johannesburg Social Housing*") -> 0 | C16: =COUNTIFS('Tender Data'!M:M,"Information service activities",'Tender Data'!J:J,"*Johannesburg Social Housing*")+COUNTIFS('Tender Data'!M:M,"Information and communication",'Tender Data'!J:J,"*Johannesburg Social Housing*") -> 0 | D16: =COUNTIFS('Tender Data'!J:J,"*Johannesburg Social Housing*",'Tender Data'!G:G,"Request for Quotation") -> 0
A17: GPL | B17: =COUNTIF('Tender Data'!J:J,"Gauteng Provincial Legislature") -> 1 | C17: =COUNTIFS('Tender Data'!M:M,"Information service activities",'Tender Data'!J:J,"Gauteng Provincial Legislature")+COUNTIFS('Tender Data'!M:M,"Information and communication",'Tender Data'!J:J,"Gauteng Provincial Legislature") -> 0 | D17: =COUNTIFS('Tender Data'!J:J,"Gauteng Provincial Legislature",'Tender Data'!G:G,"Request for Quotation") -> 1
A18: RAF | B18: =COUNTIF('Tender Data'!J:J,"Road Accident Fund") -> 4 | C18: =COUNTIFS('Tender Data'!M:M,"Information service activities",'Tender Data'!J:J,"Road Accident Fund")+COUNTIFS('Tender Data'!M:M,"Information and communication",'Tender Data'!J:J,"Road Accident Fund") -> 2 | D18: =COUNTIFS('Tender Data'!J:J,"Road Accident Fund",'Tender Data'!G:G,"Request for Quotation") -> 1
A19: MM Trading Company | B19: =COUNTIF('Tender Data'!J:J,"*Metropolitan Trading*") -> 0 | C19: =COUNTIFS('Tender Data'!M:M,"Information service activities",'Tender Data'!J:J,"*Metropolitan Trading*")+COUNTIFS('Tender Data'!M:M,"Information and communication",'Tender Data'!J:J,"*Metropolitan Trading*") -> 0 | D19: =COUNTIFS('Tender Data'!J:J,"*Metropolitan Trading*",'Tender Data'!G:G,"Request for Quotation") -> 0
A20: Nelson Mandela Bay MM | B20: =COUNTIF('Tender Data'!J:J,"*Nelson Mandela Bay*") -> 19 | C20: =COUNTIFS('Tender Data'!M:M,"Information service activities",'Tender Data'!J:J,"*Nelson Mandela Bay*")+COUNTIFS('Tender Data'!M:M,"Information and communication",'Tender Data'!J:J,"*Nelson Mandela Bay*") -> 0 | D20: =COUNTIFS('Tender Data'!J:J,"*Nelson Mandela Bay*",'Tender Data'!G:G,"Request for Quotation") -> 0
A21: Buffalo City MM | B21: =COUNTIF('Tender Data'!J:J,"*Buffalo City*") -> 1 | C21: =COUNTIFS('Tender Data'!M:M,"Information service activities",'Tender Data'!J:J,"*Buffalo City*")+COUNTIFS('Tender Data'!M:M,"Information and communication",'Tender Data'!J:J,"*Buffalo City*") -> 0 | D21: =COUNTIFS('Tender Data'!J:J,"*Buffalo City*",'Tender Data'!G:G,"Request for Quotation") -> 0
A22: EC DPW | B22: =COUNTIF('Tender Data'!J:J,"*Eastern Cape*Public Works*") -> 13 | C22: =COUNTIFS('Tender Data'!M:M,"Information service activities",'Tender Data'!J:J,"*Eastern Cape*Public Works*")+COUNTIFS('Tender Data'!M:M,"Information and communication",'Tender Data'!J:J,"*Eastern Cape*Public Works*") -> 0 | D22: =COUNTIFS('Tender Data'!J:J,"*Eastern Cape*Public Works*",'Tender Data'!G:G,"Request for Quotation") -> 2
A23: DEL | B23: =COUNTIF('Tender Data'!J:J,"*Labour*") -> 4 | C23: =COUNTIFS('Tender Data'!M:M,"Information service activities",'Tender Data'!J:J,"*Labour*")+COUNTIFS('Tender Data'!M:M,"Information and communication",'Tender Data'!J:J,"*Labour*") -> 0 | D23: =COUNTIFS('Tender Data'!J:J,"*Labour*",'Tender Data'!G:G,"Request for Quotation") -> 1
A24: SIU | B24: =COUNTIF('Tender Data'!J:J,"Special Investigation Unit*") -> 0 | C24: =COUNTIFS('Tender Data'!M:M,"Information service activities",'Tender Data'!J:J,"Special Investigation Unit*")+COUNTIFS('Tender Data'!M:M,"Information and communication",'Tender Data'!J:J,"Special Investigation Unit*") -> 0 | D24: =COUNTIFS('Tender Data'!J:J,"Special Investigation Unit*",'Tender Data'!G:G,"Request for Quotation") -> 0
A25: GDoH | B25: =COUNTIF('Tender Data'!J:J,"*Gauteng*Health*") -> 4 | C25: =COUNTIFS('Tender Data'!M:M,"Information service activities",'Tender Data'!J:J,"*Gauteng*Health*")+COUNTIFS('Tender Data'!M:M,"Information and communication",'Tender Data'!J:J,"*Gauteng*Health*") -> 0 | D25: =COUNTIFS('Tender Data'!J:J,"*Gauteng*Health*",'Tender Data'!G:G,"Request for Quotation") -> 0
A26: DIRCO | B26: =COUNTIF('Tender Data'!J:J,"*International Relation*") -> 0 | C26: =COUNTIFS('Tender Data'!M:M,"Information service activities",'Tender Data'!J:J,"*International Relation*")+COUNTIFS('Tender Data'!M:M,"Information and communication",'Tender Data'!J:J,"*International Relation*") -> 0 | D26: =COUNTIFS('Tender Data'!J:J,"*International Relation*",'Tender Data'!G:G,"Request for Quotation") -> 0
A27: DOJ | B27: =COUNTIF('Tender Data'!J:J,"*Justice*Constitutional*") -> 0 | C27: =COUNTIFS('Tender Data'!M:M,"Information service activities",'Tender Data'!J:J,"*Justice*Constitutional*")+COUNTIFS('Tender Data'!M:M,"Information and communication",'Tender Data'!J:J,"*Justice*Constitutional*") -> 0 | D27: =COUNTIFS('Tender Data'!J:J,"*Justice*Constitutional*",'Tender Data'!G:G,"Request for Quotation") -> 0
A28: CP JHB | B28: =COUNTIF('Tender Data'!J:J,"City Power*Johannesburg*") -> 0 | C28: =COUNTIFS('Tender Data'!M:M,"Information service activities",'Tender Data'!J:J,"City Power*Johannesburg*")+COUNTIFS('Tender Data'!M:M,"Information and communication",'Tender Data'!J:J,"City Power*Johannesburg*") -> 0 | D28: =COUNTIFS('Tender Data'!J:J,"City Power*Johannesburg*",'Tender Data'!G:G,"Request for Quotation") -> 0
A29: W JHB | B29: =COUNTIF('Tender Data'!J:J,"*Johannesburg Water*") -> 15 | C29: =COUNTIFS('Tender Data'!M:M,"Information service activities",'Tender Data'!J:J,"*Johannesburg Water*")+COUNTIFS('Tender Data'!M:M,"Information and communication",'Tender Data'!J:J,"*Johannesburg Water*") -> 0 | D29: =COUNTIFS('Tender Data'!J:J,"*Johannesburg Water*",'Tender Data'!G:G,"Request for Quotation") -> 11
B30: =SUM(B4:B29) -> 246 | C30: =SUM(C4:C29) -> 2 | D30: =SUM(D4:D29) -> 18

Sheet Raw Data
A1: REPORT_DATE | B1: RECORD_ID | C1: TENDER_ID | D1: PUBLICATION_DATE | E1: CLOSING_DATE | F1: CLOSING_TIME | G1: TENDER_TYPE | H1: TENDER_DESCRIPTION | I1: TENDER_SOURCE | J1: DEPARTMENT | K1: PROVINCE | L1: ESUBMISSION | M1: CATEGORY | N1: IS_THERE_A_BRIEFING_SESSION | O1: COMPULSORY_BRIEFING | P1: BRIEFING_SESSION_VENUE | Q1: LINK | R1: SOE | S1: COST_OF_SALES_ESTIMATE | T1: CAPABILITY_AVAILABLE | U1: CAPABILITY_GROUP | V1: REQUIREMENTS
A2: 46191 | B2: 639 | C2: CO 26/12 O | D2: 46191 | E2: 46230 | F2: 12:00 | G2: Request for Bid(Open-Tender) | H2: Provision of Grounds and Gardening Services at Majuba TVET College for a period of 5 Years | I2: ETENDERS.GOV.ZA | J2: Majuba Tvet college | K2: KwaZulu-Natal | L2: No | M2: Other service activities | N2: Yes | O2: Yes | P2: Newcastle Training Centre Hall, 2 HJ Van Eck Avenue, Newcastle | Q2: https://www.etenders.gov.za/home/Download/?blobName=1debbfd3-bfd5-48cc-9819-dab8ebf24933.pdf&downloadedFileName=Advert%20for%20PROVISION%20OF%20GROUND%20AND%20GARDENING%20SERVICES%20AT%20MAJUBA%20TVET%20COLLEGE%20SITES%20FOR%20THE%20PERIOD%20OF%20(05)%20YEARS.pdf
A3: 46191 | B3: 638 | C3: IT 26/03 C | D3: 46191 | E3: 46230 | F3: 12:00 | G3: Request for Bid(Open-Tender) | H3: Provision of Endpoint Protection and XDR Security Solution at Majuba TVET College for the period of five (05) Years | I3: ETENDERS.GOV.ZA | J3: Majuba Tvet college | K3: KwaZulu-Natal | L3: No | M3: Information and communication | N3: Yes | O3: Yes | P3: Virtual meeting - the link will be shared with service providers that requested for the document | Q3: https://www.etenders.gov.za/home/Download/?blobName=3e0a07c5-0aab-491e-8cd4-3b631e78b5b1.pdf&downloadedFileName=Advert%20for%20Provision%20of%20internet%20services%20-%20End%20Point-%203%20Tier.pdf
A4: 46191 | B4: 637 | C4: GMT061/25-26 | D4: 46191 | E4: 46230 | F4: 12:00 | G4: Request for Bid(Open-Tender) | H4: Appointment of a Panel of Contractors to attend to Plumbing Related Services for Municipal Buildings and Facilities, Informal Settlement Areas and Indigent Households, as and when required, for a period of three (3) years from date of appointment until 30 June 2029 | I4: ETENDERS.GOV.ZA | J4: George Municipality | K4: Western Cape | L4: No | M4: Other service activities | N4: Yes | O4: Yes | P4: Conference Hall at George Municipality’s Civic Centre, York Street, George | Q4: https://www.etenders.gov.za/home/Download/?blobName=822effce-63d3-4ef3-b75c-03cdcac572ce.pdf&downloadedFileName=GMT061%20of%2025-26%20Tender%20document_18%20June%202026_%20Final.pdf
A5: 46191 | B5: 636 | C5: NKO10/2026 | D5: 46191 | E5: 46234 | F5: 12:00 | G5: Request for Bid(Open-Tender) | H5: APPOINTMENT OF A SUITABLE SERVICE PROVIDER FOR SUPPLY AND DELIVERY OF PROTECTIVE CLOTHING AND RELATED ITEMS FOR NKOMAZI LOCAL MUNICIPALITY FOR A PERIOD OF THREE YEARS (36 MONTHS) | I5: ETENDERS.GOV.ZA | J5: Nkomazi Local Municipality | K5: Mpumalanga | L5: No | M5: Supplies: Clothing/Textiles/Footwear | N5: Yes | O5: Yes | P5: Municipal Town Hall (Kobwa), Fish Eagle, Malalane | Q5: https://www.etenders.gov.za/home/Download/?blobName=f2432ad0-77b3-4217-aace-6ab28d55ed7a.pdf&downloadedFileName=NKO%2010%202026.pdf
A6: 46191 | B6: 635 | C6: IT 26/03 O | D6: 46191 | E6: 46226 | F6: 12:00 | G6: Request for Bid(Open-Tender) | H6: Provision of Internet Services at Majuba TVET College for the period of five(05) Years | I6: ETENDERS.GOV.ZA | J6: Majuba Tvet college | K6: KwaZulu-Natal | L6: No | M6: Information and communication | N6: Yes | O6: Yes | P6: 83 Allen Street, Newcastle | Q6: https://www.etenders.gov.za/home/Download/?blobName=aa42ef56-627e-43ee-8472-b8b52e5ca98b.pdf&downloadedFileName=Advert%20for%20Provision%20of%20internet%20services%20-%20End%20Point-%203%20Tier.pdf
A7: 46191 | B7: 634 | C7: IT 26/02 O | D7: 46191 | E7: 46226 | F7: 12:00 | G7: Request for Bid(Open-Tender) | H7: Provision of 3 Tier Virtual Environment at Majuba TVET College for the Period of (05) Five Years | I7: ETENDERS.GOV.ZA | J7: Majuba Tvet college | K7: KwaZulu-Natal | L7: No | M7: Information and communication | N7: Yes | O7: Yes | P7: 83 Allen Street, Newcastle | Q7: https://www.etenders.gov.za/home/Download/?blobName=ab8110d3-d32a-4e46-9514-4dade2be3b29.pdf&downloadedFileName=Advert%20for%20Provision%20of%20internet%20services%20-%20End%20Point-%203%20Tier.pdf
A8: 46191 | B8: 633 | C8: MDM 2025/26 -54 | D8: 46191 | E8: 46225 | F8: 12:00 | G8: Request for Bid(Open-Tender) | H8: Giyani Water Reticulation Phase 2A(Contract 014)-Mushiyani Water Reticulation | I8: ETENDERS.GOV.ZA | J8: Mopani District Municipality | K8: Limpopo | L8: No | M8: Civil engineering | N8: No | O8: No | P8: N/A | Q8: https://www.etenders.gov.za/home/Download/?blobName=3de493a7-77b0-4082-93f7-5392f24917ed.pdf&downloadedFileName=Giyani%20Water%20Reticulation%20to%20Villages%20Phase%202A%20-%20Final%20advert%20.pdf
A9: 46191 | B9: 632 | C9: MDM 2025/26 -55 | D9: 46191 | E9: 46225 | F9: 12:00 | G9: Request for Bid(Open-Tender) | H9: Giyani Water Reticulation Phase 2A(Contract 015)-Nsavulani Water Reticulation | I9: ETENDERS.GOV.ZA | J9: Mopani District Municipality | K9: Limpopo | L9: No | M9: Civil engineering | N9: No | O9: No | P9: N/A | Q9: https://www.etenders.gov.za/home/Download/?blobName=ff75eedc-33dd-4422-ad80-c8b5c3edd20d.pdf&downloadedFileName=Giyani%20Water%20Reticulation%20to%20Villages%20Phase%202A%20-%20Final%20advert%20.pdf
A10: 46191 | B10: 631 | C10: MDM 2025/26 -56 | D10: 46191 | E10: 46225 | F10: 12:00 | G10: Request for Bid(Open-Tender) | H10: Giyani Water Reticulation Phase 2A(Contract 016)-Nwadzekudzeku Water Reticulation | I10: ETENDERS.GOV.ZA | J10: Mopani District Municipality | K10: Limpopo | L10: No | M10: Civil engineering | N10: No | O10: No | P10: N/A | Q10: https://www.etenders.gov.za/home/Download/?blobName=6c20d68c-60b4-4bd6-bec6-d223d4334480.pdf&downloadedFileName=Giyani%20Water%20Reticulation%20to%20Villages%20Phase%202A%20-%20Final%20advert%20.pdf
A11: 46191 | B11: 630 | C11: MDM 2025/26 -57 | D11: 46191 | E11: 46225 | F11: 12:00 | G11: Request for Bid(Open-Tender) | H11: Giyani Water Reticulation Phase 2A(Contract 017)-Phlaubeni Water Reticulation | I11: ETENDERS.GOV.ZA | J11: Mopani District Municipality | K11: Limpopo | L11: No | M11: Civil engineering | N11: No | O11: No | P11: N/A | Q11: https://www.etenders.gov.za/home/Download/?blobName=e0fd5d6a-ebc0-4d41-8d0b-e7da53144af0.pdf&downloadedFileName=Giyani%20Water%20Reticulation%20to%20Villages%20Phase%202A%20-%20Final%20advert%20.pdf
A12: 46191 | B12: 629 | C12: MDM 2025/26 -58 | D12: 46191 | E12: 46225 | F12: 12:00 | G12: Request for Bid(Open-Tender) | H12: Giyani Water Reticulation Phase 2A(Contract 018)-Vuhehli Water Reticulation Contract B | I12: ETENDERS.GOV.ZA | J12: Mopani District Municipality | K12: Limpopo | L12: No | M12: Civil engineering | N12: No | O12: No | P12: N/A | Q12: https://www.etenders.gov.za/home/Download/?blobName=0d05656e-3662-4857-adb5-1edf132c6906.pdf&downloadedFileName=Giyani%20Water%20Reticulation%20to%20Villages%20Phase%202A%20-%20Final%20advert%20.pdf
A13: 46191 | B13: 628 | C13: MDM 2025/26 -59 | D13: 46191 | E13: 46225 | F13: 12:00 | G13: Request for Bid(Open-Tender) | H13: Giyani Water Reticulation Phase 2A(Contract 019)-Xikhumba Water Reticulation Contract A | I13: ETENDERS.GOV.ZA | J13: Mopani District Municipality | K13: Limpopo | L13: No | M13: Civil engineering | N13: No | O13: No | P13: N/A | Q13: https://www.etenders.gov.za/home/Download/?blobName=6259c7a5-5913-45da-ac0a-0c6715b34390.pdf&downloadedFileName=Giyani%20Water%20Reticulation%20to%20Villages%20Phase%202A%20-%20Final%20advert%20.pdf
... A337: 46194 | B337: 304 | C337: Table 01 | D337: 46194 | E337: 46198 | F337: 10:00 | G337: Request for Quotation | H337: Supply and delivery of Boardroom table | I337: ETENDERS.GOV.ZA | J337: South African Nuclear Energy Corporation Limited | K337: North West | L337: No | M337: Manufacture of furniture | N337: No | O337: No | P337: N/A | Q337: https://www.etenders.gov.za/home/Download/?blobName=f329ec1e-7fd4-4245-af1d-3b7843d6cfaf.docx&downloadedFileName=RFQ%20number%20Tables%2001.docx
A338: 46196 | B338: 303 | C338: BCM5-26/27-0013 | D338: 46196 | E338: 46205 | F338: 11:00 | G338: Request for Quotation | H338: QUOTATION FOR THE APPOINTMENT OF A SUITABLE SERVICE PROVIDER TO RENDER TRAINING SERVICES FOR MASTERING ENGINEERING AND CONSTRUCTION CONTRACTS FOR EIGHT (08) OFFICIALS AS PER SPECIFICATION TO THE EASTERN CAPE DEPARTMENT OF PUBLIC WORKS & INFRASTRUCTURE | I338: ECDPW.GOV.ZA | J338: Eastern Cape Department of Public Works and Infrastructure | K338: Eastern Cape | Q338: https://www.ecdpw.gov.za/wp-content/tender-uploads/bcm5-2627-0013.pdf
A339: 46196 | B339: 302 | C339: SCMU5-26/27-0035 | D339: 46195 | E339: 46210 | F339: 11:00 | G339: Request for Bid | H339: APPOINTMENT OF SERVICE PROVIDER FOR THE PROVISION OF ADEQUATE OFFICE ACCOMMODATION WITHIN MTHATHA CENTRAL BUSINESS DISTRICT - DEPARTMENT OF AGRICULTURE | I339: ECDPW.GOV.ZA | J339: Eastern Cape Department of Public Works and Infrastructure | K339: Eastern Cape | Q339: https://www.ecdpw.gov.za/wp-content/tender-uploads/department-of-agriculture--mthatha-cbd--final-0035.pdf
A340: 46196 | B340: 301 | C340: SCMU5-26/27-0034 | D340: 46195 | E340: 46210 | F340: 11:00 | G340: Request for Bid | H340: APPOINTMENT OF SERVICE PROVIDER FOR THE PROVISION OF ADEQUATE OFFICE ACCOMMODATION WITHIN MTHATHA CENTRAL BUSINESS DISTRICT - DEPARTMENT OF SOCIAL DEVELOPMENT: DISTRICT OFFICE | I340: ECDPW.GOV.ZA | J340: Eastern Cape Department of Public Works and Infrastructure | K340: Eastern Cape | Q340: https://www.ecdpw.gov.za/wp-content/tender-uploads/department-of-social-development-district-office--mthatha-cbd--final-0034.pdf
A341: 46196 | B341: 300 | C341: SCMU5-26/27-0029 | D341: 46195 | E341: 46224 | G341: Request for Bid | H341: TAFALOFEFE HOSPITAL: WATER AND WASTEWATER TREATMENT WORKS | I341: ECDPW.GOV.ZA | J341: Eastern Cape Department of Public Works and Infrastructure | K341: Eastern Cape | Q341: https://www.ecdpw.gov.za/wp-content/tender-uploads/scmu5-2627-0029_-tafalofefe-hospital--water-and-wastewater-treatment-works-.pdf
A342: 46196 | B342: 299 | C342: SCMU5-26/27-0033 | D342: 46195 | E342: 46210 | F342: 11:00 | G342: Request for Bid | H342: APPOINTMENT OF SERVICE PROVIDER FOR THE PROVISION OF ADEQUATE OFFICE ACCOMMODATION WITHIN MTHATHA CENTRAL BUSINESS DISTRICT - DEPARTMENT OF TRANSPORT | I342: ECDPW.GOV.ZA | J342: Eastern Cape Department of Public Works and Infrastructure | K342: Eastern Cape | Q342: https://www.ecdpw.gov.za/wp-content/tender-uploads/department-of-transport--mthatha-cbd--final-0033.pdf
A343: 46196 | B343: 298 | C343: SCMU5-26/27-0032 | D343: 46195 | E343: 46210 | F343: 11:00 | G343: Request for Bid | H343: APPOINTMENT OF SERVICE PROVIDER FOR THE PROVISION OF ADEQUATE OFFICE ACCOMMODATION WITHIN MTHATHA CENTRAL BUSINESS DISTRICT - DEPARTMENT OF SOCIAL DEVELOPMENT: LOCAL AREA OFFICE | I343: ECDPW.GOV.ZA | J343: Eastern Cape Department of Public Works and Infrastructure | K343: Eastern Cape | Q343: https://www.ecdpw.gov.za/wp-content/tender-uploads/department-of-social-development-local-area-office--mthatha-cbd--final-0032.pdf
A344: 46196 | B344: 297 | C344: SCMU5-26/27-0009 | D344: 46195 | G344: Request for Bid | H344: ERRATUM: TERM CONTRACT FOR MANAGEMENT AND ADMINISTERING PAYMENT OF MONTHLYSTIPEND FOR EPWP PARTICIPANTS FOR A PERIOD OF 3 YEARS. | I344: ECDPW.GOV.ZA | J344: Eastern Cape Department of Public Works and Infrastructure | K344: Eastern Cape | Q344: https://www.ecdpw.gov.za/wp-content/tender-uploads/erratum-scmu5-26-27-0009.pdf
A345: 46196 | B345: 296 | C345: SCMU5-26/27-0002 | D345: 46195 | E345: 46238 | F345: 14:00 | G345: Request for Bid | H345: EXPRESSION OF INTEREST FOR A PANEL OF TRAINING PROVIDERS FOR EPWP PROGRAMMES FOR A PERIOD OF THREE (3) YEARS. | I345: ECDPW.GOV.ZA | J345: Eastern Cape Department of Public Works and Infrastructure | K345: Eastern Cape | Q345: https://www.ecdpw.gov.za/wp-content/tender-uploads/0002-9.pdf
A346: 46196 | B346: 295 | C346: SCMU5-26/27-0022 | D346: 46195 | E346: 46224 | F346: 11:00 | G346: Request for Bid | H346: BID FOR THE APPOINTMENT OF SERVICE PROVIDER FOR THE RENEWAL OF SUPPORT AND MAINTENANCE FOR DISASTER RECOVERY AND MANAGED BACKUP SERVICES INCLUDING LICENSES FOR A PERIOD OF 24 MONTHS AS PER SPECIFICATION | I346: ECDPW.GOV.ZA | J346: Eastern Cape Department of Public Works and Infrastructure | K346: Eastern Cape | Q346: https://www.ecdpw.gov.za/wp-content/tender-uploads/scmu5-26-27-0022.pdf
A347: 46196 | B347: 294 | C347: BCM5-26/27-0012 | D347: 46192 | E347: 46196 | F347: 11:00 | G347: Request for Quotation | H347: QUOTATION FOR SUPPLY, DELIVERY AND DECANTING OF DIESEL AT AMALINDA OFFICES AS PER SPECIFICATION FROM DEPARTMENT OF PUBLIC WORKS AND INFRASTRUCTURE | I347: ECDPW.GOV.ZA | J347: Eastern Cape Department of Public Works and Infrastructure | K347: Eastern Cape | Q347: https://www.ecdpw.gov.za/wp-content/tender-uploads/bcm5-26-27-0012-quotation-for-supply-delivery-and-decanting-of-diesel-at---amalinda-offices-as-per-specification-from-department-of-public-works-and-infrastructure-.pdf
A348: 46196 | B348: 293 | C348: ALF5-26/27-0004 | D348: 46192 | E348: 46216 | F348: 11:00 | G348: Request for Bid | H348: TWO YEAR TERM CONTRACT FOR SUPPLY, SERVICING, REPAIRS AND MAINTENANCE OF GENERAL BUILDING FOR ALFRED NZO DISTRICT | I348: ECDPW.GOV.ZA | J348: Eastern Cape Department of Public Works and Infrastructure | K348: Eastern Cape | Q348: https://www.ecdpw.gov.za/wp-content/tender-uploads/alf5-26-27-0004-term-contract-gaeneral-building.pdf
A349: 46196 | B349: 292 | C349: ALF5-26/27-0003 | D349: 46192 | E349: 46213 | F349: 11:00 | G349: Request for Bid | H349: TWO YEAR TERM CONTRACT FOR SUPPLY, SERVICING, REPAIRS AND MAINTENANCE OF PLUMBING AND DRAINAGE EQUIPMENT IN ALFRED NZO DISTRICT | I349: ECDPW.GOV.ZA | J349: Eastern Cape Department of Public Works and Infrastructure | K349: Eastern Cape | Q349: https://www.ecdpw.gov.za/wp-content/tender-uploads/alf5-26-27-0003-term-contract-plumbing.pdf
A350: 46196 | B350: 291 | C350: ALF5-26/27-0002 | D350: 46192 | E350: 46213 | F350: 11:00 | G350: Request for Bid | H350: TWO YEAR TERM CONTRACT FOR SUPPLY, SERVICING, REPAIRS AND MAINTENANCE OF ELECTRICAL EQUIPMENT FOR ALFRED NZO DISTRICT | I350: ECDPW.GOV.ZA | J350: Eastern Cape Department of Public Works and Infrastructure | K350: Eastern Cape | Q350: https://www.ecdpw.gov.za/wp-content/tender-uploads/alf5-26-27-0002-term-contract-electical.pdf
A351: 46194 | B351: 290 | G351: Request for Bid | H351: Training on People 300 Skills Development and Emplyment Equity for 5 Employees | I351: NTABANKULU.GOV.ZA | J351: Ntabankulu Local Municipality | K351: Eastern Cape | Q351: https://www.ntabankulu.gov.za/2026/06/19/training-on-people-300-skills-development-and-emplyment-equity-for-5-employees/
A352: 46194 | B352: 289 | G352: Request for Bid | H352: Bid Invitation for Construction of Tsweleni AR and Gxwaleni Concrete Slab | I352: NTABANKULU.GOV.ZA | J352: Ntabankulu Local Municipality | K352: Eastern Cape | Q352: https://www.ntabankulu.gov.za/2026/06/19/bid-invitation-for-construction-of-tsweleni-ar-and-gxwaleni-concrete-slab/
A353: 46194 | B353: 288 | G353: Request for Bid | H353: CLOSING REGISTER FOR SUPPLY AND DELIVERY OF DIESEL | I353: NTABANKULU.GOV.ZA | J353: Ntabankulu Local Municipality | K353: Eastern Cape | Q353: https://www.ntabankulu.gov.za/2026/06/17/closing-register-for-supply-and-delivery-of-diesel/
A354: 46194 | B354: 287 | G354: Request for Bid | H354: CLOSING REGISTER FOR PROVISION OF SECURITY SERVICES | I354: NTABANKULU.GOV.ZA | J354: Ntabankulu Local Municipality | K354: Eastern Cape | Q354: https://www.ntabankulu.gov.za/2026/06/17/closing-register-for-provision-of-security-services/
A355: 46194 | B355: 286 | G355: Request for Bid | H355: TENDER DOCUMENTFOR 3 YEAR FRAMEWORK CONTRACT OF 05 ROAD MAINTENANCE CONTRACTORS | I355: NTABANKULU.GOV.ZA | J355: Ntabankulu Local Municipality | K355: Eastern Cape | Q355: https://www.ntabankulu.gov.za/2026/06/10/tender-documentfor-3-year-framework-contract-of-05-road-maintenance-contractors/
A356: 46194 | B356: 285 | G356: Request for Bid | H356: Closing Register for Construction of Fenced Mathole Pre-School with Ablution Facilities | I356: NTABANKULU.GOV.ZA | J356: Ntabankulu Local Municipality | K356: Eastern Cape | Q356: https://www.ntabankulu.gov.za/2026/06/03/closing-register-for-construction-of-fenced-mathole-pre-school-with-ablution-facilities/
A357: 46194 | B357: 284 | G357: Request for Bid | H357: Bid Invitation for Electrification and Maintenance Contractors | I357: NTABANKULU.GOV.ZA | J357: Ntabankulu Local Municipality | K357: Eastern Cape | Q357: https://www.ntabankulu.gov.za/2026/05/29/bid-invitation-for-electrification-and-maintenance-contractors/
A358: 46194 | B358: 283 | G358: Request for Bid | H358: Supply and Delivery of Kid’s Learning Gadgets | I358: NTABANKULU.GOV.ZA | J358: Ntabankulu Local Municipality | K358: Eastern Cape | Q358: https://www.ntabankulu.gov.za/2026/05/29/supply-and-delivery-of-kids-learning-gadgets-2/
A359: 46194 | B359: 282 | G359: Request for Bid | H359: Closing Register for Construction of Rwantsana Community Hall | I359: NTABANKULU.GOV.ZA | J359: Ntabankulu Local Municipality | K359: Eastern Cape | Q359: https://www.ntabankulu.gov.za/2026/05/26/closing-register-for-construction-of-rwantsana-community-hall/
A360: 46194 | B360: 281 | G360: Request for Bid | H360: Supply and Delivery of Diesel for 12 Months | I360: NTABANKULU.GOV.ZA | J360: Ntabankulu Local Municipality | K360: Eastern Cape | Q360: https://www.ntabankulu.gov.za/2026/05/21/supply-and-delivery-of-diesel-for-12-months/
A361: 46194 | B361: 280 | G361: Request for Bid | H361: WEBSITE HOSTING AND MAINTENANCE SERVICES FOR UMZIMVUBU LOCAL MUNICIPALITY FOR A PERIOD OF 3 YEARS (1) | I361: UMZIMVUBU.GOV.ZA | J361: Umzimvubu Local Municipality | K361: Eastern Cape | Q361: https://www.umzimvubu.gov.za/wp-content/uploads/2025/02/WEBSITE-HOSTING-AND-MAINTENANCE-SERVICES-FOR-UMZIMVUBU-LOCAL-MUNICIPALITY-FOR-A-PERIOD-OF-3-YEARS-1.pdf
A362: 46194 | B362: 279 | G362: Request for Bid | H362: Umndini Tender Document 1 | I362: UMZIMVUBU.GOV.ZA | J362: Umzimvubu Local Municipality | K362: Eastern Cape | Q362: https://www.umzimvubu.gov.za/wp-content/uploads/2025/02/Umndini-Tender-Document-1.pdf
... A434: 46194 | B434: 207 | G434: Request for Bid | H434: WMM LM MBD FORMS 2023.pdf | I434: WINNIEMMLM.GOV.ZA | J434: Winnie Madikizela-Mandela Local Municipality | K434: Eastern Cape | Q434: https://www.winniemmlm.gov.za/wp-content/uploads/2023/02/WMM-LM-MBD-FORMS-2023.pdf.pdf
A435: 46194 | B435: 206 | E435: 45985 | G435: Request for Bid | H435: Erratum for Supply and Implementation of Microsoft Office 365 for 36 Months | I435: WINNIEMMLM.GOV.ZA | J435: Winnie Madikizela-Mandela Local Municipality | K435: Eastern Cape | Q435: https://www.winniemmlm.gov.za/wp-content/uploads/2025/10/Erratum-for-Supply-and-Implementation-of-Microsoft-Office-365-for-36-Months.pdf
A436: 46194 | B436: 205 | G436: Request for Bid | H436: Erratum-Procurement of Mobile Contracts for five Years | I436: WINNIEMMLM.GOV.ZA | J436: Winnie Madikizela-Mandela Local Municipality | K436: Eastern Cape | Q436: https://www.winniemmlm.gov.za/wp-content/uploads/2025/08/Erratum-Procurement-of-Mobile-Contracts-for-five-Years.pdf
A437: 46194 | B437: 204 | C437: MNQ/SCM/94/25-26 | D437: 46170 | E437: 46183 | G437: Request for Bid | H437: Training of Municipal Officials on Municipal Finance Management MNQ/SCM/94/25-26 | I437: MNQUMA.GOV.ZA | J437: Mnquma Local Municipality | K437: Eastern Cape | Q437: https://www.mnquma.gov.za/wp-content/uploads/2026/05/BIDMFM.pdf
A438: 46194 | B438: 203 | C438: SCM/MLM/83/25-26 | D438: 46169 | E438: 46176 | G438: Request for Bid | H438: Training of EPWP beneficiaries on occupational health and safety SCM/MLM/83/25-26 | I438: MNQUMA.GOV.ZA | J438: Mnquma Local Municipality | K438: Eastern Cape | Q438: https://www.mnquma.gov.za/wp-content/uploads/2026/05/Bid-Notice-Training-of-EPWP-beneficiaries-on-occupational-health-and-safety.pdf
A439: 46194 | B439: 202 | C439: MNQ/SCM/93/25-26 | D439: 46162 | E439: 46176 | G439: Request for Bid | H439: Supply/ Development, Customization, Delivery and Implementation of an Expected Credit Loss (ECL) Model in Accordance with GRAP 104 (Revised) for a Period of One Year MNQ/SCM/93/25-26 | I439: MNQUMA.GOV.ZA | J439: Mnquma Local Municipality | K439: Eastern Cape | Q439: https://www.mnquma.gov.za/wp-content/uploads/2026/05/Bid-Notice-Supply-and-development-of-Expected-Credit-Loss-ECL-in-accodance-to-GRAP-104-Revised-for-a-period-of-one-year.pdf
A440: 46194 | B440: 201 | C440: SCM/MLM/82/25-26 | D440: 46142 | E440: 46150 | G440: Request for Bid | H440: SUPPLY AND DELIVERY OF GROCERIES FOR OPENING OF NEW OFFICES SCM/MLM/82/25-26 | I440: MNQUMA.GOV.ZA | J440: Mnquma Local Municipality | K440: Eastern Cape | Q440: https://www.mnquma.gov.za/wp-content/uploads/2026/04/ADVERT-GRORICERS-NEW-BUILDING.pdf
A441: 46194 | B441: 200 | C441: MNQ/SCM/92/25-26 | D441: 46140 | E441: 46154 | G441: Request for Bid | H441: HIRING OF FRAME TENTS, DÉCOR, PA SYSTEM, CATERING EQUIPMENT, VIP MOBILE TOILETS, MOBILE FRIDGE, TABLES AND CHAIRS FOR OPENING OF NEW OFFICES MNQ/SCM/92/25-26 | I441: MNQUMA.GOV.ZA | J441: Mnquma Local Municipality | K441: Eastern Cape | Q441: https://www.mnquma.gov.za/wp-content/uploads/2026/04/ADVERT-HIRING-FRAME-28.05.pdf
A442: 46194 | B442: 199 | C442: MNQ/SCM/91/25-26 | D442: 46140 | E442: 46170 | G442: Request for Bid | H442: Repairs and Maintenance of Mnquma LED Screen for a Period of Three (03) Years MNQ/SCM/91/25-26 | I442: MNQUMA.GOV.ZA | J442: Mnquma Local Municipality | K442: Eastern Cape | Q442: https://www.mnquma.gov.za/wp-content/uploads/2026/04/ADVERT-LED-REPAIRS-28.05.pdf
A443: 46194 | B443: 198 | C443: MNQ/SCM/51/25-26 | D443: 46122 | E443: 46154 | G443: Request for Bid | H443: ONLINE PROPERTY VERIFICATION PLATFORM FOR A PERIOD OF THREE YEARS MNQ/SCM/51/25-26 | I443: MNQUMA.GOV.ZA | J443: Mnquma Local Municipality | K443: Eastern Cape | Q443: https://www.mnquma.gov.za/wp-content/uploads/2026/04/Bid-Notice-Online-Property-Verification-Platform-for-a-Period-of-Three-Years.pdf
A444: 46194 | B444: 197 | C444: MNQ/SCM/06/25-26 | D444: 46121 | E444: 46156 | G444: Request for Bid | H444: Rehabilitation of Booi Farm to Khantolo Access Road (Ward 24) MNQ/SCM/06/25-26 | I444: MNQUMA.GOV.ZA | J444: Mnquma Local Municipality | K444: Eastern Cape | Q444: https://www.mnquma.gov.za/wp-content/uploads/2026/04/AD-BOOI-FARM-KHANTOLO-NOTICE-1.pdf
A445: 46194 | B445: 196 | C445: MNQ/SCM/02/26-27 | D445: 46121 | E445: 46156 | G445: Request for Bid | H445: Construction of Sirhosheni to Mahoti Access Road (Ward 22) MNQ/SCM/02/26-27 | I445: MNQUMA.GOV.ZA | J445: Mnquma Local Municipality | K445: Eastern Cape | Q445: https://www.mnquma.gov.za/wp-content/uploads/2026/04/AD-SIRHOSHENI-NOTICE.pdf
A446: 46194 | B446: 195 | C446: MNQ/SCM/04/26-27 | D446: 46121 | E446: 46155 | G446: Request for Bid | H446: Construction of Zixhotyeni Access Road (Ward 23) MNQ/SCM/04/26-27 | I446: MNQUMA.GOV.ZA | J446: Mnquma Local Municipality | K446: Eastern Cape | Q446: https://www.mnquma.gov.za/wp-content/uploads/2026/04/AD-ZIXHOTYENI.pdf
A447: 46194 | B447: 194 | C447: MNQ/SCM/01/26-27 | D447: 46121 | E447: 46155 | G447: Request for Bid | H447: Construction of Sikhefulana, Sikhedana to Kei farm Access Road (Ward 29) MNQ/SCM/01/26-27 | I447: MNQUMA.GOV.ZA | J447: Mnquma Local Municipality | K447: Eastern Cape | Q447: https://www.mnquma.gov.za/wp-content/uploads/2026/04/AD-SIKHEFULANA-NOTICE.pdf
A448: 46194 | B448: 193 | C448: MNQ/SCM/84/25-26 | D448: 46121 | E448: 46141 | G448: Request for Bid | H448: Appointment of a Professional Service Provider for the Development of a storm water management master plan MNQ/SCM/84/25-26 | I448: MNQUMA.GOV.ZA | J448: Mnquma Local Municipality | K448: Eastern Cape | Q448: https://www.mnquma.gov.za/wp-content/uploads/2026/04/AD-STORM-WATER-MASTERPLAN.pdf
... A486: 46194 | B486: 155 | C486: SCM/MLM/72/25-26 | D486: 46050 | E486: 46057 | G486: Request for Bid | H486: Hiring of tents , chairs and generators for roadshows SCM/MLM/72/25-26 | I486: MNQUMA.GOV.ZA | J486: Mnquma Local Municipality | K486: Eastern Cape | Q486: https://www.mnquma.gov.za/wp-content/uploads/2026/01/HIRING-TENTS-AD.pdf
A487: 46194 | B487: 154 | G487: Request for Bid | H487: INVITATION TO A TENDER | I487: GREATKEILM.GOV.ZA | J487: Great Kei Local Municipality | K487: Eastern Cape | Q487: https://greatkeilm.gov.za/web/2026/06/09/invitation-to-a-tender-briefing/
A488: 46194 | B488: 153 | C488: RFQ/BTO/09 | G488: Request for Bid | H488: RFQ/BTO/09/2025/26 : Request for Re advertisement for Supply and delivery of Alternative Energy. | I488: GREATKEILM.GOV.ZA | J488: Great Kei Local Municipality | K488: Eastern Cape | Q488: https://greatkeilm.gov.za/web/2026/06/05/rfq-bto-09-2025-26-request-for-re-advertisement-for-supply-and-delivery-of-alternative-energy/
A489: 46194 | B489: 152 | G489: Request for Bid | H489: RFQ/COMM/ 08/2025/26 : Request for Fencing of Kei Mouth Transfer Station. | I489: GREATKEILM.GOV.ZA | J489: Great Kei Local Municipality | K489: Eastern Cape | Q489: https://greatkeilm.gov.za/web/2026/06/01/rfq-comm-08-2025-26-request-for-fencing-of-kei-mouth-transfer-station/
A490: 46194 | B490: 151 | G490: Request for Bid | H490: TENDER: TECH/COMM: 21/2025/26 : Re-Advertisement of Supply. Delivery, Implementation and Commissioning of Server Infrastructure for a period of Three Years | I490: GREATKEILM.GOV.ZA | J490: Great Kei Local Municipality | K490: Eastern Cape | Q490: https://greatkeilm.gov.za/web/2026/05/13/tender-tech-comm-21-2025-26-re-advertisement-of-supply-delivery-implementation-and-commissioning-of-server-infrastructure-for-a-period-of-three-years/
A491: 46194 | B491: 150 | G491: Request for Bid | H491: TENDER: CORP: 01/2025/26 : Panel of Four Service Providers for the Provision of Travel & Accommodation Services for a Period of Two (2) Years. | I491: GREATKEILM.GOV.ZA | J491: Great Kei Local Municipality | K491: Eastern Cape | Q491: https://greatkeilm.gov.za/web/2026/05/13/tender-corp-01-2025-26-panel-of-four-service-providers-for-the-provision-of-travel-accommodation-services-for-a-period-of-two-2-years/
A492: 46194 | B492: 149 | G492: Request for Bid | H492: TECH/QS: 01/2025/26 : Provision for a Panel of Ten (10) Professional Quantity Surveyors for a Period of Three (3) years | I492: GREATKEILM.GOV.ZA | J492: Great Kei Local Municipality | K492: Eastern Cape | Q492: https://greatkeilm.gov.za/web/2026/05/13/tech-qs-01-2025-26-provision-for-a-panel-of-ten-10-professional-quantity-surveyors-for-a-period-of-three-3-years/
A493: 46194 | B493: 148 | G493: Request for Bid | H493: TENDER: CORP: 02/2025/26 : Provision of Vetting Services For a Period of Three Years | I493: GREATKEILM.GOV.ZA | J493: Great Kei Local Municipality | K493: Eastern Cape | Q493: https://greatkeilm.gov.za/web/2026/05/13/tender-corp-02-2025-26-provision-of-vetting-services-for-a-period-of-three-years/
A494: 46194 | B494: 147 | G494: Request for Bid | H494: TENDER: BTO: 22/2025/26 : Provision of Insurance for Municipal Assets and Public Liability for a Period of Three (3) Years | I494: GREATKEILM.GOV.ZA | J494: Great Kei Local Municipality | K494: Eastern Cape | Q494: https://greatkeilm.gov.za/web/2026/05/13/tender-bto-22-2025-26-provision-of-insurance-for-municipal-assets-and-public-liability-for-a-period-of-three-3-years/
A495: 46194 | B495: 146 | G495: Request for Bid | H495: INVITATION TO TENDER FOR THE APPOINTED PANEL FOR THE IMPLEMENTATION OF TURNKEY ELECTRICAL SERVICES | I495: GREATKEILM.GOV.ZA | J495: Great Kei Local Municipality | K495: Eastern Cape | Q495: https://greatkeilm.gov.za/web/2026/04/30/invitation-to-tender-for-the-appointed-panel-for-the-implementation-of-turnkey-electrical-services/
A496: 46194 | B496: 145 | C496: RFQ/BTO/10 | G496: Request for Bid | H496: RFQ/BTO/10/2025/26 : Request for Supply and Delivery of Laptops and Laptop Bags. | I496: GREATKEILM.GOV.ZA | J496: Great Kei Local Municipality | K496: Eastern Cape | Q496: https://greatkeilm.gov.za/web/2026/04/29/rfq-bto-10-2025-26-request-for-supply-and-delivery-of-laptops-and-laptop-bags/
A497: 46194 | B497: 144 | C497: RFQ/BTO/11 | G497: Request for Bid | H497: RFQ/BTO/11/2025/26 : Request for Supply and Installation of Microsoft Exchange Online Licenses. | I497: GREATKEILM.GOV.ZA | J497: Great Kei Local Municipality | K497: Eastern Cape | Q497: https://greatkeilm.gov.za/web/2026/04/29/rfq-bto-11-2025-26-request-for-supply-and-installation-of-microsoft-exchange-online-licenses/
A498: 46194 | B498: 143 | C498: RFQ/STRA/02 | G498: Request for Bid | H498: RFQ/STRA/02/2025/26 : Request for Supply and Delivery of Cropping Projects. | I498: GREATKEILM.GOV.ZA | J498: Great Kei Local Municipality | K498: Eastern Cape | Q498: https://greatkeilm.gov.za/web/2026/04/22/rfq-stra-02-2025-26-request-for-supply-and-delivery-of-cropping-projects/
A499: 46194 | B499: 142 | C499: RFQ/COMM/04 | G499: Request for Bid | H499: RFQ/COMM/04/2025/26 : Request for Re Advertisement for Supply and delivery of Protective Clothing for Community Services Staff. | I499: GREATKEILM.GOV.ZA | J499: Great Kei Local Municipality | K499: Eastern Cape | Q499: https://greatkeilm.gov.za/web/2026/04/10/rfq-comm-04-2025-26-request-for-re-advertisement-for-supply-and-delivery-of-protective-clothing-for-community-services-staff/
A500: 46194 | B500: 141 | G500: Request for Bid | H500: INVITATION – TENDER TECH/CIV:01/2025/26 – Provision for a panel of ten (10) Professional Civil Engineering Consultants for a Period of THREE (3) Years | I500: GREATKEILM.GOV.ZA | J500: Great Kei Local Municipality | K500: Eastern Cape | Q500: https://greatkeilm.gov.za/web/2026/03/09/invitation-tender-tech-civ01-2025-26-provision-for-a-panel-of-ten-10-professional-civil-engineering-consultants-for-a-period-of-three-3-years/
A501: 46194 | B501: 140 | G501: Request for Bid | H501: INVITATION TO TENDER FOR THREE DISASTER ROADS PROJECTS | I501: GREATKEILM.GOV.ZA | J501: Great Kei Local Municipality | K501: Eastern Cape | Q501: https://greatkeilm.gov.za/web/2026/03/06/invitation-to-tender-for-three-disaster-roads-projects/
A502: 46194 | B502: 139 | C502: RFQ/MAY02/2025 | G502: Request for Bid | H502: RFQ/MAY02/2025/26 : Request for Supply and delivery of Banners. | I502: GREATKEILM.GOV.ZA | J502: Great Kei Local Municipality | K502: Eastern Cape | Q502: https://greatkeilm.gov.za/web/2026/03/05/rfq-may02-2025-26-request-for-supply-and-delivery-of-banners/
A503: 46194 | B503: 138 | C503: RFQ/COMM/07 | G503: Request for Bid | H503: RFQ/COMM/07/2025/26 : SUPPLY AND DELIVERY OF PROTECTIVE CLOTHING FOR DFFE PARICIPANTS | I503: GREATKEILM.GOV.ZA | J503: Great Kei Local Municipality | K503: Eastern Cape | Q503: https://greatkeilm.gov.za/web/2026/03/05/rfq-comm-07-2025-26-supply-and-delivery-of-protective-clothing-for-dffe-paricipants/
A504: 46194 | B504: 137 | C504: RFQ/CORP/02 | G504: Request for Bid | H504: RFQ/CORP/02/2025/26 : Request for Supply, delivery and Assembling of a Council Chamber Furniture | I504: GREATKEILM.GOV.ZA | J504: Great Kei Local Municipality | K504: Eastern Cape | Q504: https://greatkeilm.gov.za/web/2026/02/04/rfq-corp-02-2025-26-request-for-supply-delivery-and-assembling-of-a-council-chamber-furniture/
A505: 46194 | B505: 136 | G505: Request for Quotation | H505: Requests for Quotation | I505: GPL.GOV.ZA | J505: Gauteng Provincial Legislature | K505: Gauteng | Q505: https://www.gpl.gov.za/category/business/bids-tenders/advertised-tenders/
A506: 46194 | B506: 135 | C506: SCM/1367/S/2025-2026 | G506: Request for Bid | H506: THE CO- MANAGEMENT AND OPERATION OF MUNICIPAL POUNDValidity period: 90 days | I506: NELSONMANDELABAY.GOV.ZA | J506: Nelson Mandela Bay Metropolitan Municipality | K506: Eastern Cape
A507: 46194 | B507: 134 | C507: SCM/1351/G/2025-2026 | G507: Request for Bid | H507: SUPPLY AND DELIVERY OF WATER METERS, METER INTERFACE UNIT’S AND RELATED MATERIALSValidity period: 90 days | I507: NELSONMANDELABAY.GOV.ZA | J507: Nelson Mandela Bay Metropolitan Municipality | K507: Eastern Cape
A508: 46194 | B508: 133 | C508: SCM/1347/G/2025-2026 | G508: Expression of Interest | H508: EXPRESSION OF INTEREST (EOI) FOR THE SUPPLY AND DELIVERY OF VARIOUS CLEANING MATERIALValidity period: N/A | I508: NELSONMANDELABAY.GOV.ZA | J508: Nelson Mandela Bay Metropolitan Municipality | K508: Eastern Cape
A509: 46194 | B509: 132 | C509: SCM/1346/G/2025-2026 | G509: Request for Bid | H509: SUPPLY AND DELIVERY OF ELECTRICAL PRODUCTS FOR UNDERGROUND AND OVERHEAD SYSTEMSValidity period: 90 days | I509: NELSONMANDELABAY.GOV.ZA | J509: Nelson Mandela Bay Metropolitan Municipality | K509: Eastern Cape
A510: 46194 | B510: 131 | C510: SCM/1360/S/2025-2026 | G510: Expression of Interest | H510: CALL FOR EXPRESSION OF INTEREST FOR REPAIRS AND MAINTENANCE OF VEHICLES FOR A PERIOD OF 36 MONTHSValidity Period: N/A | I510: NELSONMANDELABAY.GOV.ZA | J510: Nelson Mandela Bay Metropolitan Municipality | K510: Eastern Cape
A511: 46194 | B511: 130 | C511: SCM/1046/G/2022-2023 | G511: Request for Bid | H511: SPECIALIZED FIRE FIGHTING VEHICLESValidity period: 90 days | I511: NELSONMANDELABAY.GOV.ZA | J511: Nelson Mandela Bay Metropolitan Municipality | K511: Eastern Cape
A512: 46194 | B512: 129 | C512: SCM/1312/S/2025-2026 | G512: Request for Bid | H512: EXTERNAL HIRE OF REFUSE COMPACTION VEHICLES ON AN "AS AND WHEN REQUIRED BASIS”Compulsory Clarification Meeting: 10 June 2026, Waste Management Boardroom, Harrower Road, Gqeberha at 10:00amValidity period: 90 days | I512: NELSONMANDELABAY.GOV.ZA | J512: Nelson Mandela Bay Metropolitan Municipality | K512: Eastern Cape
A513: 46194 | B513: 128 | C513: SCM/1333/G/2025-2026 | G513: Request for Bid | H513: MANUFACTURE, TESTING, SUPPLY AND DELIVERY OF CSP TRANSFORMERSValidity period: 90 days | I513: NELSONMANDELABAY.GOV.ZA | J513: Nelson Mandela Bay Metropolitan Municipality | K513: Eastern Cape
A514: 46194 | B514: 127 | C514: SCM/1343/C/2025-2026CIDB GRADING: 3GB or HIGHER | G514: Request for Bid | H514: CONSTRUCTION OF WARD 8 COUNCILLORS’ OFFICE FOR A PERIOD OF THREE (3) MONTHSCompulsory Clarification Meeting: 17 June 2026, 61 Longway Avenue, Lorraine, Gqeberha at 11:00 amValidity period: 90 days | I514: NELSONMANDELABAY.GOV.ZA | J514: Nelson Mandela Bay Metropolitan Municipality | K514: Eastern Cape
A515: 46194 | B515: 126 | C515: SCM/1085/C/2022-2023 | G515: Request for Bid | H515: TRIENNIAL CONTRACT FOR PROVISION OF BASIC SANITATION SERVICES: CLUSTERS 1 - 6Validity period: 90 days | I515: NELSONMANDELABAY.GOV.ZA | J515: Nelson Mandela Bay Metropolitan Municipality | K515: Eastern Cape
A516: 46194 | B516: 125 | C516: SCM/1235/S/2024-2025 | G516: Request for Bid | H516: OCCASSIONAL HIRE OF PLANT / TRUCKS FOR RELOCATIONN OF HOUSEHOLDS AND THEIR BELONGINGS FROM STRESSED INFORMAL SETTLEMENTS TO HUMAN SETTLEMENTS PROJECTSValidity period: 90 days | I516: NELSONMANDELABAY.GOV.ZA | J516: Nelson Mandela Bay Metropolitan Municipality | K516: Eastern Cape
A517: 46194 | B517: 124 | C517: SCM/1339/S/2025-2026 | G517: Request for Bid | H517: SUPPLY AND DELIVERY OF TEMPO CONSUMABLES, SPARE PARTS AND MAINTENANCE THEREOF, FOR THE MICROBIOLOGICAL ANALYSES OF FOOD AND ENVIRONMENTAL SAMPLESValidity period: 90 days | I517: NELSONMANDELABAY.GOV.ZA | J517: Nelson Mandela Bay Metropolitan Municipality | K517: Eastern Cape
... A524: 46194 | B524: 117 | C524: SCM/1035/S/2022-2023 | G524: Request for Bid | H524: PROFESSIONAL ENGINEERING SERVICES FOR JACHVLAKTE BULK_x000D_ SEWERAGE: PHASE 1Compulsory Clarification meeting: 19 May 2026, at 10:00am, 6thfloor Boardroom, Fidelity Building, 188 Govan Mbeki Avenue, Port Elizabeth_x000D_ Central, 6001Validity period: 90 | I524: NELSONMANDELABAY.GOV.ZA | J524: Nelson Mandela Bay Metropolitan Municipality | K524: Eastern Cape
A525: 46194 | B525: 116 | C525: UIF 3/26/27 | E525: 46205 | F525: 00:00 | G525: Request for Proposal | H525: Request for proposals for the appointment of a service provider to provide day-to-day cleaning and pest control services at 94 WF Nkomo Building for the Unemployment Insurance Fund for a period of thirty-six (36) Months | I525: LABOUR.GOV.ZA | J525: Department of Employment and Labour | K525: National | Q525: https://www.labour.gov.za/Tenders/Available-Tenders/Lists/Open%20Tenders/Attachments/538/DAY%20TO%20DAY%20AND%20PEST%20CONTROL%20TENDER%20.pdf
A526: 46194 | B526: 115 | C526: UIF3/26/27 | E526: 46205 | F526: 00:00 | G526: Request for Proposal | H526: Request for proposals for the appointment of a service provider to provide day to day cleaning and pest control services at 94 WF Nkomo Building for the Unemployment Insurance Fund for a period of thirty (36) months – Specifications | I526: LABOUR.GOV.ZA | J526: Department of Employment and Labour | K526: National | Q526: https://www.labour.gov.za/Tenders/Available-Tenders/Lists/Open%20Tenders/Attachments/539/DAY%20TO%20DAY%20CLEANING%20%20AND%20PEST%20CONTROL%20SERVICES%20SPECIFICATION%2009%20JUNE%202026.pdf
A527: 46194 | B527: 114 | C527: UIF2/26/27 | E527: 46202 | F527: 00:00 | G527: Request for Proposal | H527: Request for proposals for the appointment of a service provider to provide deep cleaning and hygiene services, materials, and consumable items to the Unemployment Insurance Fund for a period of thirty-six (36) months | I527: LABOUR.GOV.ZA | J527: Department of Employment and Labour | K527: National | Q527: https://www.labour.gov.za/Tenders/Available-Tenders/Lists/Open%20Tenders/Attachments/537/Approved%20Deep%20cleaning%20tender%20specification%20advert%20date%2005%20June%202026.pdf
A528: 46194 | B528: 113 | C528: JWOPS009/25 | D528: 46192 | E528: 46227 | F528: 10:30am | G528: Request for Bid | H528: Supply, Delivery and Offloading of Consumables on an “As and When” Required Basis for A Period of Thirty-Six (36) Months. | I528: JOHANNESBURGWATER.CO.ZA | J528: Johannesburg Water SOC Ltd | K528: Gauteng | P528: Turbine Hall, 65 Ntemi Piliso Street, Newtown, Auditorium, 7 July 2026 AT 13H00 | Q528: /wp-content/uploads/2026/06/19-JUNE-2026.pdf
A529: 46194 | B529: 112 | C529: JWOPS072/26 | D529: 46192 | E529: 46225 | F529: 10:30am | G529: Request for Bid | H529: Supply, Delivery, Installation, Servicing and Onsite Training for Advanced Pressure Management Equipment and Monitoring System on an “As and When” Required Basis for a Period of Thirty-Six (36) Months | I529: JOHANNESBURGWATER.CO.ZA | J529: Johannesburg Water SOC Ltd | K529: Gauteng | P529: Turbine Hall, 65 Ntemi Piliso Street, Newtown, Auditorium, 7 July at 11H00 | Q529: /wp-content/uploads/2026/06/19-JUNE-2026.pdf
A530: 46194 | B530: 111 | C530: JW14500 | D530: 46192 | E530: 46231 | F530: 10:30am | G530: Request for Bid | H530: UPGRADING AND REPLACEMENT OF WATER AND SEWER PIPELINES IN DE VILLIERS STREET INNERCITY | I530: JOHANNESBURGWATER.CO.ZA | J530: Johannesburg Water SOC Ltd | K530: Gauteng | P530: Turbine Hall, 65 Ntemi Piliso Street, Newtown, Johannesburg, 2001, Auditorium, 2 JULY AT 11H00 | Q530: /wp-content/uploads/2026/06/19-JUNE-2026.pdf
A531: 46194 | B531: 110 | C531: JW14427A | D531: 46192 | E531: 46233 | F531: 10:30am | G531: Request for Bid | H531: GREATER ORANGE FARM PHASE 3A WATER INFRASTRUCTURE UPGRADE AND RENEWAL | I531: JOHANNESBURGWATER.CO.ZA | J531: Johannesburg Water SOC Ltd | K531: Gauteng | P531: 2 James street, Ennerdale, Johannesburg Water Ennerdale Depot, 30 JUNE AT 13H00 | Q531: /wp-content/uploads/2026/06/19-JUNE-2026.pdf
A532: 46194 | B532: 109 | C532: RFP 05/12/2025/CL | E532: 46079 | F532: 11h00 | G532: Request for Bid | H532: Appointment of a Panel of Attorneys/Law Firms to provide the SIU with the Civil Litigation and other legal support services on amongst others, Administrative, Labour and Constitutional Law to all Special Investigating Unit (SIU) Offices, on an “as-and-when required” basis for a period of five (5) years with an option to renew for further 3 years | I532: SIU.ORG.ZA | J532: Special Investigating Unit | K532: National | N532: Yes | O532: No | Q532: https://www.siu.org.za/wp-content/uploads/2025/12/Bid-Document-Panel-of-Legal-Service.pdf
A533: 46194 | B533: 108 | C533: RFP: 04/12/2025/ERM | E533: 46042 | F533: 11:00am | G533: Request for Bid | H533: Appointment of a panel of close armed protection (“CPO”) services on an “as-and-when required” basis for a period from the date of the award to 3 June 2027. | I533: SIU.ORG.ZA | J533: Special Investigating Unit | K533: National | N533: Yes | O533: No | Q533: https://www.siu.org.za/wp-content/uploads/2025/12/RFP-Bid-Document-for-Close-Armed-Protection-services-v2.docx
A534: 46194 | B534: 107 | C534: RFP: 03/11/2025/ERM | E534: 46003 | F534: 11:00am | G534: Request for Bid | H534: Appointment of a service provider for the provision of polygraph examiner training and supply of required polygraph instrument, software and support for a period of three (3) years | I534: SIU.ORG.ZA | J534: Special Investigating Unit | K534: National | N534: Yes | O534: No | Q534: https://www.siu.org.za/wp-content/uploads/2025/11/RFP03-11-2025-ERM-Polygraph-Tender.docx
A535: 46194 | B535: 106 | C535: RFP: 02/09/2025/BP & OD | E535: 45929 | F535: 11h00 | G535: Request for Bid | H535: Provision of Employee Wellness Programme (“EWP”) for a period of three (3) years with an option to extend the contract, at the SIU’s sole discretion, and subject to acceptable performance levels of the appointed service provider, by a period of two (2) years | I535: SIU.ORG.ZA | J535: Special Investigating Unit | K535: National | Q535: https://www.siu.org.za/wp-content/uploads/2025/09/RFP-DOCUMENT-FOR-EMPLOYEE-WELLNESS-PROGRAMME.pdf
A536: 46194 | B536: 105 | C536: RFP: 05/12/2024/ICT | E536: 45685 | F536: 11h00 | G536: Request for Bid | H536: Appointment of Service Provider to develop Data Warehouse with Data Analytics functionality to meet the data and information storage, processing, management, and governance needs of the Special Investigating Unit (SIU) | I536: SIU.ORG.ZA | J536: Special Investigating Unit | K536: National | N536: Yes | O536: No | Q536: https://www.siu.org.za/wp-content/uploads/2024/12/BID-DOCUMENT-_DATA-WAREHOUSE-SPEC.pdf
A537: 46194 | B537: 104 | C537: RFP: 04/12/2024/NI | E537: 45687 | F537: 11h00 | G537: Request for Bid | H537: Appointment of panel of experts: POE.12 – Forensic Accountants Services on an “as-and-when-required” basis for a period of 36 months with an option to renew for a further two years. | I537: SIU.ORG.ZA | J537: Special Investigating Unit | K537: National | Q537: https://www.siu.org.za/wp-content/uploads/2024/12/Panel-of-Experts-Forensic-Accountant.docx
...
